Workbook

Sheet 回答一覧
A1: No | B1: 案件番号 | C1: 案件名 | D1: 回答種別 | E1: 電力会社 | F1: 回答日 | G1: 申込日 | H1: 申込者 | I1: 設置場所 | J1: 放電kW | K1: 充電kW | L1: 電圧 | M1: 変電所 | N1: 配電線/送電線 | O1: 負担金(円) | P1: 税区分 | Q1: 負担金(税込・万円) | R1: 負担金帯 | S1: 負担金の原文 | T1: 保証金(円) | U1: 工期(月) | V1: 工期帯 | W1: 工期の原文 | X1: 運開見込み | Y1: 主な対策工事 | Z1: 上位系統増強 | AA1: 連系条件 | AB1: 有効期限 | AC1: 読取信頼度 | AD1: 未読理由 | AE1: 備考 | AF1: 集計対象 | AG1: 律速・可否メモ | AH1: 自動チェック | AI1: 7月メモ差異 | AJ1: 検証ステータス | AK1: 検証者 | AL1: 検証コメント | AM1: 原本リンク | AN1: ファイル名 | AO1: パス
A2: 1 | B2: 0794 | C2: 0794_三重県名張市瀬古口（PX） | D2: 接続検討回答 | E2: 中部 | F2: 2025-08-18 | G2: 2025-05-28 | H2: 株式会社パワーエックス（受付番号AAD315770609） | I2: 三重県名張市瀬古口１１－４他２筆（発電者名称：瀬古口変電所隣接地蓄電） | J2: 1949 | K2: 1999 | L2: 高圧（高圧版回答書） | M2: 瀬古口変電所 | N2: 瀬古口変電所F35（65ﾈ283～西に約100mより分岐し構内柱と接続） | O2: 3418300 | P2: 税込 | Q2: =IF(O2="","",IF(P2="税抜",O2*1.1,O2)/10000) -> 341.83 | R2: =IF(Q2="","不明",IF(Q2<=500,"〜500万",IF(Q2<=1000,"500〜1,000万",IF(Q2<=3000,"1,000〜3,000万","3,000万〜")))) -> 〜500万 | S2: 工事費負担金総額3,418.3千円（消費税相当額310.8千円を含む）。税抜3,107.6千円＝架空線工事2,955.6千円＋計量設備工事152.0千円。概算工事費も同額。 | T2: 170000 | U2: 6 | V2: =IF(U2="","不明",IF(U2<=6,"〜6ヶ月",IF(U2<=12,"7〜12ヶ月",IF(U2<=24,"13〜24ヶ月","25ヶ月〜")))) -> 〜6ヶ月 | W2: 工事費負担金の入金後 6ヶ月程度（契約手続き期間は含まず） | X2: アクセス設備の運用開始希望日 2027年1月1日（連系可否：可） | Y2: 電柱新設4本、高圧線新設408m、高圧引込線60m（60㎟OCW 送電容量240A）、計量器/VCT・通信端末 | Z2: 上位系統増強工事なし（記載なし） | AA2: ノンファーム型接続適用（出力制御量に影響：西部変電所500/275kV変圧器、中勢変電所275/77kV変圧器、77kV中勢青山線）。基幹系は再給電方式（一定の順序）。PCS力率一定制御（放電/充電とも力率100%）、出力変化速度0→100%で5秒以上・1ステップ10%以下、PCS手動復帰設定、単独運転検出機能設定変更。中勢変電所作業停止時等の抑制。N-1電制本格適用。 | AB2: 接続検討の回答日から1年を経過した場合は契約申込不可 | AC2: high | AE2: 系統連系保証金170千円（消費税等相当額15.4千円を含む）。最大自家消費電力1,999kWをcapacity_kw_chargeに記載。後続の契約申込回答(KK4763)あり（別レコード）。 | AF2: － | AH2: =IF(AD2<>"","未読",IF(AND(D2<>"接続検討回答",D2<>"再接続検討",D2<>"契約申込回答"),"",TRIM(IF(O2="","負担金なし ","")&IF(U2="","工期なし ","")&IF(AND(O2<>"",OR(P2="",P2="不明")),"税区分不明 ","")&IF(AC2="low","信頼度low","")))) | AJ2: 未確認 | AM2: 開く | AN2: 接続検討回答書.pdf | AO2: 11_接続回答/接続検討回答書.pdf
A3: 2 | B3: 0794 | C3: 0794_三重県名張市瀬古口（PX） | D3: 契約申込回答 | E3: 中部 | F3: 2026-04-24 | H3: 株式会社パワーエックス（受付番号KK4763） | I3: 三重県名張市瀬古口11-4 他2筆（発電者名称：株式会社パワーエックス 瀬古口変電所隣接地蓄電所） | J3: 1949 | K3: 1999 | L3: 高圧 | M3: 瀬古口変電所（基幹系変電所：中勢275/77変電所） | N3: 瀬古口変電所F35（65ﾈ28ｱより分岐し構内柱と接続） | O3: 3418334 | P3: 税込 | Q3: =IF(O3="","",IF(P3="税抜",O3*1.1,O3)/10000) -> 341.8334 | R3: =IF(Q3="","不明",IF(Q3<=500,"〜500万",IF(Q3<=1000,"500〜1,000万",IF(Q3<=3000,"1,000〜3,000万","3,000万〜")))) -> 〜500万 | S3: 工事費負担金3,418,334円（消費税等相当額310,757円を含む）。税抜3,107,577円＝架空線工事2,955,582円＋計量設備工事151,995円。既に支払った系統連系保証金を差し引いた額を請求。 | U3: 10 | V3: =IF(U3="","不明",IF(U3<=6,"〜6ヶ月",IF(U3<=12,"7〜12ヶ月",IF(U3<=24,"13〜24ヶ月","25ヶ月〜")))) -> 7〜12ヶ月 | W3: 工事費負担金の入金後 10ヶ月程度（契約手続き期間は含まず。別紙「所要工期について」：架空線・計器・上位系統の工程10カ月） | X3: アクセス設備の運用開始希望日 2026年8月1日（連系可否：可） | Y3: 電柱4本、高圧線1548m、高圧引込線60m（OC-W60mm2 送電容量240A）、計量器・VCT等 | Z3: 上位系統増強工事なし（工程表に上位系統欄あるが工事費計上なし） | AA3: ノンファーム型接続適用（西部変電所500/275kV変圧器、中勢変電所275/77kV変圧器、77kV中勢青山線）。再給電方式。PCS力率一定制御（力率1.00）、PCS手動復帰設定、単独運転検出機能設定変更、保安通信用電話設備要確認。中勢変電所作業停止時等の抑制。N-1電制本格適用。発電側課金：配電用変電所 瀬古口変電所。 | AC3: high | AE3: 接続検討回答（2025-08-18、工期6ヶ月・高圧線408m）からの本回答（連系承諾）。負担金額はほぼ同額だが工期は10ヶ月程度、高圧線数量1548mに変更。14_接続検討要否確認フォルダに追加の要否確認依頼書(2026-05)あり（回答なし）。 | AF3: ○ | AH3: =IF(AD3<>"","未読",IF(AND(D3<>"接続検討回答",D3<>"再接続検討",D3<>"契約申込回答"),"",TRIM(IF(O3="","負担金なし ","")&IF(U3="","工期なし ","")&IF(AND(O3<>"",OR(P3="",P3="不明")),"税区分不明 ","")&IF(AC3="low","信頼度low","")))) | AJ3: 未確認 | AM3: 開く | AN3: 02 契約申込回答書（KK4763）.pdf | AO3: 13_本回答/02 契約申込回答書（KK4763）.pdf
A4: 3 | B4: 0876 | C4: 0876_埼玉県本庄市児玉町入浅見字東日延766（アスソラ） | D4: 接続検討回答 | E4: 東京 | F4: 2025-06-18 | G4: 2025-03-24 | H4: 株式会社パワーエックス（本庄児玉蓄電所） | I4: 埼玉県本庄市児玉町入浅見字東日延766番 | J4: 1998 | K4: 1999 | L4: 6.6kV | M4: 共和変電所（1B, 基幹:新岡部変電所） | N4: 6kV横手線 | O4: 5817700 | P4: 税込 | Q4: =IF(O4="","",IF(P4="税抜",O4*1.1,O4)/10000) -> 581.77 | R4: =IF(Q4="","不明",IF(Q4<=500,"〜500万",IF(Q4<=1000,"500〜1,000万",IF(Q4<=3000,"1,000〜3,000万","3,000万〜")))) -> 500〜1,000万 | S4: 工事費負担金の総額581.77万円(消費税等相当額52.89万円含む)、税抜528.88万円（架空線501.00/通信3.65/計量24.23）。概算工事費総額612.44万円(税込) | T4: 290000 | U4: 5 | V4: =IF(U4="","不明",IF(U4<=6,"〜6ヶ月",IF(U4<=12,"7〜12ヶ月",IF(U4<=24,"13〜24ヶ月","25ヶ月〜")))) -> 〜6ヶ月 | W4: 工事費負担金の入金後 5ヶ月程度（受給契約申込後からは13ヶ月程度） | X4: 希望2026年3月1日 | Y4: 架空引込線アルミ120×3条×5m、開閉器新設2台・撤去2台、変圧器新設1台、VCT・計量器・電力用保安通信設備 | Z4: なし（バンク逆潮流対策は完了済み、上位系統対策0円） | AA4: ノンファーム型接続(新岡部500/154変圧器)、再給電方式、運転力率 遅れ90%一定、N-1電制本格適用、先行事業者の設備対策工事前提 | AB4: 接続検討の回答日から1年を経過した場合は契約申込不可 | AC4: high | AE4: 系統連系保証金290千円(税込)。その後2026-02-02付「系統状況変化による再接続検討のお願い」で空き容量消失、発調申込取下げ→再接続検討(JK25GHZ042932)へ。同一ファイルのコピー(1lqVArpJi7bOcqsjyvYu8iIr6lnAAi9MM)あり | AF4: － | AH4: =IF(AD4<>"","未読",IF(AND(D4<>"接続検討回答",D4<>"再接続検討",D4<>"契約申込回答"),"",TRIM(IF(O4="","負担金なし ","")&IF(U4="","工期なし ","")&IF(AND(O4<>"",OR(P4="",P4="不明")),"税区分不明 ","")&IF(AC4="low","信頼度low","")))) | AJ4: 未確認 | AM4: 開く | AN4: 接続検討の回答について【JK24GHZ024878】.pdf | AO4: 01_接続検討/接続検討の回答について【JK24GHZ024878】.pdf
A5: 4 | B5: 0876 | C5: 0876_埼玉県本庄市児玉町入浅見字東日延766（アスソラ） | D5: その他 | E5: 東京 | F5: 2026-02-02 | H5: 株式会社パワーエックス（本庄児玉蓄電所） | I5: 埼玉県本庄市児玉町入浅見字東日延766番 | P5: 不明 | Q5: =IF(O5="","",IF(P5="税抜",O5*1.1,O5)/10000) | R5: =IF(Q5="","不明",IF(Q5<=500,"〜500万",IF(Q5<=1000,"500〜1,000万",IF(Q5<=3000,"1,000〜3,000万","3,000万〜")))) -> 不明 | T5: 290000 | V5: =IF(U5="","不明",IF(U5<=6,"〜6ヶ月",IF(U5<=12,"7〜12ヶ月",IF(U5<=24,"13〜24ヶ月","25ヶ月〜")))) -> 不明 | AB5: 再接続検討は接続検討回答日から1年以内・同内容なら調査料不要 | AC5: high | AE5: 発調申込受付前の系統確認で空き容量がなくなり再接続検討が必要との通知。発調申込取下げ・保証金返還の案内。保証金額は同フォルダ保証金請求書(2026-01-06, 290,000円税込=263,637+消費税26,363)より | AF5: － | AH5: =IF(AD5<>"","未読",IF(AND(D5<>"接続検討回答",D5<>"再接続検討",D5<>"契約申込回答"),"",TRIM(IF(O5="","負担金なし ","")&IF(U5="","工期なし ","")&IF(AND(O5<>"",OR(P5="",P5="不明")),"税区分不明 ","")&IF(AC5="low","信頼度low","")))) | AJ5: 未確認 | AM5: 開く | AN5: 系統状況変化によるご案内について(JK24GHZ024878).pdf | AO5: 02_本申請/系統状況変化によるご案内について(JK24GHZ024878).pdf
A6: 5 | B6: 0876 | C6: 0876_埼玉県本庄市児玉町入浅見字東日延766（アスソラ） | D6: 再接続検討 | E6: 東京 | F6: 2026-05-07 | G6: 2026-02-13 | H6: 株式会社パワーエックス（本庄児玉蓄電所） | I6: 埼玉県本庄市児玉町入浅見字東日延766番 | J6: 1998 | K6: 1999 | L6: 6.6kV | M6: 共和変電所（3B, 基幹:新岡部変電所） | N6: 6kV阿那志線 | O6: 26239500 | P6: 税込 | Q6: =IF(O6="","",IF(P6="税抜",O6*1.1,O6)/10000) -> 2623.95 | R6: =IF(Q6="","不明",IF(Q6<=500,"〜500万",IF(Q6<=1000,"500〜1,000万",IF(Q6<=3000,"1,000〜3,000万","3,000万〜")))) -> 1,000〜3,000万 | S6: 工事費負担金の総額2,623.95万円(消費税等相当額238.54万円含む)、税抜2,385.41万円（架空線978.35/地中線1,379.70/通信3.13/計量24.23）。概算工事費総額4,557.41万円(税込) | T6: 2623000 | U6: 18 | V6: =IF(U6="","不明",IF(U6<=6,"〜6ヶ月",IF(U6<=12,"7〜12ヶ月",IF(U6<=24,"13〜24ヶ月","25ヶ月〜")))) -> 13〜24ヶ月 | W6: 工事費負担金の入金後 18ヶ月程度（受給契約申込後からは40ヶ月程度）。先行事業者の系統対策工事完了後に本件工事を実施 | X6: 希望2026年3月1日（記載のまま） | Y6: 電柱新設15本/建替10本、高圧線新設1,087m、引込線10m、開閉器新設2台、変圧器新設3台/撤去4台、管路26m・高圧ケーブル142m(CVT325/500)、ミニクラ新設一式、VCT・計量器・保安通信 | Z6: なし（上位系統対策0円、バンク逆潮流対策完了済み） | AA6: ノンファーム型接続(新岡部500/154変圧器)、再給電方式、運転力率 遅れ90%一定、早期連系追加対策(充電制限)は現時点不要、N-1電制本格適用、先行事業者工事前提 | AB6: 接続検討の回答日から1年を経過した場合は契約申込不可 | AC6: high | AE6: 系統状況変化（他事業者申込で空き容量消失）による再接続検討の回答。系統連系保証金2,623千円(税込)。初回(JK24GHZ024878)より負担金・工期とも増加 | AF6: ○ | AH6: =IF(AD6<>"","未読",IF(AND(D6<>"接続検討回答",D6<>"再接続検討",D6<>"契約申込回答"),"",TRIM(IF(O6="","負担金なし ","")&IF(U6="","工期なし ","")&IF(AND(O6<>"",OR(P6="",P6="不明")),"税区分不明 ","")&IF(AC6="low","信頼度low","")))) | AJ6: 未確認 | AM6: 開く | AN6: 接続検討の回答について【JK25GHZ042932】.pdf | AO6: 03_再接続検討/接続検討の回答について【JK25GHZ042932】/接続検討の回答について【JK25GHZ042932】.pdf
A7: 6 | B7: 0916 | C7: 0916_島根県浜田市宇野町1819-1他3筆（エクスパワー） | D7: 接続検討回答 | E7: 中国 | F7: 2025-10-21 | G7: 2025-07-22 | H7: 株式会社パワーエックス（PX浜田市宇野町1819-1蓄電所, 受付番号G松江320） | I7: 島根県浜田市宇野町1819番1他4筆 | J7: 1994 | K7: 1999 | L7: 6.6kV | M7: 下府変電所（配電用）／基幹:西島根変電所 | N7: 6kV国分線 上府(支)78H7号柱より分岐（国分線一部を生湯線へ、生湯線一部を長沢線へ系統変更） | O7: 32000000 | P7: 税込 | Q7: =IF(O7="","",IF(P7="税抜",O7*1.1,O7)/10000) -> 3200 | R7: =IF(Q7="","不明",IF(Q7<=500,"〜500万",IF(Q7<=1000,"500〜1,000万",IF(Q7<=3000,"1,000〜3,000万","3,000万〜")))) -> 3,000万〜 | S7: 工事費負担金の総額32.0百万円(消費税等相当額2.9百万円含む)、税抜29.1百万円（架空線20.7/バンク逆潮流対策7.0/計量0.3/NTT電柱建替0.5/上位系増強0.6）。概算工事費総額104.0百万円(税込) | U7: 31 | V7: =IF(U7="","不明",IF(U7<=6,"〜6ヶ月",IF(U7<=12,"7〜12ヶ月",IF(U7<=24,"13〜24ヶ月","25ヶ月〜")))) -> 25ヶ月〜 | W7: 工事費負担金の入金後 31箇月程度（契約手続期間含まず）。運用開始希望日2026年3月1日には連系不可、連系時期の調整が必要 | X7: 希望2026年3月1日は不可（入金後31箇月程度） | Y7: 高圧線新設・増架・張替(HAL-OC200mm2)、引込線ACSR-OC58、電柱新設7本/建替37本、開閉器、下府変電所1号変圧器バンク逆潮流対策(EVT・OVGR, 2026年4月完了予定)、計量設備 | Z7: あり: 金城変電所110/66kV連系変圧器 順潮流対策用N-1電制装置(過負荷保護装置)設置工事（共用按分4.88%で特定負担0.6百万円）。本対策完了前の連系可 | AA7: ノンファーム型接続(西島根変220/110kV連系変圧器・110kV金城連絡線)、再給電方式、早期連系追加対策(充電制限:金城変110/66kV)、力率 放電93%遅れ/充電93%進み一定、充電変化速度調整、手動復帰、N-1電制本格適用 | AB7: 接続検討の回答日から1年を経過した場合は契約申込不可 | AC7: high | AE7: 検討対象年度2028年度。別紙1適合検討書・別紙2潮流グラフあり | AF7: － | AG7: 運開希望日に間に合わず | AH7: =IF(AD7<>"","未読",IF(AND(D7<>"接続検討回答",D7<>"再接続検討",D7<>"契約申込回答"),"",TRIM(IF(O7="","負担金なし ","")&IF(U7="","工期なし ","")&IF(AND(O7<>"",OR(P7="",P7="不明")),"税区分不明 ","")&IF(AC7="low","信頼度low","")))) | AJ7: 未確認 | AM7: 開く | AN7: 【秘】接続検討回答書 （G松江320）.pdf | AO7: 【秘】接続検討回答書 （G松江320）.pdf
A8: 7 | B8: 0916 | C8: 0916_島根県浜田市宇野町1819-1他3筆（エクスパワー） | D8: 契約申込回答 | E8: 中国 | F8: 2026-07-07 | G8: 2026-01-16 | H8: 株式会社パワーエックス（PX浜田市宇野町1819-1蓄電所） | I8: 島根県浜田市宇野町1819番1他4筆 | J8: 1994 | K8: 1999 | L8: 6.6kV | M8: 下府変電所（配電用） | N8: 6kV国分線 | O8: 32506910 | P8: 税込 | Q8: =IF(O8="","",IF(P8="税抜",O8*1.1,O8)/10000) -> 3250.691 | R8: =IF(Q8="","不明",IF(Q8<=500,"〜500万",IF(Q8<=1000,"500〜1,000万",IF(Q8<=3000,"1,000〜3,000万","3,000万〜")))) -> 3,000万〜 | S8: 工事費負担金の総額32,506,910円(消費税等相当額2,955,173円含む)、税抜29,551,737円（架空線20,764,400/バンク逆潮流対策6,979,000/計量337,318/NTT柱建替500,000/上位系増強971,019）。接続検討時32.0百万円から変更 | V8: =IF(U8="","不明",IF(U8<=6,"〜6ヶ月",IF(U8<=12,"7〜12ヶ月",IF(U8<=24,"13〜24ヶ月","25ヶ月〜")))) -> 不明 | W8: 別紙に連系予定（運用開始）2029年3月1日（工期月数の記載はOCRで判読できず） | X8: 2029年3月1日（系統連系予定日／竣工予定日） | Y8: 接続検討時と同様の配電線工事(HAL-OC200mm2新設・増架・張替、電柱新設7/建替37)、バンク逆潮流対策(EVT・OVGR、2026年4月完了)、計量設備 | Z8: 上位系統増強工事: 西島根変電所220/110kV連系変圧器N-1電制装置、110kV金城連絡線N-1電制装置、金城変電所110/66kV連系変圧器N-1電制装置設置工事（共用按分2.55%/4.07%） | AA8: ノンファーム型接続・再給電方式、充電制限（接続検討時に準ず） | AC8: medium | AE8: 2025年12月2日付契約申込(2026年1月16日受付)の承諾。系統容量確定。スキャンPDFのDrive OCRで読取のため一部判読不能（工期等） | AF8: ○ | AH8: =IF(AD8<>"","未読",IF(AND(D8<>"接続検討回答",D8<>"再接続検討",D8<>"契約申込回答"),"",TRIM(IF(O8="","負担金なし ","")&IF(U8="","工期なし ","")&IF(AND(O8<>"",OR(P8="",P8="不明")),"税区分不明 ","")&IF(AC8="low","信頼度low","")))) -> 工期なし | AJ8: 未確認 | AM8: 開く | AN8: 916（エクスパワー）_発電設備等に関する契約申込みお回答について（承諾）_中国電力NW_20260707.pdf | AO8: 916（エクスパワー）_発電設備等に関する契約申込みお回答について（承諾）_中国電力NW_20260707.pdf
A9: 8 | B9: 0916 | C9: 0916_島根県浜田市宇野町1819-1他3筆（エクスパワー） | D9: その他 | E9: 中国 | F9: 2026-07-07 | H9: 株式会社パワーエックス（PX浜田市宇野町1819-1蓄電所） | I9: 島根県浜田市宇野町1819番1他4筆 | J9: 1994 | K9: 1999 | L9: 6.6kV | M9: 下府変電所（配電用） | N9: 6kV国分線 | O9: 32506910 | P9: 税込 | Q9: =IF(O9="","",IF(P9="税抜",O9*1.1,O9)/10000) -> 3250.691 | R9: =IF(Q9="","不明",IF(Q9<=500,"〜500万",IF(Q9<=1000,"500〜1,000万",IF(Q9<=3000,"1,000〜3,000万","3,000万〜")))) -> 3,000万〜 | S9: 請求額 32,506,910円(税込, うち消費税等2,955,173円)。お支払済み保証金1,600,000円を差引き今回ご請求額30,906,910円、支払期限2026年8月10日 | T9: 1600000 | V9: =IF(U9="","不明",IF(U9<=6,"〜6ヶ月",IF(U9<=12,"7〜12ヶ月",IF(U9<=24,"13〜24ヶ月","25ヶ月〜")))) -> 不明 | W9: 竣工予定日 2029年3月1日 | X9: 竣工予定日2029年3月1日 | AA9: 工事はご負担額を申し受けた後に着手 | AC9: high | AE9: 工事費負担金請求書（スキャン画像を目視読取） | AF9: － | AH9: =IF(AD9<>"","未読",IF(AND(D9<>"接続検討回答",D9<>"再接続検討",D9<>"契約申込回答"),"",TRIM(IF(O9="","負担金なし ","")&IF(U9="","工期なし ","")&IF(AND(O9<>"",OR(P9="",P9="不明")),"税区分不明 ","")&IF(AC9="low","信頼度low","")))) | AJ9: 未確認 | AM9: 開く | AN9: 916（エクスパワー）_工事費のご請求について_20260707.pdf | AO9: 916（エクスパワー）_工事費のご請求について_20260707.pdf
A10: 9 | B10: 0916 | C10: 0916_島根県浜田市宇野町1819-1他3筆（エクスパワー） | D10: その他 | E10: 中国 | F10: 2026-07-07 | G10: 2026-01-16 | H10: 株式会社パワーエックス（PX浜田市宇野町1819-1蓄電所） | I10: 島根県浜田市宇野町1819番1他4筆 | J10: 1994 | K10: 1999 | L10: 6.6kV | M10: 下府変電所（配電用） | N10: 6kV国分線 | P10: 不明 | Q10: =IF(O10="","",IF(P10="税抜",O10*1.1,O10)/10000) | R10: =IF(Q10="","不明",IF(Q10<=500,"〜500万",IF(Q10<=1000,"500〜1,000万",IF(Q10<=3000,"1,000〜3,000万","3,000万〜")))) -> 不明 | V10: =IF(U10="","不明",IF(U10<=6,"〜6ヶ月",IF(U10<=12,"7〜12ヶ月",IF(U10<=24,"13〜24ヶ月","25ヶ月〜")))) -> 不明 | X10: 系統連系予定日 2029年3月1日 | AA10: PCS力率 放電94%遅れ/充電90%進み一定（2026.6.15追記）、出力変化速度設定、オンライン制御準備までオフライン(手動)出力制御、PCS2,600kW→1,999kW出力制限、蓄電池7,404kWh | AC10: medium | AE10: 系統連系承諾日2026-07-07、定格出力1,999kW、連系電圧高圧6kV。負担金記載なし（OCR読取） | AF10: － | AH10: =IF(AD10<>"","未読",IF(AND(D10<>"接続検討回答",D10<>"再接続検討",D10<>"契約申込回答"),"",TRIM(IF(O10="","負担金なし ","")&IF(U10="","工期なし ","")&IF(AND(O10<>"",OR(P10="",P10="不明")),"税区分不明 ","")&IF(AC10="low","信頼度low","")))) | AJ10: 未確認 | AM10: 開く | AN10: 916（エクスパワー）_系統連系およびアンシラリーサービス契約承諾書_20260707.pdf | AO10: 916（エクスパワー）_系統連系およびアンシラリーサービス契約承諾書_20260707.pdf
A11: 10 | B11: 0919 | C11: 0919_山口県周防大島町久賀2086-4（エクスパワー） | D11: 接続検討回答 | E11: 中国 | H11: （PX周防大島町久賀2086-4蓄電所, お問合せ番号G周南184(柳井)） | I11: 山口県大島郡周防大島町久賀2086-4 | P11: 不明 | Q11: =IF(O11="","",IF(P11="税抜",O11*1.1,O11)/10000) | R11: =IF(Q11="","不明",IF(Q11<=500,"〜500万",IF(Q11<=1000,"500〜1,000万",IF(Q11<=3000,"1,000〜3,000万","3,000万〜")))) -> 不明 | V11: =IF(U11="","不明",IF(U11<=6,"〜6ヶ月",IF(U11<=12,"7〜12ヶ月",IF(U11<=24,"13〜24ヶ月","25ヶ月〜")))) -> 不明 | AB11: 本接続検討結果の有効期間は発行日から1年（2025-10-09送付メールより） | AC11: low | AD11: スキャン画像PDF（約7MB）: read_file_contentでは本文テキスト化されず（グラフ断片のみ）、download_file_contentはMCPセッション切断で2回失敗 | AE11: 回答送付メール(2025-10-09, 中国電力NW, 1jUHmHFjZyvXbIa9p3mhiiwEaOb-XFCU6)より: 原本はパスワード付ZIP「【秘】接続検討回答書（高圧）（G周南184）.zip」。連系申込時にPCS出力制限証明書提出要、保証金=接続検討回答時の工事費負担金概算×5%。読めた断片は西島根/徳山系統の2024年度潮流グラフのみ。接続検討申込(2025-06-06)、発調申込書類(2025-11-14修正)あり | AF11: － | AH11: =IF(AD11<>"","未読",IF(AND(D11<>"接続検討回答",D11<>"再接続検討",D11<>"契約申込回答"),"",TRIM(IF(O11="","負担金なし ","")&IF(U11="","工期なし ","")&IF(AND(O11<>"",OR(P11="",P11="不明")),"税区分不明 ","")&IF(AC11="low","信頼度low","")))) -> 未読 | AJ11: 未確認 | AM11: 開く | AN11: 接続検討回答_#0919_山口県大島郡周防大島町久賀2086-4.pdf | AO11: 251010_接続検討回答/接続検討回答_#0919_山口県大島郡周防大島町久賀2086-4.pdf
A12: 11 | B12: 1092 | C12: 1092_三重県伊勢市特高 | D12: 接続検討回答 | E12: 中部 | F12: 2026-06-16 | G12: 2026-03-16 | H12: 株式会社パワーエックス（三重伊勢蓄電所） | I12: 三重県伊勢市矢持町（番地未定） | J12: 49880 | K12: 50000 | L12: 77kV | M12: 南勢変電所（275/77kV）系統／度会橋変電所 | N12: 77kV度会橋連絡線 No.26鉄塔より架空2回線(A160)で連系 | O12: 922900000 | P12: 税込 | Q12: =IF(O12="","",IF(P12="税抜",O12*1.1,O12)/10000) -> 92290 | R12: =IF(Q12="","不明",IF(Q12<=500,"〜500万",IF(Q12<=1000,"500〜1,000万",IF(Q12<=3000,"1,000〜3,000万","3,000万〜")))) -> 3,000万〜 | S12: 工事費負担金の総額922.9百万円(消費税相当額83.9百万円含む)、税抜839.0百万円（架空線643.6/変電169.0/通信18.7/計量7.8）。概算工事費総額2,355.4百万円(税込) | U12: 57 | V12: =IF(U12="","不明",IF(U12<=6,"〜6ヶ月",IF(U12<=12,"7〜12ヶ月",IF(U12<=24,"13〜24ヶ月","25ヶ月〜")))) -> 25ヶ月〜 | W12: 工事費負担金の入金後 57カ月程度（契約手続き期間・停電作業制約は含まず）。運用開始希望日2028年4月5日に間に合わないため連系時期の変更が必要 | X12: 希望2028年4月5日に間に合わず（入金後57カ月程度） | Y12: 鉄塔1基建替・アクセス線A160×2回線0.03km新設、南勢変電所 遮断器・断路器・開閉器取替(短絡容量超過)、N-1充電停止装置新設(南勢変275/77kV変圧器・77kV南勢度会橋線・77kV度会橋連絡線)、度会橋変PCM対向試験・補償リアクトル保護装置改造、押淵変電所断路器取替、他社(A社)受電用CT取替、VCT/計量器・保安通信・給電情報伝送装置新設 | Z12: 上位2電圧(500/275kV)は再給電方式。南勢変電所275/77kV変圧器関連のN-1充電停止装置新設等（増強ではなく電制装置） | AA12: ノンファーム型接続適用(主な設備:77kV度会橋連絡線)、N-1電制(本格適用)、早期連系追加対策(充電制限)前提・充電制限12時間/日目安、PCM保護継電装置設置、励磁突入電流対策(電圧変動対策 不適)、保護装置 不適(Tr%Z増加等)、運転力率は別途指定 | AB12: 接続検討の回答日から1年を経過した場合は契約申込不可 | AC12: high | AE12: 最大受電電力49,880kW・最大自家消費電力50,000kW。検討対象年度2032年度。専用線オンライン化工事は別途回答（同フォルダ） | AF12: ○ | AG12: 運開希望日に間に合わず | AH12: =IF(AD12<>"","未読",IF(AND(D12<>"接続検討回答",D12<>"再接続検討",D12<>"契約申込回答"),"",TRIM(IF(O12="","負担金なし ","")&IF(U12="","工期なし ","")&IF(AND(O12<>"",OR(P12="",P12="不明")),"税区分不明 ","")&IF(AC12="low","信頼度low","")))) | AJ12: 未確認 | AM12: 開く | AN12: 接続検討回答書【株式会社パワーエックスさま（三重伊勢蓄電所）】.pdf | AO12: 接続検討回答書/接続検討回答書【株式会社パワーエックスさま（三重伊勢蓄電所）】.pdf
A13: 12 | B13: 1092 | C13: 1092_三重県伊勢市特高 | D13: その他 | E13: 中部 | F13: 2026-06-16 | G13: 2026-03-16 | H13: 株式会社パワーエックス（三重伊勢蓄電所） | I13: 三重県伊勢市矢持町（番地未定） | O13: 152020000 | P13: 税込 | Q13: =IF(O13="","",IF(P13="税抜",O13*1.1,O13)/10000) -> 15202 | R13: =IF(Q13="","不明",IF(Q13<=500,"〜500万",IF(Q13<=1000,"500〜1,000万",IF(Q13<=3000,"1,000〜3,000万","3,000万〜")))) -> 3,000万〜 | S13: 工事補償金の総額152.02百万円(消費税等相当額13.82百万円含む)。税抜138.2百万円（給電0.0/通信138.2）、概算工事費141.8百万円(税抜,給電は未定) | V13: =IF(U13="","不明",IF(U13<=6,"〜6ヶ月",IF(U13<=12,"7〜12ヶ月",IF(U13<=24,"13〜24ヶ月","25ヶ月〜")))) -> 不明 | W13: 『未定』 通常は工事補償金の入金後41ヶ月程度(給電1ヶ月,通信41ヶ月)だが制御システム改修時期が未確定のため未定 | Y13: 通信線路の2ルート化(光ケーブル施設)、専用線オンライン用CDT装置設置、給電制御システムデータメンテ | AA13: 2ルート目の事業者鉄塔～連系変電所区間OPGWは事業者設置 | AC13: high | AE13: 接続検討回答に付随する専用線オンライン化工事の見積回答（工事補償金）。添付:通信工事検討結果(1UvesZxdLFKjdMsJE0C3L1TyUpYJpJXGO)は前提条件のみで金額なし | AF13: － | AH13: =IF(AD13<>"","未読",IF(AND(D13<>"接続検討回答",D13<>"再接続検討",D13<>"契約申込回答"),"",TRIM(IF(O13="","負担金なし ","")&IF(U13="","工期なし ","")&IF(AND(O13<>"",OR(P13="",P13="不明")),"税区分不明 ","")&IF(AC13="low","信頼度low","")))) | AJ13: 未確認 | AM13: 開く | AN13: 専用線オンライン化工事 御見積の回答について（三重伊勢蓄電所）.pdf | AO13: 接続検討回答書/専用線オンライン化工事 御見積の回答について（三重伊勢蓄電所）.pdf
A14: 13 | B14: 1113 | C14: 1113_茨城県行方市浜1985-1,1985-3,1986-3（合同会社高塚） | D14: 接続検討回答 | E14: 東京 | P14: 不明 | Q14: =IF(O14="","",IF(P14="税抜",O14*1.1,O14)/10000) | R14: =IF(Q14="","不明",IF(Q14<=500,"〜500万",IF(Q14<=1000,"500〜1,000万",IF(Q14<=3000,"1,000〜3,000万","3,000万〜")))) -> 不明 | V14: =IF(U14="","不明",IF(U14<=6,"〜6ヶ月",IF(U14<=12,"7〜12ヶ月",IF(U14<=24,"13〜24ヶ月","25ヶ月〜")))) -> 不明 | AC14: low | AD14: スキャン画像PDF（約7MB）: read_file_contentでは本文テキスト化されず（グラフ断片のみ）、download_file_contentはMCPセッション切断で2回失敗 | AE14: 埋込みファイル名「接続検討の回答について【JK25GHZ040495】.pdf」（東京電力PG様式）。同フォルダに東電PGのノンファーム型接続同意書・売電先確定のお願い・ローカル系統混雑同意書・出力制御PCS仕様確認依頼書（回答同封物）あり。申込書は「茨城県行方市浜蓄電所」(2025-12-15)。数値は未取得 | AF14: － | AH14: =IF(AD14<>"","未読",IF(AND(D14<>"接続検討回答",D14<>"再接続検討",D14<>"契約申込回答"),"",TRIM(IF(O14="","負担金なし ","")&IF(U14="","工期なし ","")&IF(AND(O14<>"",OR(P14="",P14="不明")),"税区分不明 ","")&IF(AC14="low","信頼度low","")))) -> 未読 | AJ14: 未確認 | AM14: 開く | AN14: 接続検討回答.pdf | AO14: 04_回答/接続検討回答.pdf
A15: 14 | B15: 1123 | C15: 00_取り下げ、進行不可/1123_北海道道厚岸郡浜中町姉別南三線(エクスパワー）) | D15: 接続検討回答 | E15: 北海道 | F15: 2025-04-18 | G15: 2025-01-20 | H15: 株式会社エクスパワー | I15: 北海道厚岸郡浜中町姉別南三線179、他 | J15: 20395 | K15: 20450 | L15: 66kV | M15: 厚床変電所系統（工事検討結果の系統図より、要確認） | N15: 66kV根室2号線 No.361付近より1回線T分岐（66kV連系線ACSR/AC95sq 0.34km） | O15: 63500000 | P15: 税込 | Q15: =IF(O15="","",IF(P15="税抜",O15*1.1,O15)/10000) -> 6350 | R15: =IF(Q15="","不明",IF(Q15<=500,"〜500万",IF(Q15<=1000,"500〜1,000万",IF(Q15<=3000,"1,000〜3,000万","3,000万〜")))) -> 3,000万〜 | S15: 工事費負担金総額63.5百万円（消費税等5.8百万円含む）。税抜57.7百万円＝架空線33.7＋通信10.3＋計量13.7＋給電0.0。概算工事費84.9百万円(税込)。一般負担上限超過0 | U15: 26 | V15: =IF(U15="","不明",IF(U15<=6,"〜6ヶ月",IF(U15<=12,"7〜12ヶ月",IF(U15<=24,"13〜24ヶ月","25ヶ月〜")))) -> 25ヶ月〜 | W15: 工事費負担金の入金後26ヶ月程度（契約申込受付2025年5月下旬・入金2025年12月下旬を仮定）。今回申込のアクセス線運転開始希望日には連系不可 | X15: 工程表上: アクセス設備の運用開始可能日 2027年3月上旬（希望日2027年3月1日）※本文では希望日連系不可・ノンファームシステム開発期間は含まず | Y15: 66kV根室2号線No.361支持物建替、66kV連系線新設0.34km、通信回線構成・光ケーブル0.4km、中給・釧路系統制御所システム改修、計量器・VCT。申込者側: 電圧変動対策(STATCOM等 容量性/誘導性 各16MVar程度)、連系用変圧器%Z 64%以上(100MVAベース) | Z15: なし（基幹系北新得変275/187kVはノンファーム混雑管理で対応） | AA15: ノンファーム型接続（北新得変電所275/187kV連絡用変圧器）、再給電方式(一定の順序)、ローカル系統混雑管理、N-1電制本格適用、充放電抑制、PCS単独運転検出ロック、力率別途協議 | AB15: 接続検討回答日から1年を経過すると契約申込不可 | AC15: high | AE15: 受付番号 託2024_1167（約款改訂に係る更新版）。00_取り下げ、進行不可フォルダ配下。同フォルダに01回答について/02注意事項/04工事検討結果/05計量設備接続構造図/06電圧変動対策/07保安通信回線資料、03.発調申請書類に同一回答書の重複コピー(id=1sMDU7cV4t_qkmuBQLG5nGQqHwwzOswpH)あり | AF15: ○ | AG15: 運開希望日に間に合わず | AH15: =IF(AD15<>"","未読",IF(AND(D15<>"接続検討回答",D15<>"再接続検討",D15<>"契約申込回答"),"",TRIM(IF(O15="","負担金なし ","")&IF(U15="","工期なし ","")&IF(AND(O15<>"",OR(P15="",P15="不明")),"税区分不明 ","")&IF(AC15="low","信頼度low","")))) | AJ15: 未確認 | AM15: 開く | AN15: 03_接続検討回答書（約款改訂に係る更新）_【託2024_1167】_1.pdf | AO15: 1123_北海道道厚岸郡浜中町姉別南三線(エクスパワー）)/01_接続検討回答/03_接続検討回答書（約款改訂に係る更新）_【託2024_1167】_1.pdf
A16: 15 | B16: 1129 | C16: 1129_崇徳学園入野グラウンド(大柿産業) | D16: 事前相談回答 | E16: 中国 | F16: 2026-02-17 | G16: 2026-01-28 | H16: 株式会社イノスタ | I16: 広島県東広島市河内町入野字東山2138番38,2138番37 | J16: 100000 | L16: 110kV | N16: 想定連系点まで直線距離約5.2km | P16: 不明 | Q16: =IF(O16="","",IF(P16="税抜",O16*1.1,O16)/10000) | R16: =IF(Q16="","不明",IF(Q16<=500,"〜500万",IF(Q16<=1000,"500〜1,000万",IF(Q16<=3000,"1,000〜3,000万","3,000万〜")))) -> 不明 | S16: 事前相談のため記載なし | V16: =IF(U16="","不明",IF(U16<=6,"〜6ヶ月",IF(U16<=12,"7〜12ヶ月",IF(U16<=24,"13〜24ヶ月","25ヶ月〜")))) -> 不明 | W16: 記載なし（接続検討で検討） | Z16: 平常時における混雑発生［あり］、主な混雑設備：110kV椋梨川線 | AA16: ノンファーム型接続適用電源。熱容量起因の連系制限欄は取消線（対象外）。FRT要件充足要。逆潮流側のみの検討（順潮流は接続検討で実施）。 | AC16: high | AE16: 特別高圧様式CK3。PDFはテキスト層なし（Print To PDF）のため画像レンダリングして目視で読取。事前相談は100,000kW/110kVだが、その後の接続検討申込は高圧規模で別スキーム。 | AF16: － | AH16: =IF(AD16<>"","未読",IF(AND(D16<>"接続検討回答",D16<>"再接続検討",D16<>"契約申込回答"),"",TRIM(IF(O16="","負担金なし ","")&IF(U16="","工期なし ","")&IF(AND(O16<>"",OR(P16="",P16="不明")),"税区分不明 ","")&IF(AC16="low","信頼度low","")))) | AI16: 比較不可(片方に値なし)（メモ:東広島654(1129崇徳)） | AJ16: 未確認 | AM16: 開く | AN16: 【秘】事前相談に対する回答書（広島２６１４）.pdf | AO16: 01.事前相談/【秘】事前相談に対する回答書（広島２６１４）.pdf
A17: 16 | B17: 1129 | C17: 1129_崇徳学園入野グラウンド(大柿産業) | D17: 接続検討回答 | E17: 中国 | F17: 2026-06-29 | G17: 2026-04-03 | H17: 株式会社パワーエックス | I17: 広島県東広島市河内町入野字東山12138番37（（仮称）PX東広島市河内蓄電所） | J17: 1994 | K17: 1999 | L17: 6.6kV（高圧） | M17: 高屋変電所（配電用）／基幹変電所：広島変電所 | N17: 6kV 是国線 大仙支20号柱より分岐（竹原変電所6kV新庄線は空き容量なしのため不可） | O17: 103700000 | P17: 税込 | Q17: =IF(O17="","",IF(P17="税抜",O17*1.1,O17)/10000) -> 10370 | R17: =IF(Q17="","不明",IF(Q17<=500,"〜500万",IF(Q17<=1000,"500〜1,000万",IF(Q17<=3000,"1,000〜3,000万","3,000万〜")))) -> 3,000万〜 | S17: 工事費負担金総額103.7百万円（消費税等9.5百万円含む）。税抜94.2百万円の内訳：架空線41.9／地中線44.8／計量0.3／上位系対策0.6／伐採6.6。概算工事費総額159.2百万円（税込、税抜144.7）。一般負担上限超過なし。 | U17: 92 | V17: =IF(U17="","不明",IF(U17<=6,"〜6ヶ月",IF(U17<=12,"7〜12ヶ月",IF(U17<=24,"13〜24ヶ月","25ヶ月〜")))) -> 25ヶ月〜 | W17: 工事費負担金の入金後92箇月程度（契約手続期間は含まず） | X17: 運用開始希望日2027-10-01には連系不可、連系時期の調整が必要（入金後92箇月） | Y17: 6kV架空線：高圧線新設168m・張替7,511m（RW-AL-OC200㎜2、455A）、電柱新設4本・建替59本、開閉器新設3・取替4、TVR取替1台、計測機能付開閉器1台、引込線30m／地中線：管路330m（Φ125×2条）・CVT325㎟ 195m／伐採23径間／計量器2台（受電用・供給用）ほか。工事亘長 架空約7.8km・地中約0.2km | Z17: 220kV広島西幹線対策（N-1充電停止装置設置他：先行事業者特定負担46.1百万円×共用比率1.3%＝0.6百万円）、220kV広島系SSC取替（一般負担3.0百万円）。先行事業者分として実施中で、本文では本対策完了前の連系が可能とする | AA17: ノンファーム型接続（再給電方式・一定の順序、制御量に影響する主設備：220kV広島西幹線、オンライン出力制御機器を自社負担で導入）。早期連系追加対策（充電制限）適用：110kV広島西条線の熱容量を順潮流で超過するため、スケジュール運転機能・区分計量器が必要（暫定措置、不同意なら増強工事＋再検討）。力率：放電時 進み93%／充電時 遅れ93%一定。出力変化速度の設定、停止後は手動復帰、作業停止時の充放電抑制、N-1電制本格適用。発電側課金割引区分A-3。検討年度2034年度。サイバーセキュリティ要件 | AB17: 有効期限の明記なし（系統状況の変化等で有効でなくなる場合ありとの記載のみ） | AC17: high | AE17: PDFはパスワード付きだったが、同じ回答書フォルダにあるファイル名の値（中国電力NWの通知パスワードと推定）で開けた。別紙2（概略工程表）：92箇月工程、6kV架空約7.8km・地中約0.2km。注意事項欄には『上位系統の空き容量不足のため対策工事を実施中で、連系は上位系統対策完了後』とあり、本文7頁の『本対策完了前の連系が可能』と食い違うため確認が必要。別紙4（110kV広島西条線の季節別想定潮流）はグラフのみで数値はテキストで取れない。 | AF17: ○ | AG17: 運開希望日に間に合わず | AH17: =IF(AD17<>"","未読",IF(AND(D17<>"接続検討回答",D17<>"再接続検討",D17<>"契約申込回答"),"",TRIM(IF(O17="","負担金なし ","")&IF(U17="","工期なし ","")&IF(AND(O17<>"",OR(P17="",P17="不明")),"税区分不明 ","")&IF(AC17="low","信頼度low","")))) | AI17: 比較不可(片方に値なし)（メモ:東広島654(1129崇徳)） | AJ17: 未確認 | AM17: 開く | AN17: 【秘】接続検討回答書(G東広島654).pdf | AO17: 04.接続検討回答書/【秘】接続検討回答書(G東広島654).pdf
A18: 17 | B18: 1135 | C18: 1135_北海道夕張郡由仁町川端1178番、1180番（葵アセットマネジメント株式会社） | D18: 事前相談回答 | E18: 北海道 | F18: 2026-02-27 | G18: 2026-01-28 | H18: 株式会社イノスタ | I18: 北海道夕張郡由仁町川端1178番、1180番 | J18: 25000 | L18: 66kV | N18: 66kV 川端線 NO.78 付近（想定連系点、設置場所から直線距離約2km） | P18: 不明 | Q18: =IF(O18="","",IF(P18="税抜",O18*1.1,O18)/10000) | R18: =IF(Q18="","不明",IF(Q18<=500,"〜500万",IF(Q18<=1000,"500〜1,000万",IF(Q18<=3000,"1,000〜3,000万","3,000万〜")))) -> 不明 | S18: 事前相談のため工事費負担金の記載なし | V18: =IF(U18="","不明",IF(U18<=6,"〜6ヶ月",IF(U18<=12,"7〜12ヶ月",IF(U18<=24,"13〜24ヶ月","25ヶ月〜")))) -> 不明 | W18: 記載なし（工事内容・工期は接続検討で検討） | Z18: 主な混雑設備：北江別変電所 187/66kV 連変 | AA18: ノンファーム型接続適用電源。平常時混雑発生［なし］・［あり］及び熱容量起因連系制限［なし］・［あり］の選択はテキスト抽出で判別不可（連系制限ありの場合の最大受電電力欄は「－kW」）。北海道エリアは需給調整面の出力制御可能性あり。 | AC18: high | AE18: 事前相談回答（特別高圧様式CK3、受付託2025_1317、申込者はイノスタ名義、希望受電電圧66kV・25,000kW）。その後PX名義で高圧接続検討（託2026_0059、（仮称）PX北海道夕張蓄電所、高圧4台）を申込んだが2026-06-09付で取下げ、接続検討料220,000円(税込)返金のお知らせ(2026-06-11)あり。接続検討回答書はフォルダ内に無し。 | AF18: － | AH18: =IF(AD18<>"","未読",IF(AND(D18<>"接続検討回答",D18<>"再接続検討",D18<>"契約申込回答"),"",TRIM(IF(O18="","負担金なし ","")&IF(U18="","工期なし ","")&IF(AND(O18<>"",OR(P18="",P18="不明")),"税区分不明 ","")&IF(AC18="low","信頼度low","")))) | AI18: 比較不可(片方に値なし)（メモ:北海道由仁町(案件1135)） | AJ18: 未確認 | AM18: 開く | AN18: 【非公開情報等】【託2025_1317】事前相談回答書_株式会社イノスタ.pdf | AO18: 03_接続検討申請/01.事前相談/【非公開情報等】【託2025_1317】事前相談回答書_株式会社イノスタ.pdf
A19: 18 | B19: 1136 | C19: 1136_兵庫県高砂市中筋3丁目780番（藤栄建設） | D19: 接続検討回答 | E19: 関西 | F19: 2026-04-28 | G19: 2026-02-10 | H19: 株式会社パワーエックス（兵庫高砂蓄電所, 受付番号2025-82-04346） | I19: 兵庫県高砂市中筋三丁目780番,781番 | J19: 1994 | K19: 100 | L19: 6.6kV | M19: 曽根変電所 | N19: 天川配電線（アルミ120sq, 阿弥陀43E2付近から高圧引込） | O19: 32500000 | P19: 税込 | Q19: =IF(O19="","",IF(P19="税抜",O19*1.1,O19)/10000) -> 3250 | R19: =IF(Q19="","不明",IF(Q19<=500,"〜500万",IF(Q19<=1000,"500〜1,000万",IF(Q19<=3000,"1,000〜3,000万","3,000万〜")))) -> 3,000万〜 | S19: 工事費負担金の総額32.5百万円(消費税等相当額含む, 額は空欄)、税抜29.5（架空線29.3/計量0.2）。概算工事費総額32.7百万円(税抜29.7)。※内訳表の単位表記は「千円」だが数値は百万円単位相当 | U19: 24 | V19: =IF(U19="","不明",IF(U19<=6,"〜6ヶ月",IF(U19<=12,"7〜12ヶ月",IF(U19<=24,"13〜24ヶ月","25ヶ月〜")))) -> 13〜24ヶ月 | W19: 工事費負担金の入金後 24ケ月程度（契約手続き期間含まず）。運用開始希望日2027年2月1日には連系不可、連系時期の調整が必要 | X19: 希望2027年2月1日は不可（入金後24ケ月程度） | Y19: 電柱建替15本、高圧線新設831m・張替182m(アルミ120sq)、変圧器位置替14台、開閉器新設/位置替、電圧調整器新設3台(3500kVA)、引込線20m、計量設備(VCT・計量器2台・通信端局) | Z19: なし（上位系増強工事 -） | AA19: ノンファーム型接続適用（北摂変電所500/275kV変圧器混雑）・再給電方式。早期連系追加対策(充電制限)は現時点不要。揚水・蓄電池特別措置適用前提で算定。OCR・DGR保護協調は連系申込時に検討 | AB19: 接続検討の回答日から1年を経過した場合は契約申込不可 | AC19: high | AE19: 最大自家消費電力100kWとして検討。検討対象年度2026年度。同一内容のコピーが複数(1LxdEg…, 1ecLWJ…, 1BMTiR…, 圧縮版1bMaqG…/1vyKSS…)。発調申込(2026-05-18提出)フォルダあり、充電制限同意書(関西,2026-05-15)も存在 | AF19: ○ | AG19: 運開希望日に間に合わず | AH19: =IF(AD19<>"","未読",IF(AND(D19<>"接続検討回答",D19<>"再接続検討",D19<>"契約申込回答"),"",TRIM(IF(O19="","負担金なし ","")&IF(U19="","工期なし ","")&IF(AND(O19<>"",OR(P19="",P19="不明")),"税区分不明 ","")&IF(AC19="low","信頼度low","")))) | AJ19: 未確認 | AM19: 開く | AN19: 接続検討申込みに対する回答について.pdf | AO19: 03_イノスタ作成成果物/接続検討申込みに対する回答について.pdf
A20: 19 | B20: 1147 | C20: 1147_愛知県岡崎市板田町東流石（中部産業） | D20: 接続検討回答 | E20: 中部 | F20: 2026-06-03 | G20: 2026-03-09 | H20: 株式会社パワーエックス（PX愛知県岡崎市蓄電所, 受付番号AAD610461758） | I20: 愛知県岡崎市板田町字東流石27-1 他26筆 | J20: 1994 | K20: 1999 | L20: 6.6kV | M20: 大平変電所 | N20: 大平変電所F36 01ｷ401より分岐（OC-W60mm2） | O20: 7946700 | P20: 税込 | Q20: =IF(O20="","",IF(P20="税抜",O20*1.1,O20)/10000) -> 794.67 | R20: =IF(Q20="","不明",IF(Q20<=500,"〜500万",IF(Q20<=1000,"500〜1,000万",IF(Q20<=3000,"1,000〜3,000万","3,000万〜")))) -> 500〜1,000万 | S20: 工事費負担金の総額7,946.7千円(消費税相当額722.4千円含む)、税抜7,224.3千円（架空線86.7/バンク逆潮流対策6,979.0/計量158.6）。概算工事費総額38,769.8千円(税込) | T20: 397000 | U20: 6 | V20: =IF(U20="","不明",IF(U20<=6,"〜6ヶ月",IF(U20<=12,"7〜12ヶ月",IF(U20<=24,"13〜24ヶ月","25ヶ月〜")))) -> 〜6ヶ月 | W20: 工事費負担金の入金後 6ヶ月程度（契約手続き期間含まず）。別紙: 2028年度下期頃予定のバンク逆潮流対策工事後に連系可能となるため、上記工期かバンク逆潮流対策工事のどちらか遅い時期 | X20: 入金後6ヶ月 または 2028年度下期頃（バンク逆潮流対策工事後）の遅い方 | Y20: 架空線(高圧引込線20m等)、配変バンク逆潮流対策、計量設備(計量器2台・VCT) | Z20: 上位系統の現場調査・設計/工事施工が工程表に記載（バンク逆潮流対策 2028年度下期頃） | AA20: ノンファーム型接続(275kV東部額田線・新三河変電所)、再給電方式、早期連系追加対策(充電制限)前提、PCS力率一定 充電95%進み/放電99%遅れ、手動復帰、構内変圧器タップ6600、N-1電制本格適用(新三河変電所) | AB20: 接続検討の回答日から1年を経過した場合は契約申込不可 | AC20: high | AE20: 系統連系保証金397千円(税込,消費税36千円含む)を記載。希望運用開始2027年2月1日。同一ファイルのコピー2件(1OeU4m…,1zQE5s…)とZIP版(1CHhco…, 未展開)あり。別紙「所要工期について」(1dUW8K…)参照 | AF20: ○ | AG20: 工期と別にバンク/上位系対策待ち | AH20: =IF(AD20<>"","未読",IF(AND(D20<>"接続検討回答",D20<>"再接続検討",D20<>"契約申込回答"),"",TRIM(IF(O20="","負担金なし ","")&IF(U20="","工期なし ","")&IF(AND(O20<>"",OR(P20="",P20="不明")),"税区分不明 ","")&IF(AC20="low","信頼度low","")))) | AJ20: 未確認 | AM20: 開く | AN20: 接続検討回答書（株式会社パワーエックス PX愛知県岡崎市蓄電所）.pdf | AO20: 04.接続検討回答書/接続検討回答書 株式会社パワーエックス PX愛知県岡崎市蓄電所/接続検討回答書（株式会社パワーエックス PX愛知県岡崎市蓄電所）.pdf
A21: 20 | B21: 1147 | C21: 1147_愛知県岡崎市板田町東流石（中部産業） | D21: その他 | E21: 中部 | F21: 2026-06-16 | G21: 2026-06-11 | H21: 株式会社パワーエックス | P21: 不明 | Q21: =IF(O21="","",IF(P21="税抜",O21*1.1,O21)/10000) | R21: =IF(Q21="","不明",IF(Q21<=500,"〜500万",IF(Q21<=1000,"500〜1,000万",IF(Q21<=3000,"1,000〜3,000万","3,000万〜")))) -> 不明 | V21: =IF(U21="","不明",IF(U21<=6,"〜6ヶ月",IF(U21<=12,"7〜12ヶ月",IF(U21<=24,"13〜24ヶ月","25ヶ月〜")))) -> 不明 | AC21: high | AE21: 接続検討要否確認結果: 「接続検討申込みは省略することができます」（受付番号AAD610461758, 契約申込前の要否確認） | AF21: － | AH21: =IF(AD21<>"","未読",IF(AND(D21<>"接続検討回答",D21<>"再接続検討",D21<>"契約申込回答"),"",TRIM(IF(O21="","負担金なし ","")&IF(U21="","工期なし ","")&IF(AND(O21<>"",OR(P21="",P21="不明")),"税区分不明 ","")&IF(AC21="low","信頼度low","")))) | AJ21: 未確認 | AM21: 開く | AN21: 接続検討の要否確認依頼に対する結果について（株式会社パワーエックス様）.pdf | AO21: 07.接続検討要否確認結果※イノスタ対応/接続検討の要否確認依頼に対する結果について（株式会社パワーエックス様）.pdf
A22: 21 | B22: 1168 | C22: 1168_兵庫県高砂市伊保四丁目５１６番 | D22: 接続検討回答 | E22: 関西 | F22: 2026-06-24 | G22: 2026-04-10 | H22: 株式会社パワーエックス | I22: 兵庫県高砂市伊保四丁目516番（（仮称）PX兵庫高砂伊保四丁目蓄電所） | J22: 1994 | L22: 6.6kV（高圧） | M22: 曽根変電所 | N22: 石殿配電線（上沼田35S5付近から高圧引込） | O22: 3800000 | P22: 税込 | Q22: =IF(O22="","",IF(P22="税抜",O22*1.1,O22)/10000) -> 380 | R22: =IF(Q22="","不明",IF(Q22<=500,"〜500万",IF(Q22<=1000,"500〜1,000万",IF(Q22<=3000,"1,000〜3,000万","3,000万〜")))) -> 〜500万 | S22: 工事費負担金の総額3.8百万円（消費税等相当額 欄空白）／内訳(税抜)架空線3.3・計量0.2等 計3.5百万円。概算工事費総額4.1百万円（税抜3.7）。特措適用前提 | U22: 12 | V22: =IF(U22="","不明",IF(U22<=6,"〜6ヶ月",IF(U22<=12,"7〜12ヶ月",IF(U22<=24,"13〜24ヶ月","25ヶ月〜")))) -> 7〜12ヶ月 | W22: 工事費負担金の入金後 12ケ月程度（契約手続期間は含まず）。運用開始希望日2027/2/1には連系不可 | X22: 運用開始希望日2027年2月1日は不可（入金後12ヶ月程度） | Y22: 電柱新設1本/建替2本、高圧線新設118m・張替302m(アルミ120sq)、低圧線張替38m、引込線20m、開閉器新設、計量装置 | Z22: なし（上位系増強工事 -） | AA22: ノンファーム型接続（主な混雑設備:北摂変電所500/275kV変圧器）、再給電方式、N-1電制本格適用、力率一定制御0.9、早期連系追加対策(充電制限)は不要、特措(蓄電池特別措置)適用前提 | AB22: 接続検討の回答日から1年を経過すると契約申込不可 | AC22: high | AE22: 受付番号2025-82-05087。最大自家消費電力は95kWと記載（充電側kW不明確のためcapacity_kw_chargeはnull）。消費税額欄が空白のため税込/税抜表記は総額欄の書式による。 | AF22: ○ | AG22: 運開希望日に間に合わず | AH22: =IF(AD22<>"","未読",IF(AND(D22<>"接続検討回答",D22<>"再接続検討",D22<>"契約申込回答"),"",TRIM(IF(O22="","負担金なし ","")&IF(U22="","工期なし ","")&IF(AND(O22<>"",OR(P22="",P22="不明")),"税区分不明 ","")&IF(AC22="low","信頼度low","")))) | AJ22: 未確認 | AM22: 開く | AN22: 接続検討申込に対する回答_兵庫高砂伊保四丁目蓄電所.pdf | AO22: 接続検討申込に対する回答_兵庫高砂伊保四丁目蓄電所.pdf
A23: 22 | B23: 1169 | C23: 確認要_1169_島根県邑智郡梁瀬（石見簗瀬駅）（JR西日本） | D23: 接続検討回答 | E23: 中国 | F23: 2026-06-29 | G23: 2026-03-31 | H23: 西日本旅客鉄道株式会社 | I23: 島根県邑智郡美郷町築瀬202-7（（仮称）島根県邑智郡美郷町蓄電所） | J23: 1994 | K23: 1999 | L23: 6.6kV（高圧） | M23: 明塚変電所（配電用）/潮変電所No.2変圧器増設/基幹:作木変電所 | N23: 6kV赤来線 吾郷幹30号柱より分岐（22/6kV柱上変圧器2.5MVA新設・他発電設備の系統変更後） | O23: 322500000 | P23: 税込 | Q23: =IF(O23="","",IF(P23="税抜",O23*1.1,O23)/10000) -> 32250 | R23: =IF(Q23="","不明",IF(Q23<=500,"〜500万",IF(Q23<=1000,"500〜1,000万",IF(Q23<=3000,"1,000〜3,000万","3,000万〜")))) -> 3,000万〜 | S23: 工事費負担金の総額322.5百万円（消費税等相当額29.3百万円を含む）／税抜293.2百万円＝架空線21.5+計量0.3+その他(上位系)62.2+一般負担上限額超過分209.2。概算工事費総額481.9百万円（税込） | U23: 54 | V23: =IF(U23="","不明",IF(U23<=6,"〜6ヶ月",IF(U23<=12,"7〜12ヶ月",IF(U23<=24,"13〜24ヶ月","25ヶ月〜")))) -> 25ヶ月〜 | W23: 工事費負担金の入金後 54ヶ月程度（契約手続期間は含まず）。運用開始希望日2027/10/1には連系不可、連系時期の調整が必要 | X23: 運用開始希望日2027年10月1日は不可（入金後54ヶ月程度） | Y23: 高圧線新設1344m・張替632m、電柱新設42本/建替10本、引込線11m、SVR(3,000kVA)新設、22/6kV柱上変圧器2.5MVA新設+22kV架空線、潮変電所No.2変圧器増設(20MVA)・1次CB設置 | Z23: あり：潮変電所No.2変圧器増設(20MVA)、220kV広島西幹線/作木支線N-1充電停止装置通信設備(共用負担0.6+0.5百万円)、広島系SSC取替。一般負担上限(4.1万円/kW×1,994kW=81.8百万円)超過分209.2百万円を特定負担 | AA23: ノンファーム型接続（出力制御に影響:220kV作木支線/110kV潮熊見線）、再給電方式、N-1電制本格適用、力率 放電93%遅れ/充電90%進み一定、出力変化速度規定、充電停止あり。早期連系追加対策(充電制限)は不要 | AB23: 接続検討の回答日から1年を経過すると契約申込不可 | AC23: high | AE23: 同フォルダに【秘】書類確認結果（G松江691）.pdf（回答書ではない）あり。ZIP/emlは申込書送付関係 | AF23: ○ | AG23: 運開希望日に間に合わず | AH23: =IF(AD23<>"","未読",IF(AND(D23<>"接続検討回答",D23<>"再接続検討",D23<>"契約申込回答"),"",TRIM(IF(O23="","負担金なし ","")&IF(U23="","工期なし ","")&IF(AND(O23<>"",OR(P23="",P23="不明")),"税区分不明 ","")&IF(AC23="low","信頼度low","")))) | AJ23: 未確認 | AM23: 開く | AN23: 【秘】接続検討回答書（G松江691） | AO23: 【秘】接続検討回答書（G松江691）
A24: 23 | B24: 1185 | C24: 1185_静岡県掛川市淡陽18番1（ティーライフ） | D24: 接続検討回答 | E24: 中部 | F24: 2026-08-21 | G24: 2026-05-25 | H24: 株式会社パワーエックス（受付番号AAD240735819） | I24: 静岡県掛川市淡陽18番1（（仮称）PX静岡県掛川市蓄電所） | J24: 1994 | K24: 1999 | L24: 高圧 | M24: 安養寺変電所 | N24: 安養寺変電所F27（02ｳ851より分岐し構内柱と接続） | O24: 3260700 | P24: 税込 | Q24: =IF(O24="","",IF(P24="税抜",O24*1.1,O24)/10000) -> 326.07 | R24: =IF(Q24="","不明",IF(Q24<=500,"〜500万",IF(Q24<=1000,"500〜1,000万",IF(Q24<=3000,"1,000〜3,000万","3,000万〜")))) -> 〜500万 | S24: 工事費負担金の総額3,260.7千円（消費税相当額296.4千円を含む）。税抜2,964.3千円＝架空線工事2,805.7千円＋計量設備工事158.6千円。概算工事費も同額。 | U24: 12 | V24: =IF(U24="","不明",IF(U24<=6,"〜6ヶ月",IF(U24<=12,"7〜12ヶ月",IF(U24<=24,"13〜24ヶ月","25ヶ月〜")))) -> 7〜12ヶ月 | W24: 工事費負担金の入金後 12ヶ月程度 | X24: アクセス設備の運用開始希望日 2027年2月1日（連系可否：可） | Y24: 電柱新設1本・建替1本、高圧線新設20m・張替408m（OCW-60㎟へ太線化）、高圧引込線30m、開閉器取替、計量器1台・VCT1台 | Z24: 上位系統増強なし（駿遠変電所275/77kV変圧器の順潮流超過は充電制限で対応） | AA24: ノンファーム型接続適用（500kV西部幹線、500kV三岐幹線）、再給電方式。早期連系追加対策（充電制限）適用（駿遠変電所275/77kV変圧器の熱容量超過、スケジュール運転機能要、区分計量器要）。力率：放電97%（遅れ）・充電90%（進み）で不適→対策要。変圧器励磁突入電流による瞬時電圧変動対策要。出力変化速度5秒以上・ステップ10%以下・ランプ20%/秒以下。N-1電制本格適用。 | AB24: 接続検討の回答日から1年を経過した場合は契約申込不可 | AC24: high | AE24: 最大自家消費電力1,999kWをcapacity_kw_chargeに記載。充電制限に同意しない場合は増強工事・再接続検討の可能性。保証金額の記載なし。 | AF24: ○ | AH24: =IF(AD24<>"","未読",IF(AND(D24<>"接続検討回答",D24<>"再接続検討",D24<>"契約申込回答"),"",TRIM(IF(O24="","負担金なし ","")&IF(U24="","工期なし ","")&IF(AND(O24<>"",OR(P24="",P24="不明")),"税区分不明 ","")&IF(AC24="low","信頼度low","")))) | AJ24: 未確認 | AM24: 開く | AN24: 接続検討申込みに対する回答について.pdf | AO24: 1185_接続検討回答書一式 (PX静岡県掛川)/接続検討申込みに対する回答について.pdf
A25: 24 | B25: 1186 | C25: 確認要_1186_島根県邑智郡石原（沢谷駅）（JR西日本） | D25: 接続検討回答 | E25: 中国 | F25: 2026-06-29 | G25: 2026-03-31 | H25: 西日本旅客鉄道株式会社 | I25: 島根県邑智郡美郷町石原111-9（（仮称）JR島根県邑智郡石原蓄電所） | J25: 1994 | K25: 1999 | L25: 6.6kV（高圧） | M25: 潮変電所（配電用、No.2変圧器増設）/基幹:作木変電所 | N25: 6kV新設配電線 潮来島線144M3号柱より分岐（22/6kV柱上変圧器2.5MVA新設） | O25: 307000000 | P25: 税込 | Q25: =IF(O25="","",IF(P25="税抜",O25*1.1,O25)/10000) -> 30700 | R25: =IF(Q25="","不明",IF(Q25<=500,"〜500万",IF(Q25<=1000,"500〜1,000万",IF(Q25<=3000,"1,000〜3,000万","3,000万〜")))) -> 3,000万〜 | S25: 工事費負担金の総額307.0百万円（消費税等相当額27.9百万円を含む）／税抜279.1百万円＝架空線7.9+計量0.3+その他(上位系)84.2+一般負担上限額超過分186.7。概算工事費総額466.5百万円（税込） | U25: 54 | V25: =IF(U25="","不明",IF(U25<=6,"〜6ヶ月",IF(U25<=12,"7〜12ヶ月",IF(U25<=24,"13〜24ヶ月","25ヶ月〜")))) -> 25ヶ月〜 | W25: 工事費負担金の入金後 54ヶ月程度（契約手続期間は含まず）。運用開始希望日2027/10/1には連系不可、連系時期の調整が必要 | X25: 運用開始希望日2027年10月1日は不可（入金後54ヶ月程度） | Y25: 電柱新設3本、高圧線新設15m、引込線10m、SVR(3,000kVA)新設、22/6kV柱上変圧器2.5MVA新設(特定負担100%)+22kV架空線10m、潮変電所No.2変圧器増設(20MVA)・1次CB設置 | Z25: あり：潮変電所No.2変圧器増設(20MVA)、220kV広島西幹線/作木支線N-1充電停止装置通信設備(共用負担0.6+0.5百万円)、広島系SSC取替。一般負担上限81.8百万円超過分186.7百万円を特定負担 | AA25: ノンファーム型接続（220kV作木支線/110kV潮熊見線）、再給電方式、N-1電制本格適用、力率 放電93%遅れ/充電93%進み一定、出力変化速度規定、充電停止あり。早期連系追加対策(充電制限)は不要 | AB25: 接続検討の回答日から1年を経過すると契約申込不可 | AC25: high | AE25: 同フォルダに【秘】書類確認結果（G松江670）.pdf（回答書ではない）あり | AF25: ○ | AG25: 運開希望日に間に合わず | AH25: =IF(AD25<>"","未読",IF(AND(D25<>"接続検討回答",D25<>"再接続検討",D25<>"契約申込回答"),"",TRIM(IF(O25="","負担金なし ","")&IF(U25="","工期なし ","")&IF(AND(O25<>"",OR(P25="",P25="不明")),"税区分不明 ","")&IF(AC25="low","信頼度low","")))) | AJ25: 未確認 | AM25: 開く | AN25: 【秘】接続検討回答書（G松江670） | AO25: 【秘】接続検討回答書（G松江670）
A26: 25 | B26: 1227 | C26: 1227_島根県出雲市知井宮町1360-1（JR西日本） | D26: 接続検討回答 | E26: 中国 | F26: 2026-09-04 | G26: 2026-06-19 | H26: 株式会社パワーエックス | I26: 島根県出雲市多枝町久村137-18（蓄電所） | J26: 1994 | K26: 1999 | L26: 6.6kV | M26: 知井宮変電所（配電用／発電側課金区分）、基幹: 松江変電所。適合検討書上の供給線路は多伎変電所 新設線 | N26: 6kV新設線（久村(分)18M1号柱より分岐）、配電用変圧器3次巻線22kV引出し＋22/6kV柱上変圧器2.5MVA | O26: 97700000 | P26: 税込 | Q26: =IF(O26="","",IF(P26="税抜",O26*1.1,O26)/10000) -> 9770 | R26: =IF(Q26="","不明",IF(Q26<=500,"〜500万",IF(Q26<=1000,"500〜1,000万",IF(Q26<=3000,"1,000〜3,000万","3,000万〜")))) -> 3,000万〜 | S26: 工事費負担金総額97.7百万円（消費税等8.8百万円含む）。税抜88.9百万円＝架空線8.7＋計量0.3＋上位系増強(基幹/地域/22kV)79.9。概算工事費総額341.1百万円(税込)。共用設備分は他事業者動向で変動 | U26: 55 | V26: =IF(U26="","不明",IF(U26<=6,"〜6ヶ月",IF(U26<=12,"7〜12ヶ月",IF(U26<=24,"13〜24ヶ月","25ヶ月〜")))) -> 25ヶ月〜 | W26: 工事費負担金の入金後55ヶ月程度（アクセス設備運用開始希望日2027/6/1には連系不可、連系時期調整要） | X26: 入金後55ヶ月程度（希望日2027年6月1日は不可） | Y26: 6kV新設線・高圧線増架/新設(RW-AL-OC200mm2)、高圧引込線ACSR-OC58mm2、SVR(3,000kVA)1台、22kVスイッチギヤ新設、22/6kV柱上変圧器2.5MVA新設、計量 | Z26: あり: 松江変 N-1電制装置設置(基幹)、110kV松江知井宮線・知井宮変110/66kV N-1電制装置(地域)、22kV配電関係(柱上変圧器新設他)。上位系統増強工事計79.9百万円(税抜負担分) | AA26: ノンファーム型接続（北松江変500/220kV、66kV知井宮大田線）、再給電方式(一定の順序)、ローカル系統混雑管理、N-1電制本格適用、力率93%一定(放電遅れ/充電進み)、充電停止の可能性、出力変化速度規定、早期連系追加対策(充電制限)は不要 | AB26: 接続検討回答日から1年を経過すると契約申込不可 | AC26: high | AE26: ファイル名・フォルダは知井宮町1360-1だが、本文は受付番号G松江767・発電場所『島根県出雲市多枝町久村137-18蓄電所』（申込者パワーエックス）。別案件の回答書が誤格納の可能性あり要確認。ZIP(59MB)は未展開 ／【要確認】本文は受付G松江767・発電場所 多伎町久村137-18＝1279案件の回答書。1227フォルダへの誤格納の可能性 | AF26: ○ | AG26: 運開希望日に間に合わず | AH26: =IF(AD26<>"","未読",IF(AND(D26<>"接続検討回答",D26<>"再接続検討",D26<>"契約申込回答"),"",TRIM(IF(O26="","負担金なし ","")&IF(U26="","工期なし ","")&IF(AND(O26<>"",OR(P26="",P26="不明")),"税区分不明 ","")&IF(AC26="low","信頼度low","")))) | AJ26: 未確認 | AM26: 開く | AN26: 1227（JR西日本）_接続検討回答書_島根県出雲市知井宮町1360-1.pdf | AO26: 01.接続検討申込書/1227（JR西日本）_接続検討回答書_島根県出雲市知井宮町1360-1.pdf
A27: 26 | B27: 1228 | C27: 1228_広島県福山市神島町142-2（JR西日本） | D27: 接続検討回答 | E27: 中国 | J27: 25000 | K27: 25000 | L27: 110kV | N27: 110kV特高事業者線（No.26/27/28鉄塔改造・新設・除却） | Q27: =IF(O27="","",IF(P27="税抜",O27*1.1,O27)/10000) | R27: =IF(Q27="","不明",IF(Q27<=500,"〜500万",IF(Q27<=1000,"500〜1,000万",IF(Q27<=3000,"1,000〜3,000万","3,000万〜")))) -> 不明 | V27: =IF(U27="","不明",IF(U27<=6,"〜6ヶ月",IF(U27<=12,"7〜12ヶ月",IF(U27<=24,"13〜24ヶ月","25ヶ月〜")))) -> 不明 | AC27: low | AD27: スキャン画像PDF(13MB)。テキスト抽出は工事概要図ページの断片のみ（【秘】接続検討回答書（G福山422）、110kV、25,000kW等）。サイズ超過のためダウンロード/OCR未実施 | AE27: 受付番号G福山422（中国電力NW）と推定。工事費負担金・工期・回答日は読取不可。同フォルダにZIP2件(52MB/59MB、20MB超で未展開)。110kV/66kVパターン両方の申込書あり | AF27: － | AH27: =IF(AD27<>"","未読",IF(AND(D27<>"接続検討回答",D27<>"再接続検討",D27<>"契約申込回答"),"",TRIM(IF(O27="","負担金なし ","")&IF(U27="","工期なし ","")&IF(AND(O27<>"",OR(P27="",P27="不明")),"税区分不明 ","")&IF(AC27="low","信頼度low","")))) -> 未読 | AJ27: 未確認 | AM27: 開く | AN27: 1228（JR西日本）_接続検討回答書_広島県福山市神島町142-2.pdf | AO27: 接続検討申込書（修正版_20260604）/1228（JR西日本）_接続検討回答書_広島県福山市神島町142-2.pdf
A28: 27 | B28: 1239 | C28: 1239_つくばみらい10MW（自然電力→三田証券） | D28: 接続検討回答 | E28: 東京 | F28: 2024-01-10 | G28: 2023-12-11 | H28: フェニックスエナジー | I28: 茨城県つくばみらい市野堀611-1 | J28: 10050 | K28: 10420 | L28: 66kV | M28: 常総変電所（275/66kV、基幹用変電所） | N28: 66kV取手線系の既設送電線（66kV神生ソーラー線）No.3鉄塔より1回線分岐 | O28: 131000000 | P28: 税込 | Q28: =IF(O28="","",IF(P28="税抜",O28*1.1,O28)/10000) -> 13100 | R28: =IF(Q28="","不明",IF(Q28<=500,"〜500万",IF(Q28<=1000,"500〜1,000万",IF(Q28<=3000,"1,000〜3,000万","3,000万〜")))) -> 3,000万〜 | S28: 工事費負担金総額131.0百万円（消費税等11.9百万円含む）。税抜119.1百万円＝架空線111.7＋通信4.0＋計量3.4。概算工事費138.8百万円(税込) | T28: 6543000 | U28: 18 | V28: =IF(U28="","不明",IF(U28<=6,"〜6ヶ月",IF(U28<=12,"7〜12ヶ月",IF(U28<=24,"13〜24ヶ月","25ヶ月〜")))) -> 13〜24ヶ月 | W28: 工事費負担金の入金後1年6ヶ月程度（契約申込受付後・損害実費弁償契約締結後2年10ヶ月程度）。運用開始希望日2024/10/1には連系不可 | X28: 工程表上アクセス設備供給可能時期2026/12 | Y28: 66kVアクセス線新設ACSR/AC160mm2×1回線0.04km、既設No.3鉄塔建替1基、電線移線0.22km、通信(受電状態自動伝達装置・光/メタル0.2km・ノンファーム設備)、VCT・計量器新設 | Z28: なし（上位系増強工事の記載なし） | AA28: ノンファーム型接続（275kV東京北線・鹿島線）、再給電方式(一定の順序)、N-1電制本格適用、1回線連系に伴う抑制、充電抑制/停止の可能性 | AB28: 接続検討回答日から1年を経過すると契約申込不可 | AC28: high | AE28: 受付番号JK23GHZ014338。金額・工期は2023年2月15日付接続検討回答書の値を記載と明記（再回答）。系統連系保証金6,543千円(税込)。同フォルダに受理済み系統連系申込書・保証金請求書・損害実費弁償契約書・供給承諾書(2025/04/14)・TEPCO打合せ資料(2025/3/25)あり。つくば_案件紹介資料.zip(44MB)未展開 | AF28: ○ | AG28: 運開希望日に間に合わず | AH28: =IF(AD28<>"","未読",IF(AND(D28<>"接続検討回答",D28<>"再接続検討",D28<>"契約申込回答"),"",TRIM(IF(O28="","負担金なし ","")&IF(U28="","工期なし ","")&IF(AND(O28<>"",OR(P28="",P28="不明")),"税区分不明 ","")&IF(AC28="low","信頼度low","")))) | AJ28: 未確認 | AM28: 開く | AN28: 20240110_接続検討回答書_つくばみらい.pdf | AO28: Document for Utility_電力関連資料/20240110_接続検討回答書_つくばみらい.pdf
A29: 28 | B29: 1244 | C29: 1244_高砂市阿弥陀町北池190 | D29: 接続検討回答 | E29: 関西 | F29: 2026-09-15 | G29: 2026-06-19 | H29: 株式会社パワーエックス（受付番号2026-82-00685） | I29: 兵庫県高砂市阿弥陀町北池字向沖190（(仮称)PX兵庫高砂市蓄電所） | J29: 1994 | K29: 95 | L29: 高圧 | M29: 曽根変電所 | N29: 天川配電線 | O29: 22800000 | P29: 税込 | Q29: =IF(O29="","",IF(P29="税抜",O29*1.1,O29)/10000) -> 2280 | R29: =IF(Q29="","不明",IF(Q29<=500,"〜500万",IF(Q29<=1000,"500〜1,000万",IF(Q29<=3000,"1,000〜3,000万","3,000万〜")))) -> 1,000〜3,000万 | S29: 工事費負担金の総額22.8百万円（消費税等相当額 百万円を含む＝金額欄空欄）。税抜20.7百万円＝架空線工事20.5＋計量設備工事0.2。概算工事費総額23.0百万円（税抜20.9）。一般負担上限超過0.0。 | U29: 30 | V29: =IF(U29="","不明",IF(U29<=6,"〜6ヶ月",IF(U29<=12,"7〜12ヶ月",IF(U29<=24,"13〜24ヶ月","25ヶ月〜")))) -> 25ヶ月〜 | W29: 工事費負担金の入金後 30ヶ月程度（概略工程表上は契約手続き期間を含まず）。運用開始希望日には連系不可、連系時期の調整が必要 | X29: 運用開始希望日2027年6月1日は連系不可。連系可能は工事費負担金入金から30ヶ月後 | Y29: 電柱新設3本・建替21本、高圧線新設1207m（アルミ120sq）・張替346m（銅5.0mm→アルミ120sq）、変圧器位置替13台、手動開閉器新設1・位置替2、自動開閉器位置替3、電圧調整器(SVR)新設1台3500kVA、高圧引込線20m、計量器2台・VCT1台・通信端局2台 | Z29: 上位系増強工事なし | AA29: ノンファーム型接続適用（主な混雑設備：北摂変電所500/275kV変圧器、停止作業94日/年）。基幹系は再給電方式（一定の順序）。早期連系追加対策（充電制限）は希望されたが現時点で不要と判定。出力変化速度5秒以上、力率一定制御0.9（整定値表）、自動再連系不可。蓄電池特別措置適用前提で算定。N-1電制本格適用。OCR・DGR保護協調は契約申込時に実施。 | AB29: 接続検討の回答日から1年を経過した場合は契約申込不可 | AC29: high | AE29: 最大自家消費電力95kWをcapacity_kw_chargeに記載（原文「最大自家消費電力：95kW」）。消費税額欄が空欄のため税込額は総額表記どおり。同一内容のPDFが案件フォルダ直下にも「接続検討申込に対する回答」(id 11wMRjmY9vR_k2lPjFjtXH2YMcHdAn1fg, 同サイズ515012B)として重複保存。 | AF29: ○ | AG29: 運開希望日に間に合わず | AH29: =IF(AD29<>"","未読",IF(AND(D29<>"接続検討回答",D29<>"再接続検討",D29<>"契約申込回答"),"",TRIM(IF(O29="","負担金なし ","")&IF(U29="","工期なし ","")&IF(AND(O29<>"",OR(P29="",P29="不明")),"税区分不明 ","")&IF(AC29="low","信頼度low","")))) | AJ29: 未確認 | AM29: 開く | AN29: 1244（藤栄建設）_接続検討申込に対する回答_兵庫県高砂市阿弥陀町北池字向沖190番.pdf | AO29: 03.接続検討申込書一式/1244（藤栄建設）_接続検討申込に対する回答_兵庫県高砂市阿弥陀町北池字向沖190番.pdf
A30: 29 | B30: 1279 | C30: 1279_島根県出雲市多伎町久村137-18（須山木材） | D30: 接続検討回答 | E30: 中国 | Q30: =IF(O30="","",IF(P30="税抜",O30*1.1,O30)/10000) | R30: =IF(Q30="","不明",IF(Q30<=500,"〜500万",IF(Q30<=1000,"500〜1,000万",IF(Q30<=3000,"1,000〜3,000万","3,000万〜")))) -> 不明 | V30: =IF(U30="","不明",IF(U30<=6,"〜6ヶ月",IF(U30<=12,"7〜12ヶ月",IF(U30<=24,"13〜24ヶ月","25ヶ月〜")))) -> 不明 | AC30: low | AD30: パスワード付き（PDFがユーザーパスワードで暗号化）。中国電力NWのパスワードは案件ごとにランダムに発行される（G松江691の通知メールで確認）。G松江767の『受領およびパスワードのご連絡』メールやパスワードのメモは、案件フォルダ内（再帰的に）、Drive全体の検索、Gmailのいずれにも見つからなかった | AE30: ファイル名(G松江767=中国電力NW松江の受付番号と推定)以外読めず全項目null。同フォルダに接続検討申込書xlsx・PCS仕様確認依頼書・単線結線図(2.5MVA 6.6kV 60Hz昇圧変圧器)・機器仕様書あり。パスワード入手後に再抽出要。 中国電力NWの受付担当（ネットワークサービスセンター）が発行した通知メールを入手するか、PDFを再送してもらう必要がある。 ／1227フォルダに同じG松江767の読める回答書あり（97.7百万円税込・入金後55ヶ月） | AF30: － | AH30: =IF(AD30<>"","未読",IF(AND(D30<>"接続検討回答",D30<>"再接続検討",D30<>"契約申込回答"),"",TRIM(IF(O30="","負担金なし ","")&IF(U30="","工期なし ","")&IF(AND(O30<>"",OR(P30="",P30="不明")),"税区分不明 ","")&IF(AC30="low","信頼度low","")))) -> 未読 | AJ30: 未確認 | AM30: 開く | AN30: 【秘】接続検討回答書（G松江767）.pdf | AO30: 02.接続検討/【秘】接続検討回答書（G松江767）.pdf
A31: 30 | B31: 1315 | C31: 1315_長野県上水内郡信濃町案件（本久） | D31: 接続検討回答 | E31: 中部 | F31: 2026-09-25 | G31: 2026-06-29 | H31: 株式会社パワーエックス | I31: 長野県上水内郡信濃町大字大井字市道端2272番1（（仮称）信濃蓄電所） | J31: 1998 | K31: 1999 | L31: 高圧 | M31: 牟礼変電所 | O31: 207000000 | P31: 税込 | Q31: =IF(O31="","",IF(P31="税抜",O31*1.1,O31)/10000) -> 20700 | R31: =IF(Q31="","不明",IF(Q31<=500,"〜500万",IF(Q31<=1000,"500〜1,000万",IF(Q31<=3000,"1,000〜3,000万","3,000万〜")))) -> 3,000万〜 | S31: 連系否。工事費負担金概算は207百万円以上（消費税等相当額を含む）。配変増強のみで負担可能上限額を超過、配電線以下工事は未検討・未計上 | V31: =IF(U31="","不明",IF(U31<=6,"〜6ヶ月",IF(U31<=12,"7〜12ヶ月",IF(U31<=24,"13〜24ヶ月","25ヶ月〜")))) -> 不明 | X31: 連系否 | Y31: 牟礼変電所（配電用変電所）の増強が必要 | Z31: 配電用変電所増強（牟礼変電所 熱容量超過）。費用が負担可能上限額を超過 | AA31: 連系否（理由:配変増強で負担金上限を超過するため）。代替案・連系可能最大受電電力の提示なし | AC31: high | AE31: 連系否の回答。受付番号AAD510748080。同一内容のファイルが03_電力申請/1315_接続検討申込みに対する回答について_中部電力NW_長野県上水内郡信濃町大字大井字市道端2279番4.pdf (id 1TBV299-lhcB9nz3p0aiYcfA5guFIkZlV, 同サイズ261852B) にも重複保存 | AF31: ○ | AG31: 連系不可 | AH31: =IF(AD31<>"","未読",IF(AND(D31<>"接続検討回答",D31<>"再接続検討",D31<>"契約申込回答"),"",TRIM(IF(O31="","負担金なし ","")&IF(U31="","工期なし ","")&IF(AND(O31<>"",OR(P31="",P31="不明")),"税区分不明 ","")&IF(AC31="low","信頼度low","")))) -> 工期なし | AJ31: 未確認 | AM31: 開く | AN31: 接続検討申込みに対する回答について | AO31: 接続検討申込みに対する回答について
A32: 31 | B32: 1316 | C32: 1316_北海道虻田郡喜茂別町(ソーラークリエート) | D32: 接続検討回答 | E32: 北海道 | F32: 2025-09-24 | G32: 2025-06-24 | H32: Akaysha Energy Japan株式会社（受付番号 託2024_2340） | I32: 北海道虻田郡喜茂別町中里376-1,379-1（（仮称）AKJ西双葉蓄電所） | J32: 400000 | K32: 411100 | L32: 275kV | M32: 275kV道央西幹線（西野変電所～西双葉開閉所） | N32: 275kV道央西幹線 No.111付近より2回線T分岐（2回線常時）、連系用開閉器にて架空線と気中接続 | O32: 814500000 | P32: 税込 | Q32: =IF(O32="","",IF(P32="税抜",O32*1.1,O32)/10000) -> 81450 | R32: =IF(Q32="","不明",IF(Q32<=500,"〜500万",IF(Q32<=1000,"500〜1,000万",IF(Q32<=3000,"1,000〜3,000万","3,000万〜")))) -> 3,000万〜 | S32: 工事費負担金総額814.5百万円（消費税等相当額74.1百万円を含む）。税抜740.4百万円＝架空線448.0＋通信設備203.0＋計量設備89.4（変電・給電は0）。概算工事費総額1,929.0百万円（税175.4含む、税抜1,753.6）。一般負担分923.8百万円、上限超過0。 | U32: 36 | V32: =IF(U32="","不明",IF(U32<=6,"〜6ヶ月",IF(U32<=12,"7〜12ヶ月",IF(U32<=24,"13〜24ヶ月","25ヶ月〜")))) -> 25ヶ月〜 | W32: 工事費負担金の入金後 3年程度（契約申込2025年10月・入金2027年2月までと仮定。ノンファームシステム開発期間は含まず） | X32: アクセス設備の運用開始可能日：2030年3月上旬（希望日2027年9月30日は連系不可） | Y32: 鉄塔新設2基・道央西幹線No.111建替、275kV連系線新設0.3km（ACSR/AC410mm2複導体×2回線）、No.110～112間移線0.8km、電磁誘導対策、保護継電装置取替4式（西双葉開閉所・西野変電所）、給電システム改修2式、通信装置・光ケーブル0.4km、特別精密級計量器2台。申込者側：STATCOM等無効電力補償装置 容量性230MVar・誘導性230MVar程度（概算） | Z32: 上位系統増強なし（基幹系増強の記載なし。変電・給電・通信の一般負担分のみ） | AA32: ノンファーム型接続適用（出力制御量に影響を与える主な設備：なし）、基幹系再給電方式。電圧変動対策（STATCOM等）要、送電線保護は主後一体型2系列、系統安定化システム設置の可能性、出力変動幅±400MWに対する変化率制約の可能性、N-1電制本格適用、順潮流側は作業停止時・系統状況により充電停止の可能性。 | AB32: 接続検討の回答日から1年を経過した場合は契約申込不可 | AC32: high | AE32: 申込者はAkaysha Energy Japan（PX/ソーラークリエートではない）。案件フォルダ「電力関連」に表紙・(1)工事検討結果・(2)計量設備回答書・(3)計量設備接続構造図・(4)運用制約による電圧変動対策・注意事項と一式で保管。土地契約書も「西双葉」名義で本案件(喜茂別町)と同一地点と推定。最大自家消費電力411,100kWをcapacity_kw_chargeに記載。 | AF32: ○ | AG32: 運開希望日に間に合わず | AH32: =IF(AD32<>"","未読",IF(AND(D32<>"接続検討回答",D32<>"再接続検討",D32<>"契約申込回答"),"",TRIM(IF(O32="","負担金なし ","")&IF(U32="","工期なし ","")&IF(AND(O32<>"",OR(P32="",P32="不明")),"税区分不明 ","")&IF(AC32="low","信頼度low","")))) | AJ32: 未確認 | AM32: 開く | AN32: 接続検討回答書（AKJ西双葉蓄電所_Akaysha Energy Japan㈱）.pdf | AO32: 電力関連/接続検討回答書（AKJ西双葉蓄電所_Akaysha Energy Japan㈱）.pdf
A33: 32 | B33: 1326 | C33: 1326_大栄工業_伊賀市案件 | D33: その他 | E33: 中部 | H33: 株式会社大栄工業 | I33: 三重県伊賀市予野字向川540番1（伊賀市予野540-1(蓄電池)） | O33: 13337722 | P33: 税込 | Q33: =IF(O33="","",IF(P33="税抜",O33*1.1,O33)/10000) -> 1333.7722 | R33: =IF(Q33="","不明",IF(Q33<=500,"〜500万",IF(Q33<=1000,"500〜1,000万",IF(Q33<=3000,"1,000〜3,000万","3,000万〜")))) -> 1,000〜3,000万 | S33: 連系工事費負担金 金13,337,722円（内消費税等1,212,520円）。系統連系保証金589,000円(2025/11/17支払済)を差引いた支払工事費負担金12,748,722円 | T33: 589000 | V33: =IF(U33="","不明",IF(U33<=6,"〜6ヶ月",IF(U33<=12,"7〜12ヶ月",IF(U33<=24,"13〜24ヶ月","25ヶ月〜")))) -> 不明 | W33: 支払工事費負担金は請求日から1ヶ月以内に支払 | Y33: 架空線工事一式、計量設備工事一式 | AC33: medium | AE33: 回答書ではなく連系工事費負担金契約書（中部電力PG、甲:大栄工業）。契約日の記載はOCR上『2006年7月6日』だが別通知では2026年7月16日付契約とされる。申込日は契約書上2025年10月27日付。回答書本体は1326_三重県伊賀市予野字向川540番2フォルダにあり（同一案件）。他に名義変更通知書docx2件 | AF33: － | AH33: =IF(AD33<>"","未読",IF(AND(D33<>"接続検討回答",D33<>"再接続検討",D33<>"契約申込回答"),"",TRIM(IF(O33="","負担金なし ","")&IF(U33="","工期なし ","")&IF(AND(O33<>"",OR(P33="",P33="不明")),"税区分不明 ","")&IF(AC33="low","信頼度low","")))) | AJ33: 未確認 | AM33: 開く | AN33: 工事負担金契約書.pdf | AO33: 工事負担金契約書.pdf
A34: 33 | B34: 1326 | C34: 1326_三重県伊賀市予野字向川540番2 | D34: 接続検討回答 | E34: 中部 | N34: 77kV荒木上野線（潮流実績グラフのみ判読） | Q34: =IF(O34="","",IF(P34="税抜",O34*1.1,O34)/10000) | R34: =IF(Q34="","不明",IF(Q34<=500,"〜500万",IF(Q34<=1000,"500〜1,000万",IF(Q34<=3000,"1,000〜3,000万","3,000万〜")))) -> 不明 | V34: =IF(U34="","不明",IF(U34<=6,"〜6ヶ月",IF(U34<=12,"7〜12ヶ月",IF(U34<=24,"13〜24ヶ月","25ヶ月〜")))) -> 不明 | AC34: low | AD34: スキャン画像PDF(5.8MB)。テキスト抽出はグラフ断片のみで本文読取不可（サイズのためダウンロード/OCR未実施） | AE34: 接続検討回答書（中部電力PG）と推定。後続の契約申込回答書(KK5390)に主要条件あり | AF34: － | AH34: =IF(AD34<>"","未読",IF(AND(D34<>"接続検討回答",D34<>"再接続検討",D34<>"契約申込回答"),"",TRIM(IF(O34="","負担金なし ","")&IF(U34="","工期なし ","")&IF(AND(O34<>"",OR(P34="",P34="不明")),"税区分不明 ","")&IF(AC34="low","信頼度low","")))) -> 未読 | AJ34: 未確認 | AM34: 開く | AN34: 予野接続検討回答.pdf | AO34: 予野接続検討回答.pdf
A35: 34 | B35: 1326 | C35: 1326_三重県伊賀市予野字向川540番2 | D35: その他 | E35: 中部 | F35: 2026-03-25 | H35: 株式会社大栄工業 | I35: 伊賀市予野540-2蓄電池 | Q35: =IF(O35="","",IF(P35="税抜",O35*1.1,O35)/10000) | R35: =IF(Q35="","不明",IF(Q35<=500,"〜500万",IF(Q35<=1000,"500〜1,000万",IF(Q35<=3000,"1,000〜3,000万","3,000万〜")))) -> 不明 | V35: =IF(U35="","不明",IF(U35<=6,"〜6ヶ月",IF(U35<=12,"7〜12ヶ月",IF(U35<=24,"13〜24ヶ月","25ヶ月〜")))) -> 不明 | AC35: high | AE35: 接続検討の要否確認結果：接続検討申込は不要（地番540-2→540-1へ変更可能）。工事費・工期の記載なし | AF35: － | AH35: =IF(AD35<>"","未読",IF(AND(D35<>"接続検討回答",D35<>"再接続検討",D35<>"契約申込回答"),"",TRIM(IF(O35="","負担金なし ","")&IF(U35="","工期なし ","")&IF(AND(O35<>"",OR(P35="",P35="不明")),"税区分不明 ","")&IF(AC35="low","信頼度low","")))) | AJ35: 未確認 | AM35: 開く | AN35: 接続検討の要否確認依頼に対する結果について.pdf | AO35: 接続検討の要否確認依頼に対する結果について.pdf
A36: 35 | B36: 1326 | C36: 1326_三重県伊賀市予野字向川540番2 | D36: 契約申込回答 | E36: 中部 | F36: 2026-05-28 | G36: 2025-12-02 | H36: 株式会社大栄工業 | I36: 三重県伊賀市予野字向川540番2 | J36: 1997 | K36: 1999 | L36: 6.6kV | M36: 予野変電所（配電用）、基幹系: 中勢275/77変電所 | N36: 予野変電所F25 56ﾇ191より分岐 | O36: 13337722 | P36: 税込 | Q36: =IF(O36="","",IF(P36="税抜",O36*1.1,O36)/10000) -> 1333.7722 | R36: =IF(Q36="","不明",IF(Q36<=500,"〜500万",IF(Q36<=1000,"500〜1,000万",IF(Q36<=3000,"1,000〜3,000万","3,000万〜")))) -> 1,000〜3,000万 | S36: 工事費負担金13,337,722円（消費税等1,212,520円含む）=概算工事費。税抜12,125,203円＝架空線11,973,208＋計量151,995。支払済系統連系保証金を差引いて請求 | T36: 589000 | U36: 29 | V36: =IF(U36="","不明",IF(U36<=6,"〜6ヶ月",IF(U36<=12,"7〜12ヶ月",IF(U36<=24,"13〜24ヶ月","25ヶ月〜")))) -> 25ヶ月〜 | W36: 工事費負担金の入金後29ヶ月程度（運用開始希望日2026/4/1は所要工期超過のため調整要） | Y36: 高圧線張替316m（5mm→OC-W60mm2）、高圧引込線新設10m、電圧調整器取替1台、計量器・VCT | Z36: 別紙工程表に『上位系統』『先行件名』の記載あり（詳細不明） | AA36: ノンファーム型接続（西部変500/275kV、新鈴鹿変275/77kV、77kV新鈴鹿壬生野線・荒木壬生野線・荒木上野線・白樫分岐線）、再給電方式(一定の順序)、ローカル系統混雑管理、N-1電制本格適用、PCS力率一定0.98、手動復帰、早期連系追加対策(充電制限)留意事項あり | AB36: 連系工事費負担金契約の締結意思を2026年6月29日までに表示（01案内） | AC36: high | AE36: 受付番号KK5390。同内容PDF(02 契約申込回答書（KK5390）.pdf, id=1P3ezrP3TiQAGK5rjy2e_o7HaJ0aL3Zyk)あり、本文はdocx版から読取。申込受付日2025/12/2は01案内記載（工事負担金契約書では2025/10/27付申込）。保証金589,000円は工事負担金契約書記載。別紙03〜06（取り決め・検討結果説明書・工事概要図・所要工期）同梱。連系工事費負担金契約締結済み(13,337,722円)、2026/9/16付で発電者名を大栄工業→パワーエックスに変更 | AF36: ○ | AH36: =IF(AD36<>"","未読",IF(AND(D36<>"接続検討回答",D36<>"再接続検討",D36<>"契約申込回答"),"",TRIM(IF(O36="","負担金なし ","")&IF(U36="","工期なし ","")&IF(AND(O36<>"",OR(P36="",P36="不明")),"税区分不明 ","")&IF(AC36="low","信頼度low","")))) | AJ36: 未確認 | AM36: 開く | AN36: 02 契約申込回答書（KK5390）.docx | AO36: 02 契約申込回答書（KK5390）.docx
A37: 36 | B37: 1326 | C37: 1326_三重県伊賀市予野字向川540番2 | D37: その他 | E37: 中部 | F37: 2026-09-16 | H37: 株式会社パワーエックス | I37: 伊賀市予野540-1（蓄電池） | Q37: =IF(O37="","",IF(P37="税抜",O37*1.1,O37)/10000) | R37: =IF(Q37="","不明",IF(Q37<=500,"〜500万",IF(Q37<=1000,"500〜1,000万",IF(Q37<=3000,"1,000〜3,000万","3,000万〜")))) -> 不明 | V37: =IF(U37="","不明",IF(U37<=6,"〜6ヶ月",IF(U37<=12,"7〜12ヶ月",IF(U37<=24,"13〜24ヶ月","25ヶ月〜")))) -> 不明 | AC37: high | AE37: 2026/7/16付連系工事費負担金契約の発電者名を株式会社大栄工業→株式会社パワーエックスへ変更した旨の通知（名義変更通知書2026/9/8付に基づく） | AF37: － | AH37: =IF(AD37<>"","未読",IF(AND(D37<>"接続検討回答",D37<>"再接続検討",D37<>"契約申込回答"),"",TRIM(IF(O37="","負担金なし ","")&IF(U37="","工期なし ","")&IF(AND(O37<>"",OR(P37="",P37="不明")),"税区分不明 ","")&IF(AC37="low","信頼度low","")))) | AJ37: 未確認 | AM37: 開く | AN37: 発電者名の変更について（お知らせ） | AO37: 発電者名の変更について（お知らせ）
A38: 37 | B38: 1412 | C38: 1412_秦野案件(セブンシーズアドバイザーズ) | D38: その他 | E38: 東京 | F38: 2026-08-28 | H38: セブンシーズアドバイザーズ株式会社 | O38: 143000000 | P38: 税込 | Q38: =IF(O38="","",IF(P38="税抜",O38*1.1,O38)/10000) -> 14300 | R38: =IF(Q38="","不明",IF(Q38<=500,"〜500万",IF(Q38<=1000,"500〜1,000万",IF(Q38<=3000,"1,000〜3,000万","3,000万〜")))) -> 3,000万〜 | S38: ①アクセス線新設（新設電源線増強） 概算負担金 143百万円（税込） | U38: 27 | V38: =IF(U38="","不明",IF(U38<=6,"〜6ヶ月",IF(U38<=12,"7〜12ヶ月",IF(U38<=24,"13〜24ヶ月","25ヶ月〜")))) -> 25ヶ月〜 | W38: 概算工期 2年3ケ月（起点の記載なし） | X38: 上位系統である変電所の設備対策が必要。この対策工事には少なくとも10年以上を要する可能性が高く、貴社蓄電所連系はその工事完了後 | Y38: アクセス線新設（新設電源線増強） | Z38: 有：順潮流時の送電容量確保のため上位系統変電所の設備対策が必要、少なくとも10年以上を要する可能性が高い | AA38: 最大受電電力に対する連系可否の確認であり接続供給契約の契約電力等を考慮した設備対策ではない。概算負担金は発電側最大受電電力が需要側契約電力を超過する想定で算出。送電線距離・架空/地中・周辺環境・周辺電源申込状況・電源線共用・制度変更による変動は未考慮 | AC38: high | AE38: 東京電力PGの『概算負担金・概算工期のお知らせ』（接続検討前の簡易回答。正式な接続検討回答ではない）。容量・電圧・変電所の記載なし。同フォルダ07.接続検討申込書一式に『秦野特高蓄電所』（66kV GIS仕様あり）の接続検討申込書xlsxがあるが回答書は未格納。概算工期2年3ヶ月とは別に上位系統対策10年以上が律速。 | AF38: － | AG38: 工期と別にバンク/上位系対策待ち | AH38: =IF(AD38<>"","未読",IF(AND(D38<>"接続検討回答",D38<>"再接続検討",D38<>"契約申込回答"),"",TRIM(IF(O38="","負担金なし ","")&IF(U38="","工期なし ","")&IF(AND(O38<>"",OR(P38="",P38="不明")),"税区分不明 ","")&IF(AC38="low","信頼度low","")))) | AJ38: 未確認 | AM38: 開く | AN38: 概算負担金・概算工期のお知らせ(（仮）セブンシーズ秦野グラウンド蓄電所) | AO38: 概算負担金・概算工期のお知らせ(（仮）セブンシーズ秦野グラウンド蓄電所)
A39: 38 | B39: 1437 | C39: 1437_大阪府大阪市平野区長吉長原４丁目１８−１０（タイヨー平野店） | D39: 接続検討回答 | E39: 関西 | F39: 2026-09-02 | G39: 2026-06-30 | H39: 株式会社リッチフィールド | I39: 大阪府大阪市平野区長吉長原4丁目18-19 | J39: 1994 | K39: 1999 | L39: 6.6kV | M39: 川辺変電所 | N39: F38 南川辺配電線（高圧引込線ACOCL120sq 3m） | O39: 6382300 | P39: 税込 | Q39: =IF(O39="","",IF(P39="税抜",O39*1.1,O39)/10000) -> 638.23 | R39: =IF(Q39="","不明",IF(Q39<=500,"〜500万",IF(Q39<=1000,"500〜1,000万",IF(Q39<=3000,"1,000〜3,000万","3,000万〜")))) -> 500〜1,000万 | S39: 工事費負担金の総額6,382.3千円（消費税等相当額を含む・額欄は空欄）／総額(消費税等相当額を除く)5,803.0千円。概算工事費総額6,599.5千円（税抜5,999.5千円）。主な項目: バンク逆潮流対策5,383.8千円。内訳列はテキスト抽出で崩れており要原本確認 | U39: 3 | V39: =IF(U39="","不明",IF(U39<=6,"〜6ヶ月",IF(U39<=12,"7〜12ヶ月",IF(U39<=24,"13〜24ヶ月","25ヶ月〜")))) -> 〜6ヶ月 | W39: バンク逆潮流対策工事：2031年4月以降連系可／架空線・計量装置工事：工事費負担金の入金後3ヶ月程度 | X39: バンク逆潮流対策工事完了後の2031年4月以降かつ工事費負担金入金から3ヶ月程度後 | Y39: バンク逆潮流対策1式、高圧引込線3m新設、引込用開閉器200A新設、計量器(受電・供給)・VCT・通信端局 | Z39: 上位系増強工事の記載なし（バンク逆潮流対策が律速、2031年4月以降） | AA39: ノンファーム型接続、再給電方式(一定の順序)、N-1電制本格適用、出力変化速度5秒以上、力率一定制御90%、早期連系追加対策(充電制限)は不要 | AB39: 接続検討回答日から1年を経過すると契約申込不可 | AC39: medium | AE39: 受付番号22-J0095。表紙に『＜第2案＞』とあり第1案はフォルダ内に無し。発電場所は回答書上18-19（フォルダ名は18-10）。工事費負担金の内訳列の対応がテキスト抽出で崩れているため内訳は要原本確認。税込判断は税抜総額5,803.0千円×1.1≒6,382.3千円による | AF39: ○ | AG39: 工期と別にバンク/上位系対策待ち | AH39: =IF(AD39<>"","未読",IF(AND(D39<>"接続検討回答",D39<>"再接続検討",D39<>"契約申込回答"),"",TRIM(IF(O39="","負担金なし ","")&IF(U39="","工期なし ","")&IF(AND(O39<>"",OR(P39="",P39="不明")),"税区分不明 ","")&IF(AC39="low","信頼度low","")))) | AJ39: 未確認 | AM39: 開く | AN39: 接続検討回答書 | AO39: 接続検討回答書
A40: 39 | C40: xxxx_熊本県阿蘇郡杖立（アークエル）設備変更_小嶋さん | D40: 接続検討回答 | E40: 九州 | Q40: =IF(O40="","",IF(P40="税抜",O40*1.1,O40)/10000) | R40: =IF(Q40="","不明",IF(Q40<=500,"〜500万",IF(Q40<=1000,"500〜1,000万",IF(Q40<=3000,"1,000〜3,000万","3,000万〜")))) -> 不明 | V40: =IF(U40="","不明",IF(U40<=6,"〜6ヶ月",IF(U40<=12,"7〜12ヶ月",IF(U40<=24,"13〜24ヶ月","25ヶ月〜")))) -> 不明 | AC40: low | AD40: 画像のみPDF（read_file_contentでテキスト空）かつ10.6MBでdownload_file_contentの10MB上限超過のためダウンロード不可 | AE40: ファイル名から2025-09-11付の接続検討回答書と推定（未読）。参考：同フォルダ『20260519_工事負担金請求書.pdf』(id 1TAxIersnPI0NGEzzlDPtXSDPtZfJJQ8g)は読取可で、九州電力送配電 日田配電事業所→アークエル株式会社、2026-05-19発行、使用場所 熊本県阿蘇郡小国町大字下城三俣263（杖立第一蓄電所）、工事件名『発電所新設申込に伴う系統連系工事』、請求金額34,251,663円（10%対象、うち消費税等3,113,787円）、支払期日2026-06-18、単独申込。概算工事金額34,516,663円（税込）=配電設備工事(電柱新設2本・高圧線585m・高圧引込線90m等)+バンク逆潮流対策 杖立変電所 1,320円/kW(税込)×1,999kW=2,638,680円。フォルダには接続検討申込書・接続供給/発電量調整供給申込書xlsxもあり。サブフォルダ『イノスタ提出済み/02.接続検討』には大阪府池田市桃園案件の申込書類が混在 | AF40: － | AH40: =IF(AD40<>"","未読",IF(AND(D40<>"接続検討回答",D40<>"再接続検討",D40<>"契約申込回答"),"",TRIM(IF(O40="","負担金なし ","")&IF(U40="","工期なし ","")&IF(AND(O40<>"",OR(P40="",P40="不明")),"税区分不明 ","")&IF(AC40="low","信頼度low","")))) -> 未読 | AJ40: 未確認 | AM40: 開く | AN40: 20250911_接続検討回答書_杖立_(1)_1.pdf | AO40: 20250911_接続検討回答書_杖立_(1)_1.pdf
A41: 40 | C41: xxxx_熊本県玉名郡（CIP）210MW設備変更_小嶋さん | D41: 契約申込回答 | E41: 九州 | F41: 2025-07-22 | G41: 2025-01-23 | H41: 株式会社西日本パワーエナジー | I41: 熊本県玉名郡南関町大字豊永2864他48筆（熊本県南関町A蓄電所） | J41: 67668 | K41: 71861 | L41: 110kV | M41: 三池変電所/西山鹿変電所/南関変電所（110kV西山鹿三池線） | N41: 110kV西山鹿三池線 №52鉄塔分岐（1L連系）、ACSR160mm2連系線 | O41: 311400000 | P41: 税込 | Q41: =IF(O41="","",IF(P41="税抜",O41*1.1,O41)/10000) -> 31140 | R41: =IF(Q41="","不明",IF(Q41<=500,"〜500万",IF(Q41<=1000,"500〜1,000万",IF(Q41<=3000,"1,000〜3,000万","3,000万〜")))) -> 3,000万〜 | S41: 工事費負担金の総額311.4百万円（消費税等相当額28.3百万円を含む）／税抜283.1百万円=単独負担266.8(架空線223.0・通信18.1・計量25.7)+共同負担16.3(架空線0.9・変電15.2・通信0.2)。概算工事費総額529.9百万円（税込） | T41: 15725000 | U41: 32 | V41: =IF(U41="","不明",IF(U41<=6,"〜6ヶ月",IF(U41<=12,"7〜12ヶ月",IF(U41<=24,"13〜24ヶ月","25ヶ月〜")))) -> 25ヶ月〜 | W41: 工事費負担金の入金後 2年8か月程度（当社施工範囲のみ、手続遅延時は更に要する可能性） | X41: 運用開始希望日2028年6月1日。連系時期は別途協議 | Y41: 西山鹿三池線№52鉄塔建替、TACSR610張替0.8km(№52～53)、連系線0.1km新設、光ケーブル13km(西山鹿変電所～発電所)、給電情報伝送装置、PCM+DZ保護装置取替(三池・南関・西山鹿)、計量装置 | Z41: 基幹系統増強なし。三池変電所(220kV)N-1故障時過負荷対策としてC蓄電所に転送遮断装置設置。PCM取替(三池・西山鹿・南関) | AA41: ノンファーム型接続（出力制御影響:220kV三池変電所）、再給電方式、ローカル系統混雑管理システム(2027年4月頃運開予定)によるオンライン制御、N-1電制本格適用、連系点力率一定制御+出力変化速度4%MW/分以下（緩和には±35MVA無効電力調整装置）、単独運転検出機能オフ、特措適用(有)前提、充電停止あり | AB41: 工事費負担金請求から原則1か月以内に入金（未入金で契約解除の場合あり）。A/B/C蓄電所の同時連系が前提（いずれか不成立で回答無効） | AC41: high | AE41: 発電量調整供給契約申込み(契約申込)に対する技術検討回答書（契ネ契第2182号, 2025-07-22付）。回答書本体の回答日欄は空欄『2025年 月 日』。ファイル名末尾r（再提出/改訂版か）。案件フォルダ名は『設備変更』だが本書は当初の契約申込回答。A/B/C 3蓄電所計約203MW。同フォルダに連系承諾通知(№23251)・工事費負担金契約書A(2025-08-25)・Amended grid construction cost agreement(2026-02-09)あり。deposit_yenは同フォルダ工事費負担金契約書(2025-08-25締結/2026-02-09一部変更)記載の2025-04-15支払済保証金。同契約書の工事費負担金見積額は回答書と同額、需給開始希望日2028-06-30、分割入金予定（本体工事2027年1月等） | AF41: ○ | AH41: =IF(AD41<>"","未読",IF(AND(D41<>"接続検討回答",D41<>"再接続検討",D41<>"契約申込回答"),"",TRIM(IF(O41="","負担金なし ","")&IF(U41="","工期なし ","")&IF(AND(O41<>"",OR(P41="",P41="不明")),"税区分不明 ","")&IF(AC41="low","信頼度low","")))) | AJ41: 未確認 | AM41: 開く | AN41: 【株式会社西日本パワーエナジーさま】技術検討回答書(23251)r.pdf | AO41: 【株式会社西日本パワーエナジーさま】技術検討回答書(23251)r.pdf
A42: 41 | C42: xxxx_熊本県玉名郡（CIP）210MW設備変更_小嶋さん | D42: 契約申込回答 | E42: 九州 | F42: 2025-07-22 | G42: 2025-01-23 | H42: 株式会社西日本パワーエナジー | I42: 熊本県玉名郡南関町大字豊永2760他41筆（熊本県南関町B蓄電所） | J42: 67668 | K42: 71861 | L42: 110kV | M42: 三池変電所/西山鹿変電所/南関変電所（110kV西山鹿三池線） | N42: 110kV西山鹿三池線 新№51分岐（2L連系）、ACSR160mm2連系線 | O42: 186100000 | P42: 税込 | Q42: =IF(O42="","",IF(P42="税抜",O42*1.1,O42)/10000) -> 18610 | R42: =IF(Q42="","不明",IF(Q42<=500,"〜500万",IF(Q42<=1000,"500〜1,000万",IF(Q42<=3000,"1,000〜3,000万","3,000万〜")))) -> 3,000万〜 | S42: 工事費負担金の総額186.1百万円（消費税等相当額16.9百万円を含む）／税抜169.2百万円=単独負担55.6(架空線11.8・通信18.1・計量25.7)+共同負担113.6(架空線98.2・変電15.2・通信0.2)。概算工事費総額515.4百万円（税込） | T42: 9560000 | U42: 32 | V42: =IF(U42="","不明",IF(U42<=6,"〜6ヶ月",IF(U42<=12,"7〜12ヶ月",IF(U42<=24,"13〜24ヶ月","25ヶ月〜")))) -> 25ヶ月〜 | W42: 工事費負担金の入金後 2年8か月程度（当社施工範囲のみ、手続遅延時は更に要する可能性） | X42: 運用開始希望日2028年6月1日。連系時期は別途協議 | Y42: 西山鹿三池線№51鉄塔建替(共同負担、182.8百万円の50%)、TACSR610張替0.8km、連系線0.1km、光ケーブル13km、給電情報伝送装置、PCM+DZ保護装置取替、計量装置 | Z42: 基幹系統増強なし。三池変電所(220kV)N-1故障時過負荷対策としてC蓄電所に転送遮断装置設置。PCM取替(三池・西山鹿・南関) | AA42: ノンファーム型接続（出力制御影響:220kV三池変電所）、再給電方式、ローカル系統混雑管理システム(2027年4月頃運開予定)によるオンライン制御、N-1電制本格適用、連系点力率一定制御+出力変化速度4%MW/分以下（緩和には±35MVA無効電力調整装置）、単独運転検出機能オフ、特措適用(有)前提、充電停止あり | AB42: 工事費負担金請求から原則1か月以内に入金（未入金で契約解除の場合あり）。A/B/C蓄電所の同時連系が前提（いずれか不成立で回答無効） | AC42: high | AE42: 発電量調整供給契約申込みに対する技術検討回答書（契ネ契第2183号, 2025-07-22付）。回答日欄空欄。A/C蓄電所同時連系前提。同フォルダに連系承諾通知(№23252)・工事費負担金契約書Bあり。deposit_yenは同フォルダ工事費負担金契約書(2025-08-25締結/2026-02-09一部変更)記載の2025-04-15支払済保証金。同契約書の工事費負担金見積額は回答書と同額、需給開始希望日2028-06-30、分割入金予定（本体工事2027年1月等） | AF42: ○ | AH42: =IF(AD42<>"","未読",IF(AND(D42<>"接続検討回答",D42<>"再接続検討",D42<>"契約申込回答"),"",TRIM(IF(O42="","負担金なし ","")&IF(U42="","工期なし ","")&IF(AND(O42<>"",OR(P42="",P42="不明")),"税区分不明 ","")&IF(AC42="low","信頼度low","")))) | AJ42: 未確認 | AM42: 開く | AN42: 【株式会社西日本パワーエナジーさま】技術検討回答書(23252)r.pdf | AO42: 【株式会社西日本パワーエナジーさま】技術検討回答書(23252)r.pdf
A43: 42 | C43: xxxx_熊本県玉名郡（CIP）210MW設備変更_小嶋さん | D43: 契約申込回答 | E43: 九州 | F43: 2025-07-22 | G43: 2025-01-23 | H43: 株式会社西日本パワーエナジー | I43: 熊本県玉名郡南関町大字豊永2753他47筆（熊本県南関町C蓄電所） | J43: 67668 | K43: 71861 | L43: 110kV | M43: 三池変電所/西山鹿変電所/南関変電所（110kV西山鹿三池線） | N43: 110kV西山鹿三池線 新№51分岐（1L連系）、ACSR160mm2連系線 | O43: 182900000 | P43: 税込 | Q43: =IF(O43="","",IF(P43="税抜",O43*1.1,O43)/10000) -> 18290 | R43: =IF(Q43="","不明",IF(Q43<=500,"〜500万",IF(Q43<=1000,"500〜1,000万",IF(Q43<=3000,"1,000〜3,000万","3,000万〜")))) -> 3,000万〜 | S43: 工事費負担金の総額182.9百万円（消費税等相当額16.6百万円を含む）／税抜166.3百万円=単独負担68.1(架空線11.8・通信30.6・計量25.7)+共同負担98.2(架空線)。概算工事費総額450.1百万円（税込） | T43: 9190000 | U43: 32 | V43: =IF(U43="","不明",IF(U43<=6,"〜6ヶ月",IF(U43<=12,"7〜12ヶ月",IF(U43<=24,"13〜24ヶ月","25ヶ月〜")))) -> 25ヶ月〜 | W43: 工事費負担金の入金後 2年8か月程度（当社施工範囲のみ、手続遅延時は更に要する可能性） | X43: 運用開始希望日2028年6月1日。連系時期は別途協議 | Y43: 西山鹿三池線№51鉄塔建替(共同負担)、TACSR610張替、連系線0.1km、光ケーブル(西山鹿・三池～発電所)、三池変電所転送遮断装置(送信盤)+C蓄電所受信盤、励磁突入電流抑制装置(貴社)、給電情報伝送装置、計量装置 | Z43: 三池変電所220/110kV主要変圧器N-1故障時の順潮流(充電)過負荷対策として転送遮断装置(三池ss送信盤19.9百万円等)設置。基幹系統増強なし | AA43: ノンファーム型接続（出力制御影響:220kV三池変電所）、再給電方式、ローカル系統混雑管理システム(2027年4月頃運開予定)によるオンライン制御、N-1電制本格適用、連系点力率一定制御+出力変化速度4%MW/分以下（緩和には±35MVA無効電力調整装置）、単独運転検出機能オフ、特措適用(有)前提、充電停止あり | AB43: 工事費負担金請求から原則1か月以内に入金（未入金で契約解除の場合あり）。A/B/C蓄電所の同時連系が前提（いずれか不成立で回答無効） | AC43: high | AE43: 発電量調整供給契約申込みに対する技術検討回答書（契ネ契第2184号, 2025-07-22付）。回答日欄空欄。A/B蓄電所同時連系前提。主要変圧器事故時の充電停止(転送遮断)条件あり。同フォルダに連系承諾通知(№23253)・工事費負担金契約書Cあり。deposit_yenは同フォルダ工事費負担金契約書(2025-08-25締結/2026-02-09一部変更)記載の2025-04-15支払済保証金。同契約書の工事費負担金見積額は回答書と同額、需給開始希望日2028-06-30、分割入金予定（本体工事2027年1月等） | AF43: ○ | AH43: =IF(AD43<>"","未読",IF(AND(D43<>"接続検討回答",D43<>"再接続検討",D43<>"契約申込回答"),"",TRIM(IF(O43="","負担金なし ","")&IF(U43="","工期なし ","")&IF(AND(O43<>"",OR(P43="",P43="不明")),"税区分不明 ","")&IF(AC43="low","信頼度low","")))) | AJ43: 未確認 | AM43: 開く | AN43: 【株式会社西日本パワーエナジーさま】技術検討回答書(23253)r.pdf | AO43: 【株式会社西日本パワーエナジーさま】技術検討回答書(23253)r.pdf
A44: 43 | C44: xxxx_熊本県玉名郡（CIP）210MW設備変更_小嶋さん | D44: 契約申込回答 | E44: 九州 | F44: 2025-09-03 | G44: 2025-01-23 | H44: 株式会社西日本パワーエナジー | I44: 熊本県玉名郡南関町大字豊永2864他48筆（熊本県南関町A蓄電所） | J44: 67668 | L44: 110kV | M44: 三池変電所（系統設備効率化割引A対象変電所、割引A-2） | P44: 不明 | Q44: =IF(O44="","",IF(P44="税抜",O44*1.1,O44)/10000) | R44: =IF(Q44="","不明",IF(Q44<=500,"〜500万",IF(Q44<=1000,"500〜1,000万",IF(Q44<=3000,"1,000〜3,000万","3,000万〜")))) -> 不明 | S44: 承諾通知本文には工事費負担金の記載なし（技術検討回答書記載額は税込311.4百万円） | T44: 15725000 | V44: =IF(U44="","不明",IF(U44<=6,"〜6ヶ月",IF(U44<=12,"7〜12ヶ月",IF(U44<=24,"13〜24ヶ月","25ヶ月〜")))) -> 不明 | AA44: 契約申込みを承諾、送配電等業務指針第97条に基づき連系予約確定。系統設備効率化割引A：A-2（三池変電所） | AC44: high | AE44: 連系承諾通知（契ネ契第2364号）。工事費負担金・工期は同案件の技術検討回答書(id 1riz0ItXhH1BagUR_wsc_NedwbzpVEkEE)参照。deposit_yenは工事費負担金契約書記載の支払済保証金 | AF44: － | AH44: =IF(AD44<>"","未読",IF(AND(D44<>"接続検討回答",D44<>"再接続検討",D44<>"契約申込回答"),"",TRIM(IF(O44="","負担金なし ","")&IF(U44="","工期なし ","")&IF(AND(O44<>"",OR(P44="",P44="不明")),"税区分不明 ","")&IF(AC44="low","信頼度low","")))) -> 負担金なし 工期なし | AJ44: 未確認 | AM44: 開く | AN44: 【株式会社西日本パワーエナジーさま】発電設備等に関する契約申込みの回答について(承諾)(№23251).pdf | AO44: 連系承諾資料等/【株式会社西日本パワーエナジーさま】発電設備等に関する契約申込みの回答について(承諾)(№23251).pdf
A45: 44 | C45: xxxx_熊本県玉名郡（CIP）210MW設備変更_小嶋さん | D45: 契約申込回答 | E45: 九州 | F45: 2025-09-03 | G45: 2025-01-23 | H45: 株式会社西日本パワーエナジー | I45: 熊本県玉名郡南関町大字豊永2760他41筆（熊本県南関町B蓄電所） | J45: 67668 | L45: 110kV | M45: 三池変電所（系統設備効率化割引A対象変電所、割引A-2） | P45: 不明 | Q45: =IF(O45="","",IF(P45="税抜",O45*1.1,O45)/10000) | R45: =IF(Q45="","不明",IF(Q45<=500,"〜500万",IF(Q45<=1000,"500〜1,000万",IF(Q45<=3000,"1,000〜3,000万","3,000万〜")))) -> 不明 | S45: 承諾通知本文には工事費負担金の記載なし（技術検討回答書記載額は税込186.1百万円） | T45: 9560000 | V45: =IF(U45="","不明",IF(U45<=6,"〜6ヶ月",IF(U45<=12,"7〜12ヶ月",IF(U45<=24,"13〜24ヶ月","25ヶ月〜")))) -> 不明 | AA45: 契約申込みを承諾、送配電等業務指針第97条に基づき連系予約確定。系統設備効率化割引A：A-2（三池変電所） | AC45: high | AE45: 連系承諾通知（契ネ契第2365号）。工事費負担金・工期は同案件の技術検討回答書(id 14-LRbl6d5XE2FQVqa_iv19oM0sT7vOiJ)参照。deposit_yenは工事費負担金契約書記載の支払済保証金 | AF45: － | AH45: =IF(AD45<>"","未読",IF(AND(D45<>"接続検討回答",D45<>"再接続検討",D45<>"契約申込回答"),"",TRIM(IF(O45="","負担金なし ","")&IF(U45="","工期なし ","")&IF(AND(O45<>"",OR(P45="",P45="不明")),"税区分不明 ","")&IF(AC45="low","信頼度low","")))) -> 負担金なし 工期なし | AJ45: 未確認 | AM45: 開く | AN45: 【株式会社西日本パワーエナジーさま】発電設備等に関する契約申込みの回答について(承諾)(№23252).pdf | AO45: 連系承諾資料等/【株式会社西日本パワーエナジーさま】発電設備等に関する契約申込みの回答について(承諾)(№23252).pdf
A46: 45 | C46: xxxx_熊本県玉名郡（CIP）210MW設備変更_小嶋さん | D46: 契約申込回答 | E46: 九州 | F46: 2025-09-03 | G46: 2025-01-23 | H46: 株式会社西日本パワーエナジー | I46: 熊本県玉名郡南関町大字豊永2753他47筆（熊本県南関町C蓄電所） | J46: 67668 | L46: 110kV | M46: 三池変電所（系統設備効率化割引A対象変電所、割引A-2） | P46: 不明 | Q46: =IF(O46="","",IF(P46="税抜",O46*1.1,O46)/10000) | R46: =IF(Q46="","不明",IF(Q46<=500,"〜500万",IF(Q46<=1000,"500〜1,000万",IF(Q46<=3000,"1,000〜3,000万","3,000万〜")))) -> 不明 | S46: 承諾通知本文には工事費負担金の記載なし（技術検討回答書記載額は税込182.9百万円） | T46: 9190000 | V46: =IF(U46="","不明",IF(U46<=6,"〜6ヶ月",IF(U46<=12,"7〜12ヶ月",IF(U46<=24,"13〜24ヶ月","25ヶ月〜")))) -> 不明 | AA46: 契約申込みを承諾、送配電等業務指針第97条に基づき連系予約確定。系統設備効率化割引A：A-2（三池変電所） | AC46: high | AE46: 連系承諾通知（契ネ契第2366号）。工事費負担金・工期は同案件の技術検討回答書(id 1GYWYB5DfXsmFzEkvUVWAltoOJIdlGKxL)参照。deposit_yenは工事費負担金契約書記載の支払済保証金 | AF46: － | AH46: =IF(AD46<>"","未読",IF(AND(D46<>"接続検討回答",D46<>"再接続検討",D46<>"契約申込回答"),"",TRIM(IF(O46="","負担金なし ","")&IF(U46="","工期なし ","")&IF(AND(O46<>"",OR(P46="",P46="不明")),"税区分不明 ","")&IF(AC46="low","信頼度low","")))) -> 負担金なし 工期なし | AJ46: 未確認 | AM46: 開く | AN46: 【株式会社西日本パワーエナジーさま】発電設備等に関する契約申込みの回答について(承諾)(№23253).pdf | AO46: 連系承諾資料等/【株式会社西日本パワーエナジーさま】発電設備等に関する契約申込みの回答について(承諾)(№23253).pdf
A47: 46 | B47: 005 | C47: 【保留】/005_鏡石町笠石117-2他（福島県）_高圧蓄電所 | D47: 接続検討回答 | E47: 東北 | F47: 2024-09-06 | G47: 2024-06-07 | H47: 株式会社パワーエックス（PX鏡石BESS1, 受付番号A62324006） | I47: 福島県鏡石町笠石117-2他 | J47: 1996 | K47: 1995 | L47: 高圧（高圧版回答書） | O47: 900000 | P47: 税込 | Q47: =IF(O47="","",IF(P47="税抜",O47*1.1,O47)/10000) -> 90 | R47: =IF(Q47="","不明",IF(Q47<=500,"〜500万",IF(Q47<=1000,"500〜1,000万",IF(Q47<=3000,"1,000〜3,000万","3,000万〜")))) -> 〜500万 | S47: 工事費負担金の総額 0.9百万円(消費税等相当額 0.1百万円を含む)、税抜0.8百万円（架空線0.5/計量0.3）。概算工事費の総額 1.1百万円(税込)。別紙「概算工事費及び工事費負担金の総額」より | U47: 6 | V47: =IF(U47="","不明",IF(U47<=6,"〜6ヶ月",IF(U47<=12,"7〜12ヶ月",IF(U47<=24,"13〜24ヶ月","25ヶ月〜")))) -> 〜6ヶ月 | W47: 配電設備 6か月程度 ／ 混雑管理システム(ローカル系統) 運開時期は別途HP等でお知らせします。（契約手続き期間は含まず。工事費負担金入金後の期間） | X47: 希望2025年9月8日(別途協議)。回答日＋配電設備工期6か月の単純計算で2025年3月頃（契約手続き期間は含まず） | Y47: 高圧引込線30m(120mm2)、変圧器タップ切替1箇所、計量器2台・計器用変成器1台(200A) | Z47: 上位系統増強工事なし（対象設備表の上位系統増強工事・バンク逆潮流対策は空欄） | AA47: ノンファーム型接続適用（基幹系統:別紙1-1グループ[福島4]、ローカル系統:154kV第一、第二福島線(0626)、154kV日和田線(0632)、須賀川変電所154/66kV主要変圧器(604)）、再給電方式（一定の順序）、PCS力率一定制御 96%（有効出力1,998kW程度）、非認証PCSの実機試験成績書提出、出力制御設定の確認書類提出、N-1電制本格適用、運用上の制約あり（作業停止時等の発電抑制・停止）、前提条件: 力率一定制御96% | AB47: 接続検討の回答日から1年を経過した場合は契約申込不可 | AC47: high | AE47: 状態: 保留（【保留】フォルダ内）。検討対象年度2023~2024年度。 | AF47: － | AH47: =IF(AD47<>"","未読",IF(AND(D47<>"接続検討回答",D47<>"再接続検討",D47<>"契約申込回答"),"",TRIM(IF(O47="","負担金なし ","")&IF(U47="","工期なし ","")&IF(AND(O47<>"",OR(P47="",P47="不明")),"税区分不明 ","")&IF(AC47="low","信頼度low","")))) | AJ47: 未確認 | AM47: 開く | AN47: 【接続検討回答書】No005_鏡石町笠石117-2他（A62324006）.pdf | AO47: 03_電力/02_接続検討/04_回答/【接続検討回答書】No005_鏡石町笠石117-2他（A62324006）.pdf
A48: 47 | B48: 005 | C48: 【保留】/005_鏡石町笠石117-2他（福島県）_高圧蓄電所 | D48: 再接続検討 | E48: 東北 | F48: 2025-12-02 | G48: 2025-09-02 | H48: 株式会社パワーエックス（PX鏡石BESS1, 受付番号A62325462） | I48: 福島県鏡石町笠石117-2他 | J48: 1996 | K48: 1995 | L48: 高圧（高圧版回答書） | O48: 4577100000 | P48: 税込 | Q48: =IF(O48="","",IF(P48="税抜",O48*1.1,O48)/10000) -> 457710 | R48: =IF(Q48="","不明",IF(Q48<=500,"〜500万",IF(Q48<=1000,"500〜1,000万",IF(Q48<=3000,"1,000〜3,000万","3,000万〜")))) -> 3,000万〜 | S48: 工事費負担金の総額 4,577.1百万円(消費税等相当額 416.1百万円を含む)、税抜4,161.0百万円（架空線13.5/計量0.3/一般負担の上限超過分4,147.2）。概算工事費の総額 4,681.7百万円(税込)。別紙「概算工事費及び工事費負担金の総額」より | U48: 8 | V48: =IF(U48="","不明",IF(U48<=6,"〜6ヶ月",IF(U48<=12,"7〜12ヶ月",IF(U48<=24,"13〜24ヶ月","25ヶ月〜")))) -> 7〜12ヶ月 | W48: 配電設備工事 8か月程度 ／ 上位系統増強工事 (先行する系統利用者の為の増強工事を含む) 10年2か月 ／ 混雑管理システム(ローカル系統) 運開時期は別途HP等でお知らせします。（契約手続き期間は含まず。工事費負担金入金後の期間） | X48: 希望2025年9月8日。回答日＋配電設備工期8か月の単純計算で2026年8月頃（契約手続き期間は含まず）→希望日に間に合わず。上位系統増強工事 (先行する系統利用者の為の増強工事を含む) 10年2か月は別途 | Y48: 高圧引込線30m(AL-ACSR-L120mm2)、柱上変圧器タップ変更13箇所、電圧調整器1台(逆潮流対応II型SVR 5,000kVA)、計量器2台・計器用変成器1台(200A)、上位系統増強工事1式（須賀川(変)MT2台） | Z48: あり: 須賀川(変)275/154kV主要変圧器取替(2台)が貴社連系のため必要。先行利用者の連系に伴い須賀川(変)・東福島(変)275/154kV主要変圧器増設(各1台)ほかを予定（当社工事・当社負担）。上位系統増強工事10年2か月（先行利用者向け増強を含む）。一般負担の上限超過分4,147.2百万円 | AA48: ノンファーム型接続適用（基幹系統:別紙1-1グループ[福島4]、ローカル系統:154kV第一、第二福島線(0626)、154kV日和田線(0632)、須賀川変電所154/66kV主要変圧器(604)）、再給電方式（一定の順序）、PCS力率一定制御 97%、非認証PCSの実機試験成績書提出、出力制御設定の確認書類提出、早期連系追加対策(充電制限)は適用不可、N-1電制本格適用、運用上の制約あり（作業停止時等の発電抑制・停止）、前提条件: 先行する他発電設備が連系すること | AB48: 接続検討の回答日から1年を経過した場合は契約申込不可 | AC48: high | AE48: 状態: 保留（【保留】フォルダ内）。検討対象年度2024~2025年度。負担金は上位系統増強に係る一般負担の上限超過分を含むため極めて高額。格納フォルダは「12_回答（2回目）」。ファイル名は「接続検討回答書」だが2回目の回答のため種別は再接続検討とした。初回回答(A62324006, 2024-09-06)あり。運用開始希望日(2025年9月8日)は回答日より前の日付のまま。 | AF48: ○ | AG48: 運開希望日に間に合わず / 工期と別にバンク/上位系対策待ち | AH48: =IF(AD48<>"","未読",IF(AND(D48<>"接続検討回答",D48<>"再接続検討",D48<>"契約申込回答"),"",TRIM(IF(O48="","負担金なし ","")&IF(U48="","工期なし ","")&IF(AND(O48<>"",OR(P48="",P48="不明")),"税区分不明 ","")&IF(AC48="low","信頼度low","")))) | AJ48: 未確認 | AM48: 開く | AN48: 【接続検討回答書】No005_鏡石町笠石117-2他（A62325462）.pdf | AO48: 03_電力/02_接続検討/12_回答（2回目）/【接続検討回答書】No005_鏡石町笠石117-2他（A62325462）.pdf
A49: 48 | B49: 006 | C49: 006_須賀川市江持字喜太夫70（福島県）_高圧蓄電所 | D49: 接続検討回答 | E49: 東北 | F49: 2024-07-16 | G49: 2024-04-16 | H49: 株式会社パワーエックス（PX須賀川BESS1, 受付番号A62324001） | I49: 福島県須賀川市江持字喜太夫70 | J49: 1818 | K49: 1980 | L49: 高圧（高圧版回答書） | O49: 26600000 | P49: 税込 | Q49: =IF(O49="","",IF(P49="税抜",O49*1.1,O49)/10000) -> 2660 | R49: =IF(Q49="","不明",IF(Q49<=500,"〜500万",IF(Q49<=1000,"500〜1,000万",IF(Q49<=3000,"1,000〜3,000万","3,000万〜")))) -> 1,000〜3,000万 | S49: 工事費負担金の総額 26.6百万円(消費税等相当額 2.4百万円を含む)、税抜24.2百万円（架空線17.5/地中線6.4/計量0.3）。概算工事費の総額 26.8百万円(税込)。別紙「概算工事費及び工事費負担金の総額」より | U49: 24 | V49: =IF(U49="","不明",IF(U49<=6,"〜6ヶ月",IF(U49<=12,"7〜12ヶ月",IF(U49<=24,"13〜24ヶ月","25ヶ月〜")))) -> 13〜24ヶ月 | W49: 配電設備 24か月程度 ／ 混雑管理システム(ローカル系統) 運開時期は別途HP等でお知らせします。（契約手続き期間は含まず。工事費負担金入金後の期間） | X49: 希望2025年8月10日(別途協議)。回答日＋配電設備工期24か月の単純計算で2026年7月頃（契約手続き期間は含まず）→希望日に間に合わず | Y49: 電柱2本(14m)、高圧線1,956m／57m(120mm2・200mm2)、高圧引込線30m、開閉器2台(FTAS表示器)、電圧調整器1台(5000kVA)、高圧ケーブル280m(250mm2)、計量器2台・計器用変成器1台(200A)。電圧調整器取替、電柱建替、高圧線新設・張替、開閉器改造 | Z49: 上位系統増強工事なし（対象設備表の上位系統増強工事・バンク逆潮流対策は空欄） | AA49: ノンファーム型接続適用（基幹系統:別紙1-1グループ[福島4]、ローカル系統:154kV第一、第二福島線(0626)、154kV日和田線(0632)、須賀川変電所154/66kV主要変圧器(604)）、再給電方式（一定の順序）、PCS力率一定制御 87%（有効出力1998kW程度）、非認証PCSの実機試験成績書提出、出力制御設定の確認書類提出、N-1電制本格適用、運用上の制約あり（作業停止時等の発電抑制・停止）、前提条件: 力率一定制御87% | AB49: 接続検討の回答日から1年を経過した場合は契約申込不可 | AC49: high | AE49: 状態: 進行中（対象フォルダ直下）。検討対象年度2022~2023年度。 | AF49: ○ | AG49: 運開希望日に間に合わず | AH49: =IF(AD49<>"","未読",IF(AND(D49<>"接続検討回答",D49<>"再接続検討",D49<>"契約申込回答"),"",TRIM(IF(O49="","負担金なし ","")&IF(U49="","工期なし ","")&IF(AND(O49<>"",OR(P49="",P49="不明")),"税区分不明 ","")&IF(AC49="low","信頼度low","")))) | AJ49: 未確認 | AM49: 開く | AN49: 【接続検討回答書】No006_須賀川市江持字喜太夫70（A62324001）.pdf | AO49: 03_電力/02_接続検討/04_回答/【接続検討回答書】No006_須賀川市江持字喜太夫70（A62324001）.pdf
A50: 49 | B50: 008 | C50: 008_三春町字樋ノ口144-1（福島県）_高圧蓄電所 | D50: 接続検討回答 | E50: 東北 | F50: 2024-09-06 | G50: 2024-06-07 | H50: 株式会社パワーエックス（PX三春BESS1, 受付番号A62124013） | I50: 福島県三春町字樋ノ口144-1 | J50: 1996 | K50: 1995 | L50: 高圧（高圧版回答書） | O50: 5100000 | P50: 税込 | Q50: =IF(O50="","",IF(P50="税抜",O50*1.1,O50)/10000) -> 510 | R50: =IF(Q50="","不明",IF(Q50<=500,"〜500万",IF(Q50<=1000,"500〜1,000万",IF(Q50<=3000,"1,000〜3,000万","3,000万〜")))) -> 500〜1,000万 | S50: 工事費負担金の総額 5.1百万円(消費税等相当額 0.5百万円を含む)、税抜4.6百万円（架空線4.3/計量0.3）。概算工事費の総額 5.3百万円(税込)。別紙「概算工事費及び工事費負担金の総額」より | U50: 6 | V50: =IF(U50="","不明",IF(U50<=6,"〜6ヶ月",IF(U50<=12,"7〜12ヶ月",IF(U50<=24,"13〜24ヶ月","25ヶ月〜")))) -> 〜6ヶ月 | W50: 配電設備 6か月程度 ／ 混雑管理システム(ローカル系統) 運開時期は別途HP等でお知らせします。（契約手続き期間は含まず。工事費負担金入金後の期間） | X50: 希望2025年9月8日(別途協議)。回答日＋配電設備工期6か月の単純計算で2025年3月頃（契約手続き期間は含まず） | Y50: 電柱1本(14m)、高圧線60m(120mm2)、高圧引込線30m、柱上変圧器タップ切替32箇所、計量器2台・計器用変成器1台(200A)。電柱建替、高圧線張替 | Z50: 上位系統増強工事なし（対象設備表の上位系統増強工事・バンク逆潮流対策は空欄） | AA50: ノンファーム型接続適用（基幹系統:別紙1-1グループ[福島4]、ローカル系統:154kV第一、第二福島線(0626)、154kV日和田線(0632)）、再給電方式（一定の順序）、PCS力率一定制御 91%（有効出力1,998kW程度）、非認証PCSの実機試験成績書提出、出力制御設定の確認書類提出、N-1電制本格適用、運用上の制約あり（作業停止時等の発電抑制・停止）、前提条件: 力率一定制御91% | AB50: 接続検討の回答日から1年を経過した場合は契約申込不可 | AC50: high | AE50: 状態: 進行中（対象フォルダ直下）。検討対象年度2023~2024年度。 | AF50: ○ | AH50: =IF(AD50<>"","未読",IF(AND(D50<>"接続検討回答",D50<>"再接続検討",D50<>"契約申込回答"),"",TRIM(IF(O50="","負担金なし ","")&IF(U50="","工期なし ","")&IF(AND(O50<>"",OR(P50="",P50="不明")),"税区分不明 ","")&IF(AC50="low","信頼度low","")))) | AJ50: 未確認 | AM50: 開く | AN50: 【接続検討回答書】No008_三春町字樋ノ口144-1（A62124013）.pdf | AO50: 03_電力/02_接続検討/04_回答/【接続検討回答書】No008_三春町字樋ノ口144-1（A62124013）.pdf
A51: 50 | B51: 022 | C51: 【中止】/022_三春町字樋ノ口157-1他（福島県）_高圧蓄電所 | D51: 接続検討回答 | E51: 東北 | F51: 2024-09-24 | G51: 2024-06-24 | H51: 株式会社パワーエックス（PX三春BESS2, 受付番号A62124018） | I51: 福島県三春町字樋ノ口157-1他 | J51: 1996 | K51: 1995 | L51: 高圧（高圧版回答書） | O51: 4400000 | P51: 税込 | Q51: =IF(O51="","",IF(P51="税抜",O51*1.1,O51)/10000) -> 440 | R51: =IF(Q51="","不明",IF(Q51<=500,"〜500万",IF(Q51<=1000,"500〜1,000万",IF(Q51<=3000,"1,000〜3,000万","3,000万〜")))) -> 〜500万 | S51: 工事費負担金の総額 4.4百万円(消費税等相当額 0.4百万円を含む)、税抜4.0百万円（架空線3.7/計量0.3）。概算工事費の総額 4.6百万円(税込)。別紙「概算工事費及び工事費負担金の総額」より | U51: 5 | V51: =IF(U51="","不明",IF(U51<=6,"〜6ヶ月",IF(U51<=12,"7〜12ヶ月",IF(U51<=24,"13〜24ヶ月","25ヶ月〜")))) -> 〜6ヶ月 | W51: 配電設備 5か月程度 ／ 混雑管理システム(ローカル系統) 運開時期は別途HP等でお知らせします。（契約手続き期間は含まず。工事費負担金入金後の期間） | X51: 希望2025年10月6日(別途協議)。回答日＋配電設備工期5か月の単純計算で2025年2月頃（契約手続き期間は含まず） | Y51: 高圧引込線30m(120mm2)、変圧器タップ切替32箇所、計量器2台・計器用変成器1台(200A) | Z51: 上位系統増強工事なし（対象設備表の上位系統増強工事・バンク逆潮流対策は空欄） | AA51: ノンファーム型接続適用（基幹系統:別紙1-1グループ[福島4]、ローカル系統:154kV第一、第二福島線(0626)154kV日和田線(0632)）、再給電方式（一定の順序）、PCS力率一定制御 91%（有効出力1998kW程度）、非認証PCSの実機試験成績書提出、出力制御設定の確認書類提出、N-1電制本格適用、運用上の制約あり（作業停止時等の発電抑制・停止）、前提条件: 力率一定制御91% | AB51: 接続検討の回答日から1年を経過した場合は契約申込不可 | AC51: high | AE51: 状態: 中止（【中止】フォルダ内）。検討対象年度2023~2024年度。 | AF51: ○ | AH51: =IF(AD51<>"","未読",IF(AND(D51<>"接続検討回答",D51<>"再接続検討",D51<>"契約申込回答"),"",TRIM(IF(O51="","負担金なし ","")&IF(U51="","工期なし ","")&IF(AND(O51<>"",OR(P51="",P51="不明")),"税区分不明 ","")&IF(AC51="low","信頼度low","")))) | AJ51: 未確認 | AM51: 開く | AN51: 【接続検討回答書】No022_三春町字樋ノ口157-1他（A62124018）.pdf | AO51: 03_電力/02_接続検討/04_回答/【接続検討回答書】No022_三春町字樋ノ口157-1他（A62124018）.pdf
A52: 51 | B52: 029 | C52: 【保留】/029_富谷市穀田瀬戸ノ沢65-1（宮城県）_高圧蓄電所 | D52: 接続検討回答 | E52: 東北 | F52: 2024-10-16 | G52: 2024-07-16 | H52: 株式会社パワーエックス（PX富谷BESS1, 受付番号A41524018） | I52: 宮城県富谷市穀田瀬戸ノ沢65-1 | J52: 1996 | K52: 1995 | L52: 高圧（高圧版回答書） | N52: 穀田枝線41北1号より架空線連系 | O52: 141400000 | P52: 税込 | Q52: =IF(O52="","",IF(P52="税抜",O52*1.1,O52)/10000) -> 14140 | R52: =IF(Q52="","不明",IF(Q52<=500,"〜500万",IF(Q52<=1000,"500〜1,000万",IF(Q52<=3000,"1,000〜3,000万","3,000万〜")))) -> 3,000万〜 | S52: 工事費負担金の総額 141.4百万円(消費税等相当額 12.9百万円を含む)、税抜128.5百万円（架空線21.8/地中線106.4/計量0.3）。概算工事費の総額 141.6百万円(税込)。別紙「概算工事費及び工事費負担金の総額」より | U52: 12 | V52: =IF(U52="","不明",IF(U52<=6,"〜6ヶ月",IF(U52<=12,"7〜12ヶ月",IF(U52<=24,"13〜24ヶ月","25ヶ月〜")))) -> 7〜12ヶ月 | W52: 配電設備工事 12か月程度 ／ 混雑管理システム(ローカル系統) 運開時期は別途HP等でお知らせします。（契約手続き期間は含まず。工事費負担金入金後の期間） | X52: 希望2025年11月10日。回答日＋配電設備工期12か月の単純計算で2025年10月頃（契約手続き期間は含まず） | Y52: 電柱21本(16m・14m)、高圧線366m(AL-ACSR-L120mm2)、高圧引込線20m、B種接地抵抗改修11箇所、管路520m(125Φ)、ハンドホール2箇所、高圧ケーブル548m(CVT100mm2)、計量器2台・計器用変成器1台(200A)。高圧延長工事、既設配電線の他系統ルート変更工事 | Z52: 上位系統増強工事なし（対象設備表の上位系統増強工事・バンク逆潮流対策は空欄） | AA52: ノンファーム型接続適用（基幹系統:別紙1-1グループ[宮城2]、ローカル系統:なし）、再給電方式（一定の順序）、PCS力率一定制御 88%（有効出力1,998kW程度）、非認証PCSの実機試験成績書提出、出力制御設定の確認書類提出、書類不備による未検討項目あり（系統連系申込時に技術検討）、N-1電制本格適用、運用上の制約あり（作業停止時等の発電抑制・停止） | AB52: 接続検討の回答日から1年を経過した場合は契約申込不可 | AC52: high | AE52: 状態: 保留（【保留】フォルダ内）。検討対象年度2023~2024年度。 | AF52: ○ | AH52: =IF(AD52<>"","未読",IF(AND(D52<>"接続検討回答",D52<>"再接続検討",D52<>"契約申込回答"),"",TRIM(IF(O52="","負担金なし ","")&IF(U52="","工期なし ","")&IF(AND(O52<>"",OR(P52="",P52="不明")),"税区分不明 ","")&IF(AC52="low","信頼度low","")))) | AJ52: 未確認 | AM52: 開く | AN52: 【接続検討回答書】No029_富谷市穀田瀬戸ノ沢65-1（A41524018）.pdf | AO52: 03_電力/02_接続検討/04_回答/【接続検討回答書】No029_富谷市穀田瀬戸ノ沢65-1（A41524018）.pdf
A53: 52 | B53: 032 | C53: 032_川崎町大字川内字七曲山77（宮城県）_高圧蓄電所 | D53: 接続検討回答 | E53: 東北 | F53: 2024-09-24 | G53: 2024-06-24 | H53: 株式会社パワーエックス（PX川崎BESS1, 受付番号A41324011） | I53: 宮城県川崎町大字川内字七曲山77 | J53: 1996 | K53: 1995 | L53: 高圧（高圧版回答書） | N53: 川内線（延長。本文(c)より） | O53: 7300000 | P53: 税込 | Q53: =IF(O53="","",IF(P53="税抜",O53*1.1,O53)/10000) -> 730 | R53: =IF(Q53="","不明",IF(Q53<=500,"〜500万",IF(Q53<=1000,"500〜1,000万",IF(Q53<=3000,"1,000〜3,000万","3,000万〜")))) -> 500〜1,000万 | S53: 工事費負担金の総額 7.3百万円(消費税等相当額 0.7百万円を含む)、税抜6.6百万円（架空線6.3/計量0.3）。概算工事費の総額 7.5百万円(税込)。別紙「概算工事費及び工事費負担金の総額」より | U53: 6 | V53: =IF(U53="","不明",IF(U53<=6,"〜6ヶ月",IF(U53<=12,"7〜12ヶ月",IF(U53<=24,"13〜24ヶ月","25ヶ月〜")))) -> 〜6ヶ月 | W53: 配電設備 6か月程度 ／ 混雑管理システム(ローカル系統) 運開時期は別途HP等でお知らせします。（契約手続き期間は含まず。工事費負担金入金後の期間） | X53: 希望2025年10月6日。回答日＋配電設備工期6か月の単純計算で2025年3月頃（契約手続き期間は含まず） | Y53: 電柱2本(12m)、高圧線80m／530m(Al-ACSR-L120mm2)、高圧引込線20m、計量器2台・計器用変成器1台(200A)。最寄り系統は許容電流超過で連系不可のため川内線を延長（高圧線新設・電柱新設）、既設高圧線の張替 | Z53: 上位系統増強工事なし（対象設備表の上位系統増強工事・バンク逆潮流対策は空欄） | AA53: ノンファーム型接続適用（基幹系統:別紙1-1グループ[宮城2]、ローカル系統:66kV遠刈田線(425J)、仙南変電所154/66kV主要変圧器(411)）、再給電方式（一定の順序）、PCS力率一定制御 遅れ90%（有効出力1998kW程度）、非認証PCSの実機試験成績書提出、出力制御設定の確認書類提出、N-1電制本格適用、運用上の制約あり（作業停止時等の発電抑制・停止）、前提条件: 順潮流側検討時、力率98% 先行する発電設備が連系すること | AB53: 接続検討の回答日から1年を経過した場合は契約申込不可 | AC53: high | AE53: 状態: 進行中（対象フォルダ直下）。検討対象年度2023、2024年度。 | AF53: ○ | AH53: =IF(AD53<>"","未読",IF(AND(D53<>"接続検討回答",D53<>"再接続検討",D53<>"契約申込回答"),"",TRIM(IF(O53="","負担金なし ","")&IF(U53="","工期なし ","")&IF(AND(O53<>"",OR(P53="",P53="不明")),"税区分不明 ","")&IF(AC53="low","信頼度low","")))) | AJ53: 未確認 | AM53: 開く | AN53: 【接続検討回答書】No032_川崎町大字川内字七曲山77（A41324011）.pdf | AO53: 03_電力/02_接続検討/04_回答/【接続検討回答書】No032_川崎町大字川内字七曲山77（A41324011）.pdf
A54: 53 | B54: 038 | C54: 【保留】/038_南相馬市小高区飯崎字南原23-1（福島県）_高圧蓄電所 | D54: 接続検討回答 | E54: 東北 | F54: 2024-10-31 | G54: 2024-08-01 | H54: 株式会社パワーエックス（PX南相馬BESS1, 受付番号A61224054） | I54: 福島県南相馬市小高区飯崎字南原23-1 | J54: 1996 | K54: 1995 | L54: 高圧（高圧版回答書） | M54: 小高変電所（工事概要図より） | N54: F:行津線／泉沢線・金房線（工事概要図より） | O54: 171900000 | P54: 税込 | Q54: =IF(O54="","",IF(P54="税抜",O54*1.1,O54)/10000) -> 17190 | R54: =IF(Q54="","不明",IF(Q54<=500,"〜500万",IF(Q54<=1000,"500〜1,000万",IF(Q54<=3000,"1,000〜3,000万","3,000万〜")))) -> 3,000万〜 | S54: 工事費負担金の総額 171.9百万円(消費税等相当額 15.6百万円を含む)、税抜156.3百万円（架空線90.1/地中線65.9/計量0.3）。概算工事費の総額 172.2百万円(税込)。別紙「概算工事費及び工事費負担金の総額」より | U54: 40 | V54: =IF(U54="","不明",IF(U54<=6,"〜6ヶ月",IF(U54<=12,"7〜12ヶ月",IF(U54<=24,"13〜24ヶ月","25ヶ月〜")))) -> 25ヶ月〜 | W54: 配電設備工事 40か月程度 ／ 混雑管理システム(ローカル系統) 運開時期は別途HP等でお知らせします。（契約手続き期間は含まず。工事費負担金入金後の期間） | X54: 希望2025年11月10日。回答日＋配電設備工期40か月の単純計算で2028年2月頃（契約手続き期間は含まず）→希望日に間に合わず | Y54: 電柱新設15本(14m)・建替87本(16m×77本、14m×10本)、高圧線新設4,990m(Al-ACSR120mm2)、高圧引込線20m、電圧調整器新設1台(逆潮流対応II型3000kVA)、管路300m(3条以下)、マンホール2箇所、高圧ケーブル300m(CVT150mm2)、計量器2台・計器用変成器1台(200A) | Z54: 上位系統増強工事なし（対象設備表の上位系統増強工事・バンク逆潮流対策は空欄） | AA54: ノンファーム型接続適用（基幹系統:別紙1-1グループ[福島1]、ローカル系統:66kV南相線(651A)）、再給電方式（一定の順序）、PCS力率一定制御 88%（有効出力1,998kW）、非認証PCSの実機試験成績書提出、出力制御設定の確認書類提出、N-1電制本格適用、運用上の制約あり（作業停止時等の発電抑制・停止） | AB54: 接続検討の回答日から1年を経過した場合は契約申込不可 | AC54: high | AE54: 状態: 保留（【保留】フォルダ内）。検討対象年度2023、2024年度。 | AF54: ○ | AG54: 運開希望日に間に合わず | AH54: =IF(AD54<>"","未読",IF(AND(D54<>"接続検討回答",D54<>"再接続検討",D54<>"契約申込回答"),"",TRIM(IF(O54="","負担金なし ","")&IF(U54="","工期なし ","")&IF(AND(O54<>"",OR(P54="",P54="不明")),"税区分不明 ","")&IF(AC54="low","信頼度low","")))) | AJ54: 未確認 | AM54: 開く | AN54: 【接続検討回答書】No038_南相馬市小高区飯崎字南原23-1（A61224054）.pdf | AO54: 03_電力/02_接続検討/04_回答/【接続検討回答書】No038_南相馬市小高区飯崎字南原23-1（A61224054）.pdf
A55: 54 | B55: 040 | C55: 040_新地町駒ケ嶺字桜下51-1（福島県）_高圧蓄電所 | D55: 接続検討回答 | E55: 東北 | F55: 2025-02-10 | G55: 2024-11-11 | H55: 株式会社パワーエックス（PX新地BESS1, 受付番号A61224162） | I55: 福島県新地町駒ケ嶺字桜下51-1 | J55: 1996 | K55: 1995 | L55: 高圧（高圧版回答書） | M55: 駒ケ嶺変電所（工事概要図より） | N55: F:大菅線／菅谷線（工事概要図より） | O55: 16300000 | P55: 税込 | Q55: =IF(O55="","",IF(P55="税抜",O55*1.1,O55)/10000) -> 1630 | R55: =IF(Q55="","不明",IF(Q55<=500,"〜500万",IF(Q55<=1000,"500〜1,000万",IF(Q55<=3000,"1,000〜3,000万","3,000万〜")))) -> 1,000〜3,000万 | S55: 工事費負担金の総額 16.3百万円(消費税等相当額 1.5百万円を含む)、税抜14.8百万円（架空線14.5/計量0.3）。概算工事費の総額 16.5百万円(税込)。別紙「概算工事費及び工事費負担金の総額」より | U55: 15 | V55: =IF(U55="","不明",IF(U55<=6,"〜6ヶ月",IF(U55<=12,"7〜12ヶ月",IF(U55<=24,"13〜24ヶ月","25ヶ月〜")))) -> 13〜24ヶ月 | W55: 配電設備工事 15か月程度 ／ 混雑管理システム(ローカル系統) 運開時期は別途HP等でお知らせします。（契約手続き期間は含まず。工事費負担金入金後の期間） | X55: 希望2026年3月9日。回答日＋配電設備工期15か月の単純計算で2026年5月頃（契約手続き期間は含まず）→希望日に間に合わず | Y55: 高圧線張替2,099m（OC60mm2⇒Al-ACSR200mm2 916m＋1,183m）、高圧引込線15m、開閉器取替1台(400A)、柱上変圧器タップ切替10台、計量器2台・計器用変成器1台(200A)、電力用保安通信設備 | Z55: 上位系統増強工事なし（対象設備表の上位系統増強工事・バンク逆潮流対策は空欄） | AA55: ノンファーム型接続適用（基幹系統:別紙1-1グループ[福島2]、ローカル系統:154kV新駒線(0624)、駒ヶ嶺変電所154/66kV主要変圧器(612)）、再給電方式（一定の順序）、PCS力率一定制御 85%（有効出力1,998kW）、非認証PCSの実機試験成績書提出、出力制御設定の確認書類提出、PCSと出力制御ユニットの組合せ審査（系統連系申込後）、N-1電制本格適用、運用上の制約あり（作業停止時等の発電抑制・停止） | AB55: 接続検討の回答日から1年を経過した場合は契約申込不可 | AC55: high | AE55: 状態: 進行中（対象フォルダ直下）。検討対象年度2023、2024年度。高圧線の線種は対象設備表「AL-ACSR120mm2」、工事概要図「Al-ACSR200mm2」と記載が異なる。 | AF55: － | AG55: 運開希望日に間に合わず | AH55: =IF(AD55<>"","未読",IF(AND(D55<>"接続検討回答",D55<>"再接続検討",D55<>"契約申込回答"),"",TRIM(IF(O55="","負担金なし ","")&IF(U55="","工期なし ","")&IF(AND(O55<>"",OR(P55="",P55="不明")),"税区分不明 ","")&IF(AC55="low","信頼度low","")))) | AJ55: 未確認 | AM55: 開く | AN55: 【接続検討回答書】No040_新地町駒ケ嶺字桜下51-1（A61224162）.pdf | AO55: 03_電力/02_接続検討/04_回答/【接続検討回答書】No040_新地町駒ケ嶺字桜下51-1（A61224162）.pdf
A56: 55 | B56: 040 | C56: 040_新地町駒ケ嶺字桜下51-1（福島県）_高圧蓄電所 | D56: 再接続検討 | E56: 東北 | F56: 2025-09-12 | G56: 2025-06-12 | H56: 株式会社パワーエックス（PX新地BESS1, 受付番号A61225471） | I56: 福島県新地町駒ケ嶺字桜下51-1 | J56: 1996 | K56: 1995 | L56: 高圧（高圧版回答書） | M56: 駒ケ嶺変電所（初回回答A61224162の工事概要図より） | O56: 32100000 | P56: 税込 | Q56: =IF(O56="","",IF(P56="税抜",O56*1.1,O56)/10000) -> 3210 | R56: =IF(Q56="","不明",IF(Q56<=500,"〜500万",IF(Q56<=1000,"500〜1,000万",IF(Q56<=3000,"1,000〜3,000万","3,000万〜")))) -> 3,000万〜 | S56: 工事費負担金の総額 32.1百万円(消費税等相当額 2.9百万円を含む)、税抜29.2百万円（架空線28.9/計量0.3）。概算工事費の総額 89.5百万円(税込)。別紙「概算工事費及び工事費負担金の総額」より | U56: 17 | V56: =IF(U56="","不明",IF(U56<=6,"〜6ヶ月",IF(U56<=12,"7〜12ヶ月",IF(U56<=24,"13〜24ヶ月","25ヶ月〜")))) -> 13〜24ヶ月 | W56: 配電設備工事 1年5か月程度 ／ 上位系統増強工事 2年5か月程度 ／ 混雑管理システム(ローカル系統) 運開時期は別途HP等でお知らせします。（契約手続き期間は含まず。工事費負担金入金後の期間） | X56: 希望2026年3月9日。回答日＋配電設備工期17か月の単純計算で2027年2月頃（契約手続き期間は含まず）→希望日に間に合わず。上位系統増強工事 2年5か月程度は別途 | Y56: 電柱5本、高圧線1,245m(AL-ACSR-L120mm2)、高圧引込線15m、開閉器1台(逆潮流対応型事故区間表示器)、電圧調整器2台(逆潮流対応II型SVR 3000kVA・5000kVA)、計量器2台・計器用変成器1台(200A)、上位系統増強工事1式。電圧調整器新設、許容電流超過の高圧線張替・電柱建替、逆潮流対応型機器への取替 | Z56: あり: 154kV新駒線2号増強工事（先行他社申込みにより計画。充電側連系で増強容量の一部を使用するため、連系時期によっては費用一部負担）。上位系統増強工事2年5か月程度 | AA56: ノンファーム型接続適用（基幹系統:別紙1-1グループ[福島2]、ローカル系統:154kV新駒線(0624)、駒ヶ嶺変電所154/66kV主要変圧器(612)）、再給電方式（一定の順序）、PCS力率一定制御 93%（有効出力1,930kW程度）、非認証PCSの実機試験成績書提出、出力制御設定の確認書類提出、書類不備による未検討項目あり（系統連系申込時に技術検討）、早期連系追加対策(充電制限)は適用不可、N-1電制本格適用、運用上の制約あり（作業停止時等の発電抑制・停止） | AB56: 接続検討の回答日から1年を経過した場合は契約申込不可 | AC56: high | AE56: 状態: 進行中（対象フォルダ直下）。検討対象年度2024~2025年度。初回回答(A61224162, 2025-02-10)からの再接続検討。 | AF56: ○ | AG56: 運開希望日に間に合わず / 工期と別にバンク/上位系対策待ち | AH56: =IF(AD56<>"","未読",IF(AND(D56<>"接続検討回答",D56<>"再接続検討",D56<>"契約申込回答"),"",TRIM(IF(O56="","負担金なし ","")&IF(U56="","工期なし ","")&IF(AND(O56<>"",OR(P56="",P56="不明")),"税区分不明 ","")&IF(AC56="low","信頼度low","")))) | AJ56: 未確認 | AM56: 開く | AN56: 【再接続検討回答書】No040_新地町駒ケ嶺字桜下51-1（A61225471）.pdf | AO56: 03_電力/02_接続検討/12_回答（2回目）/【再接続検討回答書】No040_新地町駒ケ嶺字桜下51-1（A61225471）.pdf
A57: 56 | B57: 044 | C57: 【保留】/044_白河市合戦坂88-2他（福島県）_高圧蓄電所 | D57: 接続検討回答 | E57: 東北 | F57: 2024-12-27 | G57: 2024-10-02 | H57: 株式会社パワーエックス（PX白河BESS1, 受付番号A62224073） | I57: 福島県白河市合戦坂88-2他 | J57: 1996 | K57: 1995 | L57: 高圧（高圧版回答書） | O57: 1500000 | P57: 税込 | Q57: =IF(O57="","",IF(P57="税抜",O57*1.1,O57)/10000) -> 150 | R57: =IF(Q57="","不明",IF(Q57<=500,"〜500万",IF(Q57<=1000,"500〜1,000万",IF(Q57<=3000,"1,000〜3,000万","3,000万〜")))) -> 〜500万 | S57: 工事費負担金の総額 1.5百万円(消費税等相当額 0.1百万円を含む)、税抜1.4百万円（架空線1.1/計量0.3）。概算工事費の総額 1.8百万円(税込)。別紙「概算工事費及び工事費負担金の総額」より | U57: 4 | V57: =IF(U57="","不明",IF(U57<=6,"〜6ヶ月",IF(U57<=12,"7〜12ヶ月",IF(U57<=24,"13〜24ヶ月","25ヶ月〜")))) -> 〜6ヶ月 | W57: 配電設備工事 4か月程度 ／ 混雑管理システム(ローカル系統) 運開時期は別途HP等でお知らせします。（契約手続き期間は含まず。工事費負担金入金後の期間） | X57: 希望2026年1月12日。回答日＋配電設備工期4か月の単純計算で2025年4月頃（契約手続き期間は含まず） | Y57: 高圧引込線8m(AL-ACSR120mm2)、柱上変圧器タップ切替9台、計量器2台・計器用変成器1台(200A)。高圧引込線以下計器一式新設、既設バンクのタップ切替 | Z57: 上位系統増強工事なし（対象設備表の上位系統増強工事・バンク逆潮流対策は空欄） | AA57: ノンファーム型接続適用（基幹系統:別紙1-1グループ[福島4]、ローカル系統:154kV第一、第二福島線(0626)154kV日和田線(0632)西白河変電所154/66kV主要変圧器(613)）、再給電方式（一定の順序）、PCS力率一定制御 91%（有効出力1,998kW）、非認証PCSの実機試験成績書提出、出力制御設定の確認書類提出、PCSと出力制御ユニットの組合せ審査（系統連系申込後）、N-1電制本格適用、運用上の制約あり（作業停止時等の発電抑制・停止） | AB57: 接続検討の回答日から1年を経過した場合は契約申込不可 | AC57: high | AE57: 状態: 保留（【保留】フォルダ内）。検討対象年度2023、2024年度。 | AF57: － | AH57: =IF(AD57<>"","未読",IF(AND(D57<>"接続検討回答",D57<>"再接続検討",D57<>"契約申込回答"),"",TRIM(IF(O57="","負担金なし ","")&IF(U57="","工期なし ","")&IF(AND(O57<>"",OR(P57="",P57="不明")),"税区分不明 ","")&IF(AC57="low","信頼度low","")))) | AJ57: 未確認 | AM57: 開く | AN57: 【接続検討回答書】No044_白河市合戦坂88-2他（A62224073）.pdf | AO57: 03_電力/02_接続検討/04_回答/【接続検討回答書】No044_白河市合戦坂88-2他（A62224073）.pdf
A58: 57 | B58: 044 | C58: 【保留】/044_白河市合戦坂88-2他（福島県）_高圧蓄電所 | D58: 再接続検討 | E58: 東北 | F58: 2025-09-02 | G58: 2025-06-03 | H58: 株式会社パワーエックス（PX白河BESS1, 受付番号A62225452） | I58: 福島県白河市合戦坂88-2他 | J58: 1996 | K58: 1995 | L58: 高圧（高圧版回答書） | O58: 4563000000 | P58: 税込 | Q58: =IF(O58="","",IF(P58="税抜",O58*1.1,O58)/10000) -> 456300 | R58: =IF(Q58="","不明",IF(Q58<=500,"〜500万",IF(Q58<=1000,"500〜1,000万",IF(Q58<=3000,"1,000〜3,000万","3,000万〜")))) -> 3,000万〜 | S58: 工事費負担金の総額 4,563.0百万円(消費税等相当額 414.8百万円を含む)、税抜4,148.2百万円（架空線0.7/計量0.3/一般負担の上限超過分4,147.2）。概算工事費の総額 4,667.6百万円(税込)。別紙「概算工事費及び工事費負担金の総額」より | U58: 4 | V58: =IF(U58="","不明",IF(U58<=6,"〜6ヶ月",IF(U58<=12,"7〜12ヶ月",IF(U58<=24,"13〜24ヶ月","25ヶ月〜")))) -> 〜6ヶ月 | W58: 配電設備工事 4か月程度 ／ 混雑管理システム(ローカル系統) 運開時期は別途HP等でお知らせします。 ／ 上位系統増強工事 10年2ヵ月 (先行する系統利用者の為の増強工事を含む)（契約手続き期間は含まず。工事費負担金入金後の期間） | X58: 希望2026年1月12日。回答日＋配電設備工期4か月の単純計算で2026年1月頃（契約手続き期間は含まず）。上位系統増強工事 10年2ヵ月 (先行する系統利用者の為の増強工事を含む)は別途 | Y58: 高圧引込線8m(AL-ACSR-L120mm2)、柱上変圧器タップ変更5箇所、計量器2台・計器用変成器1台(200A)、上位系統増強工事1式（須賀川(変)MT2台） | Z58: あり: 須賀川(変)275/154kV主要変圧器取替(2台)が貴社連系のため必要。先行利用者の連系に伴い須賀川(変)・東福島(変)275/154kV主要変圧器増設(各1台)、西白河(変)154/66kV主要変圧器増設(1台)ほかを予定（当社工事・当社負担）。上位系統増強工事10年2ヵ月（先行利用者向け増強を含む）。一般負担の上限超過分4,147.2百万円 | AA58: ノンファーム型接続適用（基幹系統:別紙1-1グループ[福島4]、ローカル系統:154kV第一、第二福島線(0626)、154kV日和田線(0632)、西白河変電所154/66kV主要変圧器(613)）、再給電方式（一定の順序）、PCS力率一定制御 91%（有効出力1,998kW程度）、非認証PCSの実機試験成績書提出、出力制御設定の確認書類提出、N-1電制本格適用、運用上の制約あり（作業停止時等の発電抑制・停止） | AB58: 接続検討の回答日から1年を経過した場合は契約申込不可 | AC58: high | AE58: 状態: 保留（【保留】フォルダ内）。検討対象年度2024~2025年度。負担金は上位系統増強に係る一般負担の上限超過分を含むため極めて高額。初回回答(A62224073, 2024-12-27)からの再接続検討。 | AF58: ○ | AG58: 工期と別にバンク/上位系対策待ち | AH58: =IF(AD58<>"","未読",IF(AND(D58<>"接続検討回答",D58<>"再接続検討",D58<>"契約申込回答"),"",TRIM(IF(O58="","負担金なし ","")&IF(U58="","工期なし ","")&IF(AND(O58<>"",OR(P58="",P58="不明")),"税区分不明 ","")&IF(AC58="low","信頼度low","")))) | AJ58: 未確認 | AM58: 開く | AN58: 【再接続検討回答書】No044_白河市合戦坂88-2他（A62225452）.pdf | AO58: 03_電力/02_接続検討/12_回答（2回目）/【再接続検討回答書】No044_白河市合戦坂88-2他（A62225452）.pdf
A59: 58 | B59: 045 | C59: 【保留】/045_大衡村大衡字萱刈場102-2（宮城県）_高圧蓄電所 | D59: 接続検討回答 | E59: 東北 | F59: 2025-01-10 | G59: 2024-10-11 | H59: 株式会社パワーエックス（PX大衡BESS1, 受付番号A41524056） | I59: 宮城県大衡村大衡字萱刈場102-2 | J59: 1996 | K59: 1995 | L59: 高圧（高圧版回答書） | N59: 大衡幹線160東1南6号より架空線連系 | O59: 102700000 | P59: 税込 | Q59: =IF(O59="","",IF(P59="税抜",O59*1.1,O59)/10000) -> 10270 | R59: =IF(Q59="","不明",IF(Q59<=500,"〜500万",IF(Q59<=1000,"500〜1,000万",IF(Q59<=3000,"1,000〜3,000万","3,000万〜")))) -> 3,000万〜 | S59: 工事費負担金の総額 102.7百万円(消費税等相当額 9.3百万円を含む)、税抜93.4百万円（架空線93.1/計量0.3）。概算工事費の総額 103.0百万円(税込)。別紙「概算工事費及び工事費負担金の総額」より | U59: 36 | V59: =IF(U59="","不明",IF(U59<=6,"〜6ヶ月",IF(U59<=12,"7〜12ヶ月",IF(U59<=24,"13〜24ヶ月","25ヶ月〜")))) -> 25ヶ月〜 | W59: 配電設備工事 36か月程度 ／ 混雑管理システム(ローカル系統) 運開時期は別途HP等でお知らせします。（契約手続き期間は含まず。工事費負担金入金後の期間） | X59: 希望2026年2月9日。回答日＋配電設備工期36か月の単純計算で2028年1月頃（契約手続き期間は含まず）→希望日に間に合わず | Y59: 電柱7本／6本(16m・14m)、高圧線240m／6,674m(AL-OC-L200mm2)、高圧引込線20m、開閉器1台(400A)、変圧器3箇所(電圧調整工事)、電圧調整器1台／2台(TVR3,000kVA・SVRII型5,000kVA)、計量器2台・計器用変成器1台(200A)。高圧線延長、許容電流超過の高圧線・配電線機器の取替、電圧調整器新設 | Z59: 上位系統増強工事なし（対象設備表の上位系統増強工事・バンク逆潮流対策は空欄） | AA59: ノンファーム型接続適用（基幹系統:別紙1-1グループ[宮城1]、ローカル系統:大崎変電所154/66kV主要変圧器(406)）、再給電方式（一定の順序）、PCS力率一定制御 98%（有効出力1,998kW程度）、非認証PCSの実機試験成績書提出、出力制御設定の確認書類提出、書類不備による未検討項目あり（系統連系申込時に技術検討）、N-1電制本格適用、運用上の制約あり（作業停止時等の発電抑制・停止） | AB59: 接続検討の回答日から1年を経過した場合は契約申込不可 | AC59: high | AE59: 状態: 保留（【保留】フォルダ内）。検討対象年度2023~2024年度。 | AF59: ○ | AG59: 運開希望日に間に合わず | AH59: =IF(AD59<>"","未読",IF(AND(D59<>"接続検討回答",D59<>"再接続検討",D59<>"契約申込回答"),"",TRIM(IF(O59="","負担金なし ","")&IF(U59="","工期なし ","")&IF(AND(O59<>"",OR(P59="",P59="不明")),"税区分不明 ","")&IF(AC59="low","信頼度low","")))) | AJ59: 未確認 | AM59: 開く | AN59: 【接続検討回答書】No045_大衡村大衡字萱刈場102-2（A41524056）.pdf | AO59: 03_電力/02_接続検討/04_回答/【接続検討回答書】No045_大衡村大衡字萱刈場102-2（A41524056）.pdf
A60: 59 | B60: 046 | C60: 【保留】/046_加美町菜切谷字青木原28-146（宮城県）_高圧蓄電所 | D60: 接続検討回答 | E60: 東北 | F60: 2025-01-10 | G60: 2024-10-11 | H60: 株式会社パワーエックス（PX加美BESS1, 受付番号A43124096） | I60: 宮城県加美町菜切谷字青木原28-146 | J60: 1996 | K60: 1995 | L60: 高圧（高圧版回答書） | N60: 広原幹線23北39号より架空線連系 | O60: 93200000 | P60: 税込 | Q60: =IF(O60="","",IF(P60="税抜",O60*1.1,O60)/10000) -> 9320 | R60: =IF(Q60="","不明",IF(Q60<=500,"〜500万",IF(Q60<=1000,"500〜1,000万",IF(Q60<=3000,"1,000〜3,000万","3,000万〜")))) -> 3,000万〜 | S60: 工事費負担金の総額 93.2百万円(消費税等相当額 8.5百万円を含む)、税抜84.7百万円（架空線29.1/地中線43.3/変電設備12.0/計量0.3）。概算工事費の総額 1,968.7百万円(税込)。別紙「概算工事費及び工事費負担金の総額」より | U60: 33 | V60: =IF(U60="","不明",IF(U60<=6,"〜6ヶ月",IF(U60<=12,"7〜12ヶ月",IF(U60<=24,"13〜24ヶ月","25ヶ月〜")))) -> 25ヶ月〜 | W60: 配電設備工事 33か月程度 ／ 上位系統増強工事 2026年6月頃完了見込み ／ 混雑管理システム(ローカル系統) 運開時期は別途HP等でお知らせします。（契約手続き期間は含まず。工事費負担金入金後の期間） | X60: 希望2026年2月9日。回答日＋配電設備工期33か月の単純計算で2027年10月頃（契約手続き期間は含まず）→希望日に間に合わず | Y60: 電柱9本／8本(16m・14m)、高圧線2,186m(AL-ACSR-L120mm2)、高圧引込線30m、電圧調整器1台(SVRII型3,000kVA)、管路165m(Φ100)、マンホール2箇所、高圧ケーブル233m(CVT100mm2)、計量器2台・計器用変成器1台(200A)、上位系統増強工事1式（宮城(変)主要変圧器）。高圧線延長、電圧調整器新設、離隔確保困難箇所は地中線路 | Z60: あり: 宮城(変)154/66kV主要変圧器容変工事(2台)・宮城(変)短絡容量超過対策工事（先行他社申込みにより実施中。増強容量の一部を使用するため連系時期によっては費用一部負担。変電設備工事の負担金概算12.0百万円）。上位系統増強工事は2026年6月頃完了見込み | AA60: ノンファーム型接続適用（基幹系統:別紙1-1グループ[宮城1]、ローカル系統:宮城変電所154/66kV主要変圧器(401)）、再給電方式（一定の順序）、PCS力率一定制御 90%（有効出力1,998kW程度）、非認証PCSの実機試験成績書提出、出力制御設定の確認書類提出、書類不備による未検討項目あり（系統連系申込時に技術検討）、N-1電制本格適用、運用上の制約あり（作業停止時等の発電抑制・停止） | AB60: 接続検討の回答日から1年を経過した場合は契約申込不可 | AC60: high | AE60: 状態: 保留（【保留】フォルダ内）。検討対象年度2023~2024年度。 | AF60: ○ | AG60: 運開希望日に間に合わず | AH60: =IF(AD60<>"","未読",IF(AND(D60<>"接続検討回答",D60<>"再接続検討",D60<>"契約申込回答"),"",TRIM(IF(O60="","負担金なし ","")&IF(U60="","工期なし ","")&IF(AND(O60<>"",OR(P60="",P60="不明")),"税区分不明 ","")&IF(AC60="low","信頼度low","")))) | AJ60: 未確認 | AM60: 開く | AN60: 【接続検討回答書】No046_加美町菜切谷字青木原28-146（A43124096）.pdf | AO60: 03_電力/02_接続検討/04_回答/【接続検討回答書】No046_加美町菜切谷字青木原28-146（A43124096）.pdf
A61: 60 | B61: 047 | C61: 【保留】/047_石巻市桃生町寺崎字元町116-1（宮城県）_高圧蓄電所 | D61: 接続検討回答 | E61: 東北 | F61: 2025-01-10 | G61: 2024-10-11 | H61: 株式会社パワーエックス（PX石巻BESS1, 受付番号A42124040） | I61: 宮城県石巻市桃生町寺崎字元町116-1 | J61: 1996 | K61: 1995 | L61: 高圧（高圧版回答書） | O61: 224700000 | P61: 税込 | Q61: =IF(O61="","",IF(P61="税抜",O61*1.1,O61)/10000) -> 22470 | R61: =IF(Q61="","不明",IF(Q61<=500,"〜500万",IF(Q61<=1000,"500〜1,000万",IF(Q61<=3000,"1,000〜3,000万","3,000万〜")))) -> 3,000万〜 | S61: 工事費負担金の総額 224.7百万円(消費税等相当額 20.4百万円を含む)、税抜204.3百万円（架空線204.0/計量0.3）。概算工事費の総額 225.0百万円(税込)。別紙「概算工事費及び工事費負担金の総額」より | U61: 30 | V61: =IF(U61="","不明",IF(U61<=6,"〜6ヶ月",IF(U61<=12,"7〜12ヶ月",IF(U61<=24,"13〜24ヶ月","25ヶ月〜")))) -> 25ヶ月〜 | W61: 配電設備 30か月程度 ／ バンク逆潮流対策(自社工事) 2025年度運開予定 ／ 混雑管理システム(ローカル系統) 運開時期は別途HP等でお知らせします。（契約手続き期間は含まず。工事費負担金入金後の期間） | X61: 希望2026年2月9日。回答日＋配電設備工期30か月の単純計算で2027年7月頃（契約手続き期間は含まず）→希望日に間に合わず | Y61: 電柱9本／106本(14m・16m)、高圧線4,867m／5,418m(Al-OC-L200mm2)、高圧引込線30m、柱上変圧器タップ切替9箇所、電圧調整器3台／2台(5,000kVA・3,000kVA)、計量器2台・計器用変成器1台(200A)。適正電圧逸脱のため高圧線新設・張替、タップ切替、自動電圧調整器新設。既設自動電圧調整器は許容電流超過のため取替 | Z61: 上位系統増強工事なし。別途、バンク逆潮流対策（自社工事）2025年度運開予定 | AA61: ノンファーム型接続適用（基幹系統:別紙1-1グループ[宮城1]、ローカル系統:西石巻変電所154/66kV主要変圧器(406)）、再給電方式（一定の順序）、PCS力率一定制御 遅れ97%（有効出力1,998kW程度）、非認証PCSの実機試験成績書提出、出力制御設定の確認書類提出、N-1電制本格適用、運用上の制約あり（作業停止時等の発電抑制・停止）、前提条件: 順潮流側検討時、力率98% | AB61: 接続検討の回答日から1年を経過した場合は契約申込不可 | AC61: high | AE61: 状態: 保留（【保留】フォルダ内）。検討対象年度2023、2024年度。 | AF61: ○ | AG61: 運開希望日に間に合わず | AH61: =IF(AD61<>"","未読",IF(AND(D61<>"接続検討回答",D61<>"再接続検討",D61<>"契約申込回答"),"",TRIM(IF(O61="","負担金なし ","")&IF(U61="","工期なし ","")&IF(AND(O61<>"",OR(P61="",P61="不明")),"税区分不明 ","")&IF(AC61="low","信頼度low","")))) | AJ61: 未確認 | AM61: 開く | AN61: 【接続検討回答書】No047_石巻市桃生町寺崎字元町116-1（A42124040）.pdf | AO61: 03_電力/02_接続検討/04_回答/【接続検討回答書】No047_石巻市桃生町寺崎字元町116-1（A42124040）.pdf
A62: 61 | B62: 048 | C62: 【保留】/048_大崎市岩出山南沢字桂沢19-63（宮城県）_高圧蓄電所 | D62: 接続検討回答 | E62: 東北 | F62: 2024-12-19 | G62: 2024-09-20 | H62: 株式会社パワーエックス（PX大崎BESS1, 受付番号A43124081） | I62: 宮城県大崎市岩出山南沢字桂沢19-63 | J62: 1996 | K62: 1995 | L62: 高圧（高圧版回答書） | N62: 岩出山連絡線36号より架空線連系 | O62: 145300000 | P62: 税込 | Q62: =IF(O62="","",IF(P62="税抜",O62*1.1,O62)/10000) -> 14530 | R62: =IF(Q62="","不明",IF(Q62<=500,"〜500万",IF(Q62<=1000,"500〜1,000万",IF(Q62<=3000,"1,000〜3,000万","3,000万〜")))) -> 3,000万〜 | S62: 工事費負担金の総額 145.3百万円(消費税等相当額 13.2百万円を含む)、税抜132.1百万円（架空線119.8/変電設備12.0/計量0.3）。概算工事費の総額 2,020.8百万円(税込)。別紙「概算工事費及び工事費負担金の総額」より | U62: 42 | V62: =IF(U62="","不明",IF(U62<=6,"〜6ヶ月",IF(U62<=12,"7〜12ヶ月",IF(U62<=24,"13〜24ヶ月","25ヶ月〜")))) -> 25ヶ月〜 | W62: 配電設備工事 42か月程度 ／ 上位系統増強工事 2026年6月頃完了見込み ／ 混雑管理システム(ローカル系統) 運開時期は別途HP等でお知らせします。（契約手続き期間は含まず。工事費負担金入金後の期間） | X62: 希望2026年1月12日。回答日＋配電設備工期42か月の単純計算で2028年6月頃（契約手続き期間は含まず）→希望日に間に合わず | Y62: 電柱2本／54本(16m・14m)、高圧線6,742m(AL-OC-L200mm2)、高圧引込線8m、電圧調整器2台(SVRII型3,000kVA)、計量器2台・計器用変成器1台(200A)、上位系統増強工事1式（宮城(変)主要変圧器）。高圧線延長、電圧調整器新設 | Z62: あり: 宮城(変)154/66kV主要変圧器容変工事(2台)・宮城(変)短絡容量超過対策工事（先行他社申込みにより実施中。増強容量の一部を使用するため連系時期によっては費用一部負担。変電設備工事の負担金概算12.0百万円）。上位系統増強工事は2026年6月頃完了見込み | AA62: ノンファーム型接続適用（基幹系統:別紙1-1グループ[宮城1]、ローカル系統:66kV荒雄線(4A2A)、宮城変電所154/66kV主要変圧器(401)）、再給電方式（一定の順序）、PCS力率一定制御 95%（有効出力1,998kW程度）、非認証PCSの実機試験成績書提出、出力制御設定の確認書類提出、書類不備による未検討項目あり（系統連系申込時に技術検討）、N-1電制本格適用、運用上の制約あり（作業停止時等の発電抑制・停止） | AB62: 接続検討の回答日から1年を経過した場合は契約申込不可 | AC62: high | AE62: 状態: 保留（【保留】フォルダ内）。検討対象年度2023~2024年度。 | AF62: ○ | AG62: 運開希望日に間に合わず | AH62: =IF(AD62<>"","未読",IF(AND(D62<>"接続検討回答",D62<>"再接続検討",D62<>"契約申込回答"),"",TRIM(IF(O62="","負担金なし ","")&IF(U62="","工期なし ","")&IF(AND(O62<>"",OR(P62="",P62="不明")),"税区分不明 ","")&IF(AC62="low","信頼度low","")))) | AJ62: 未確認 | AM62: 開く | AN62: 【接続検討回答書】No048_大崎市岩出山南沢字桂沢19-63（A43124081）.pdf | AO62: 03_電力/02_接続検討/04_回答/【接続検討回答書】No048_大崎市岩出山南沢字桂沢19-63（A43124081）.pdf
A63: 62 | B63: 049 | C63: 【保留】/049_奥州市前沢字狐石484-1（岩手県）_高圧蓄電所 | D63: 接続検討回答 | E63: 東北 | F63: 2025-01-24 | G63: 2024-10-24 | H63: 株式会社パワーエックス（PX奥州BESS1, 受付番号A23124052） | I63: 岩手県奥州市前沢字狐石484-1 | J63: 1996 | K63: 1995 | L63: 高圧（高圧版回答書） | O63: 13600000 | P63: 税込 | Q63: =IF(O63="","",IF(P63="税抜",O63*1.1,O63)/10000) -> 1360 | R63: =IF(Q63="","不明",IF(Q63<=500,"〜500万",IF(Q63<=1000,"500〜1,000万",IF(Q63<=3000,"1,000〜3,000万","3,000万〜")))) -> 1,000〜3,000万 | S63: 工事費負担金の総額 13.6百万円(消費税等相当額 1.2百万円を含む)、税抜12.4百万円（架空線12.1/計量0.3）。概算工事費の総額 13.9百万円(税込)。別紙「概算工事費及び工事費負担金の総額」より | U63: 9 | V63: =IF(U63="","不明",IF(U63<=6,"〜6ヶ月",IF(U63<=12,"7〜12ヶ月",IF(U63<=24,"13〜24ヶ月","25ヶ月〜")))) -> 7〜12ヶ月 | W63: 配電設備工事 9か月程度 ／ 混雑管理システム(ローカル系統) 運開時期は別途HP等でお知らせします。（契約手続き期間は含まず。工事費負担金入金後の期間） | X63: 希望2026年2月9日。回答日＋配電設備工期9か月の単純計算で2025年10月頃（契約手続き期間は含まず） | Y63: 電柱1本／1本(コン柱)、高圧線25m(AL-ACSR-L120mm2)、高圧引込線10m、電圧調整器1台(5000kVA)、計量器2台・計器用変成器1台(200A)。高圧線新設に伴う電柱新設・建替、電圧調整器新設 | Z63: 上位系統増強工事なし（対象設備表の上位系統増強工事・バンク逆潮流対策は空欄） | AA63: ノンファーム型接続適用（基幹系統:別紙1-1グループ[岩手2]、ローカル系統:なし）、再給電方式（一定の順序）、PCS力率一定制御 95%（有効出力1,998kW程度）、非認証PCSの実機試験成績書提出、出力制御設定の確認書類提出、書類不備による未検討項目あり（系統連系申込時に技術検討）、N-1電制本格適用、運用上の制約あり（作業停止時等の発電抑制・停止） | AB63: 接続検討の回答日から1年を経過した場合は契約申込不可 | AC63: high | AE63: 状態: 保留（【保留】フォルダ内）。検討対象年度2023~2024年度。 | AF63: － | AH63: =IF(AD63<>"","未読",IF(AND(D63<>"接続検討回答",D63<>"再接続検討",D63<>"契約申込回答"),"",TRIM(IF(O63="","負担金なし ","")&IF(U63="","工期なし ","")&IF(AND(O63<>"",OR(P63="",P63="不明")),"税区分不明 ","")&IF(AC63="low","信頼度low","")))) | AJ63: 未確認 | AM63: 開く | AN63: 【接続検討回答書】No049_奥州市前沢字狐石484-1（A23124052）.pdf | AO63: 03_電力/02_接続検討/04_回答/【接続検討回答書】No049_奥州市前沢字狐石484-1（A23124052）.pdf
A64: 63 | B64: 049 | C64: 【保留】/049_奥州市前沢字狐石484-1（岩手県）_高圧蓄電所 | D64: 再接続検討 | E64: 東北 | F64: 2025-08-13 | G64: 2025-05-13 | H64: 株式会社パワーエックス（PX奥州BESS1, 受付番号A23125415） | I64: 岩手県奥州市前沢字狐石484-1 | J64: 1996 | K64: 1995 | L64: 高圧（高圧版回答書） | O64: 39200000 | P64: 税込 | Q64: =IF(O64="","",IF(P64="税抜",O64*1.1,O64)/10000) -> 3920 | R64: =IF(Q64="","不明",IF(Q64<=500,"〜500万",IF(Q64<=1000,"500〜1,000万",IF(Q64<=3000,"1,000〜3,000万","3,000万〜")))) -> 3,000万〜 | S64: 工事費負担金の総額 39.2百万円(消費税等相当額 3.6百万円を含む)、税抜35.6百万円（架空線35.3/計量0.3）。概算工事費の総額 39.5百万円(税込)。別紙「概算工事費及び工事費負担金の総額」より | U64: 24 | V64: =IF(U64="","不明",IF(U64<=6,"〜6ヶ月",IF(U64<=12,"7〜12ヶ月",IF(U64<=24,"13〜24ヶ月","25ヶ月〜")))) -> 13〜24ヶ月 | W64: 配電設備工事 2年程度 ／ 混雑管理システム(ローカル系統) 運開時期は別途HP等でお知らせします。（契約手続き期間は含まず。工事費負担金入金後の期間） | X64: 希望2026年2月9日。回答日＋配電設備工期24か月の単純計算で2027年8月頃（契約手続き期間は含まず）→希望日に間に合わず | Y64: 電柱29本／1本、高圧線1,138m(AL-ACSR-L120mm2)、高圧引込線20m、柱上変圧器タップ変更2箇所、電圧調整器1台(逆潮流対応II型SVR 5,000kVA)、計量器2台・計器用変成器1台(200A)。既設系統が許容電流超過のため高圧線を延長（高圧線新設・電柱新設）、電圧調整器新設 | Z64: 上位系統増強工事なし（対象設備表の上位系統増強工事・バンク逆潮流対策は空欄） | AA64: ノンファーム型接続適用（基幹系統:別紙1-1グループ[岩手2]、ローカル系統:なし）、再給電方式（一定の順序）、PCS力率一定制御 93%（有効出力1,998.00kW程度）、非認証PCSの実機試験成績書提出、出力制御設定の確認書類提出、書類不備による未検討項目あり（系統連系申込時に技術検討）、早期連系追加対策(充電制限)を適用（一関(変)154kV/66kV主要変圧器の運用容量超過のため。スケジュール運転機能等の導入要。同意しない場合は工事概要・負担金・工期が変更）、N-1電制本格適用、運用上の制約あり（作業停止時等の発電抑制・停止）、前提条件: 先行する他発電設備が連系すること | AB64: 接続検討の回答日から1年を経過した場合は契約申込不可 | AC64: high | AE64: 状態: 保留（【保留】フォルダ内）。検討対象年度2024~2025年度。初回回答(A23124052, 2025-01-24)からの再接続検討（2回目）。早期連系追加対策(充電制限)を前提とした検討結果。 | AF64: － | AG64: 運開希望日に間に合わず | AH64: =IF(AD64<>"","未読",IF(AND(D64<>"接続検討回答",D64<>"再接続検討",D64<>"契約申込回答"),"",TRIM(IF(O64="","負担金なし ","")&IF(U64="","工期なし ","")&IF(AND(O64<>"",OR(P64="",P64="不明")),"税区分不明 ","")&IF(AC64="low","信頼度low","")))) | AJ64: 未確認 | AM64: 開く | AN64: 【再接続検討回答書】No049_奥州市前沢字狐石484-1（A23125415）.pdf | AO64: 03_電力/02_接続検討/12_回答（2回目）/【再接続検討回答書】No049_奥州市前沢字狐石484-1（A23125415）.pdf
A65: 64 | B65: 049 | C65: 【保留】/049_奥州市前沢字狐石484-1（岩手県）_高圧蓄電所 | D65: 再接続検討 | E65: 東北 | F65: 2026-01-14 | G65: 2025-10-14 | H65: 株式会社パワーエックス（PX奥州BESS1, 受付番号A23125477） | I65: 岩手県奥州市前沢字狐石484-1 | J65: 1996 | K65: 1995 | L65: 高圧（高圧版回答書） | N65: 衣川線（延長。本文(c)より） | O65: 8079800000 | P65: 税込 | Q65: =IF(O65="","",IF(P65="税抜",O65*1.1,O65)/10000) -> 807980 | R65: =IF(Q65="","不明",IF(Q65<=500,"〜500万",IF(Q65<=1000,"500〜1,000万",IF(Q65<=3000,"1,000〜3,000万","3,000万〜")))) -> 3,000万〜 | S65: 工事費負担金の総額 8,079.8百万円(消費税等相当額 734.5百万円を含む)、税抜7,345.3百万円（架空線12.8/変電設備22.0/計量0.3/一般負担の上限超過分7,310.2）。概算工事費の総額 8,171.2百万円(税込)。別紙「概算工事費及び工事費負担金の総額」より | U65: 6 | V65: =IF(U65="","不明",IF(U65<=6,"〜6ヶ月",IF(U65<=12,"7〜12ヶ月",IF(U65<=24,"13〜24ヶ月","25ヶ月〜")))) -> 〜6ヶ月 | W65: 配電設備工事 6ヶ月程度 ／ 上位系統増強工事 7年3ヶ月程度 ／ 混雑管理システム(ローカル系統) 運開時期は別途HP等でお知らせします。（契約手続き期間は含まず。工事費負担金入金後の期間） | X65: 希望2026年2月9日。回答日＋配電設備工期6か月の単純計算で2026年7月頃（契約手続き期間は含まず）→希望日に間に合わず。上位系統増強工事 7年3ヶ月程度は別途 | Y65: 電柱10本、高圧線483m(AL-ACSR-L120mm2)、高圧引込線20m、柱上変圧器タップ変更18箇所、計量器2台・計器用変成器1台(200A)、上位系統増強工事1式（岩手(変)主要変圧器）。衣川線延長（高圧線新設・電柱新設） | Z65: あり: 岩手(変)275/154kV主要変圧器(MT4、5)取替工事(300MVA→300MVA)、同LA(避雷器)移設工事（充電側連系で運用容量超過のため）。上位系統増強工事7年3ヶ月程度。変電設備工事の負担金概算22.0百万円、一般負担の上限超過分7,310.2百万円 | AA65: ノンファーム型接続適用（基幹系統:別紙1-1グループ[岩手2]、ローカル系統:なし）、再給電方式（一定の順序）、PCS力率一定制御 90%、非認証PCSの実機試験成績書提出、出力制御設定の確認書類提出、早期連系追加対策(充電制限)は適用不可、N-1電制本格適用、運用上の制約あり（作業停止時等の発電抑制・停止） | AB65: 接続検討の回答日から1年を経過した場合は契約申込不可 | AC65: high | AE65: 状態: 保留（【保留】フォルダ内）。検討対象年度2024~2025年度。負担金は上位系統増強に係る一般負担の上限超過分を含むため極めて高額。再接続検討（3回目、格納フォルダ「22_回答（3回目）」）。2回目(A23125415)は充電制限適用で負担金39.2百万円だったが、本回答では充電制限が適用不可となり上位系統増強が必要。 | AF65: ○ | AG65: 運開希望日に間に合わず / 工期と別にバンク/上位系対策待ち | AH65: =IF(AD65<>"","未読",IF(AND(D65<>"接続検討回答",D65<>"再接続検討",D65<>"契約申込回答"),"",TRIM(IF(O65="","負担金なし ","")&IF(U65="","工期なし ","")&IF(AND(O65<>"",OR(P65="",P65="不明")),"税区分不明 ","")&IF(AC65="low","信頼度low","")))) | AJ65: 未確認 | AM65: 開く | AN65: 【再接続検討回答書】No049_奥州市前沢字狐石484-1（A23125477）.pdf | AO65: 03_電力/02_接続検討/22_回答（3回目）/【再接続検討回答書】No049_奥州市前沢字狐石484-1（A23125477）.pdf
A66: 65 | B66: 052 | C66: 【保留】/052_白河市東工業団地字南7他（福島県）_高圧蓄電所 | D66: 接続検討回答 | E66: 東北 | F66: 2025-02-10 | G66: 2024-11-11 | H66: 株式会社パワーエックス（PX白河BESS2, 受付番号A62224099） | I66: 福島県白河市東工業団地字南7他 | J66: 1996 | K66: 1995 | L66: 高圧（高圧版回答書） | O66: 4500000 | P66: 税込 | Q66: =IF(O66="","",IF(P66="税抜",O66*1.1,O66)/10000) -> 450 | R66: =IF(Q66="","不明",IF(Q66<=500,"〜500万",IF(Q66<=1000,"500〜1,000万",IF(Q66<=3000,"1,000〜3,000万","3,000万〜")))) -> 〜500万 | S66: 工事費負担金の総額 4.5百万円(消費税等相当額 0.4百万円を含む)、税抜4.1百万円（架空線3.8/計量0.3）。概算工事費の総額 4.7百万円(税込)。別紙「概算工事費及び工事費負担金の総額」より | U66: 5 | V66: =IF(U66="","不明",IF(U66<=6,"〜6ヶ月",IF(U66<=12,"7〜12ヶ月",IF(U66<=24,"13〜24ヶ月","25ヶ月〜")))) -> 〜6ヶ月 | W66: 配電設備工事 5か月程度 ／ 混雑管理システム(ローカル系統) 運開時期は別途HP等でお知らせします。（契約手続き期間は含まず。工事費負担金入金後の期間） | X66: 希望2025年3月9日。回答日＋配電設備工期5か月の単純計算で2025年7月頃（契約手続き期間は含まず）→希望日に間に合わず | Y66: 高圧線337m(AL-OC-L200mm2)、高圧引込線30m、柱上変圧器タップ変更7箇所、計量器2台・計器用変成器1台(200A)。許容電流超過の高圧線張替 | Z66: 上位系統増強工事なし（対象設備表の上位系統増強工事・バンク逆潮流対策は空欄） | AA66: ノンファーム型接続適用（基幹系統:別紙1-1グループ[福島4]、ローカル系統:154kV第一、第二福島線(0626)154kV日和田線(0632)66kV東釜子線(691A)泉崎変電所154/66kV主要変圧器(608)）、再給電方式（一定の順序）、PCS力率一定制御 93%（有効出力1,998kW程度）、非認証PCSの実機試験成績書提出、出力制御設定の確認書類提出、書類不備による未検討項目あり（系統連系申込時に技術検討）、N-1電制本格適用、運用上の制約あり（作業停止時等の発電抑制・停止） | AB66: 接続検討の回答日から1年を経過した場合は契約申込不可 | AC66: high | AE66: 状態: 保留（【保留】フォルダ内）。検討対象年度2023~2024年度。 | AF66: － | AG66: 運開希望日に間に合わず | AH66: =IF(AD66<>"","未読",IF(AND(D66<>"接続検討回答",D66<>"再接続検討",D66<>"契約申込回答"),"",TRIM(IF(O66="","負担金なし ","")&IF(U66="","工期なし ","")&IF(AND(O66<>"",OR(P66="",P66="不明")),"税区分不明 ","")&IF(AC66="low","信頼度low","")))) | AJ66: 未確認 | AM66: 開く | AN66: 【接続検討回答書】No052_白河市東工業団地字南7他（A62224099）.pdf | AO66: 03_電力/02_接続検討/04_回答/【接続検討回答書】No052_白河市東工業団地字南7他（A62224099）.pdf
A67: 66 | B67: 052 | C67: 【保留】/052_白河市東工業団地字南7他（福島県）_高圧蓄電所 | D67: 再接続検討 | E67: 東北 | F67: 2025-08-13 | G67: 2025-05-13 | H67: 株式会社パワーエックス（PX白河BESS2, 受付番号A62225433） | I67: 福島県白河市東工業団地字南7他 | J67: 1996 | K67: 1995 | L67: 高圧（高圧版回答書） | O67: 6589300000 | P67: 税込 | Q67: =IF(O67="","",IF(P67="税抜",O67*1.1,O67)/10000) -> 658930 | R67: =IF(Q67="","不明",IF(Q67<=500,"〜500万",IF(Q67<=1000,"500〜1,000万",IF(Q67<=3000,"1,000〜3,000万","3,000万〜")))) -> 3,000万〜 | S67: 工事費負担金の総額 6,589.3百万円(消費税等相当額 599.0百万円を含む)、税抜5,990.3百万円（架空線3.8/計量0.3/一般負担の上限超過分5,986.2）。概算工事費の総額 6,702.7百万円(税込)。別紙「概算工事費及び工事費負担金の総額」より | U67: 5 | V67: =IF(U67="","不明",IF(U67<=6,"〜6ヶ月",IF(U67<=12,"7〜12ヶ月",IF(U67<=24,"13〜24ヶ月","25ヶ月〜")))) -> 〜6ヶ月 | W67: 配電設備工事 5か月程度 ／ 上位系統増強工事 10年2か月程度 (先行する系統利用者の為の増強工事を含む) ／ 混雑管理システム(ローカル系統) 運開時期は別途HP等でお知らせします。（契約手続き期間は含まず。工事費負担金入金後の期間） | X67: 希望2026年3月9日。回答日＋配電設備工期5か月の単純計算で2026年1月頃（契約手続き期間は含まず）。上位系統増強工事 10年2か月程度 (先行する系統利用者の為の増強工事を含む)は別途 | Y67: 高圧線337m(AL-OC-L200mm2)、高圧引込線30m、開閉器1台(逆潮流対応型事故区間表示器)、計量器2台・計器用変成器1台(200A)、上位系統増強工事1式（須賀川(変)MT2台・泉崎(変)MT2台取替）。高圧線張替、逆潮流対応型機器への取替 | Z67: あり: 須賀川(変)275/154kV主要変圧器取替(2台)および泉崎(変)154/66kV主要変圧器取替(2台)が貴社連系のため必要。先行利用者の連系に伴い須賀川(変)・東福島(変)275/154kV主要変圧器増設(各1台)ほかを予定（当社工事・当社負担）。上位系統増強工事10年2か月程度（先行利用者向け増強を含む）。一般負担の上限超過分5,986.2百万円 | AA67: ノンファーム型接続適用（基幹系統:別紙1-1グループ[福島4]、ローカル系統:154kV第一、第二福島線(0626)、154kV日和田線(0632)、66kV東釜子線(691A)、泉崎変電所154/66kV主要変圧器(608)）、再給電方式（一定の順序）、PCS力率一定制御 92%（有効出力1,998kW程度）、非認証PCSの実機試験成績書提出、出力制御設定の確認書類提出、書類不備による未検討項目あり（系統連系申込時に技術検討）、早期連系追加対策(充電制限)は適用不可、N-1電制本格適用、運用上の制約あり（作業停止時等の発電抑制・停止） | AB67: 接続検討の回答日から1年を経過した場合は契約申込不可 | AC67: high | AE67: 状態: 保留（【保留】フォルダ内）。検討対象年度2024~2025年度。負担金は上位系統増強に係る一般負担の上限超過分を含むため極めて高額。初回回答(A62224099, 2025-02-10)からの再接続検討。 | AF67: ○ | AG67: 工期と別にバンク/上位系対策待ち | AH67: =IF(AD67<>"","未読",IF(AND(D67<>"接続検討回答",D67<>"再接続検討",D67<>"契約申込回答"),"",TRIM(IF(O67="","負担金なし ","")&IF(U67="","工期なし ","")&IF(AND(O67<>"",OR(P67="",P67="不明")),"税区分不明 ","")&IF(AC67="low","信頼度low","")))) | AJ67: 未確認 | AM67: 開く | AN67: 【再接続検討回答書】No052_白河市東工業団地字南7他（A62225433）.pdf | AO67: 03_電力/02_接続検討/12_回答（2回目）/【再接続検討回答書】No052_白河市東工業団地字南7他（A62225433）.pdf
A68: 67 | B68: 054 | C68: 【保留】/054_大崎市岩出山字細峯55-137（宮城県）_高圧蓄電所 | D68: 接続検討回答 | E68: 東北 | F68: 2025-02-10 | G68: 2024-11-11 | H68: 株式会社パワーエックス（PX大崎BESS2, 受付番号A43124115） | I68: 宮城県大崎市岩出山字細峯55-137 | J68: 1996 | K68: 1995 | L68: 高圧（高圧版回答書） | N68: 多田川幹線59号より架空線連系 | O68: 43500000 | P68: 税込 | Q68: =IF(O68="","",IF(P68="税抜",O68*1.1,O68)/10000) -> 4350 | R68: =IF(Q68="","不明",IF(Q68<=500,"〜500万",IF(Q68<=1000,"500〜1,000万",IF(Q68<=3000,"1,000〜3,000万","3,000万〜")))) -> 3,000万〜 | S68: 工事費負担金の総額 43.5百万円(消費税等相当額 4.0百万円を含む)、税抜39.5百万円（架空線27.2/変電設備12.0/計量0.3）。概算工事費の総額 1,919.0百万円(税込)。別紙「概算工事費及び工事費負担金の総額」より | U68: 14 | V68: =IF(U68="","不明",IF(U68<=6,"〜6ヶ月",IF(U68<=12,"7〜12ヶ月",IF(U68<=24,"13〜24ヶ月","25ヶ月〜")))) -> 13〜24ヶ月 | W68: 配電設備工事 14か月程度 ／ 上位系統増強工事 2026年6月頃完了見込み ／ 混雑管理システム(ローカル系統) 運開時期は別途HP等でお知らせします。（契約手続き期間は含まず。工事費負担金入金後の期間） | X68: 希望2025年3月9日。回答日＋配電設備工期14か月の単純計算で2026年4月頃（契約手続き期間は含まず）→希望日に間に合わず。上位系統増強工事 2026年6月頃完了見込みは別途 | Y68: 電柱1本／1本(コン柱)、高圧線1,757m(AL-ACSR-L120mm2)、高圧引込線23m、電圧調整器1台(SVRII型3,000kVA)、計量器2台・計器用変成器1台(200A)、上位系統増強工事1式（宮城(変)主要変圧器）。高圧延長工事、電圧調整器新設 | Z68: あり: 宮城(変)154/66kV主要変圧器容変工事(2台)・宮城(変)短絡容量超過対策工事（先行他社申込みにより実施中。増強容量の一部を使用するため連系時期によっては費用一部負担。変電設備工事の負担金概算12.0百万円）。上位系統増強工事は2026年6月頃完了見込み | AA68: ノンファーム型接続適用（基幹系統:別紙1-1グループ[宮城1]、ローカル系統:66kV荒雄線(4A2A)、宮城変電所154/66kV主要変圧器(401)）、再給電方式（一定の順序）、PCS力率一定制御 91%（有効出力1,998kW程度）、非認証PCSの実機試験成績書提出、出力制御設定の確認書類提出、書類不備による未検討項目あり（系統連系申込時に技術検討）、N-1電制本格適用、運用上の制約あり（作業停止時等の発電抑制・停止） | AB68: 接続検討の回答日から1年を経過した場合は契約申込不可 | AC68: high | AE68: 状態: 保留（【保留】フォルダ内）。検討対象年度2023~2024年度。 | AF68: ○ | AG68: 運開希望日に間に合わず / 工期と別にバンク/上位系対策待ち | AH68: =IF(AD68<>"","未読",IF(AND(D68<>"接続検討回答",D68<>"再接続検討",D68<>"契約申込回答"),"",TRIM(IF(O68="","負担金なし ","")&IF(U68="","工期なし ","")&IF(AND(O68<>"",OR(P68="",P68="不明")),"税区分不明 ","")&IF(AC68="low","信頼度low","")))) | AJ68: 未確認 | AM68: 開く | AN68: 【接続検討回答書】No054_大崎市岩出山字細峯55-137（A43124115）.pdf | AO68: 03_電力/02_接続検討/04_回答/【接続検討回答書】No054_大崎市岩出山字細峯55-137（A43124115）.pdf
A69: 68 | B69: 055 | C69: 【保留】/055_松島町高城字石田沢一17-1他（宮城県）_高圧蓄電所 | D69: 接続検討回答 | E69: 東北 | F69: 2025-03-13 | G69: 2024-12-13 | H69: 株式会社パワーエックス（PX松島BESS1, 受付番号A41224038） | I69: 宮城県松島町高城字石田沢-17-1他 | J69: 1996 | K69: 1995 | L69: 高圧（高圧版回答書） | N69: 湯の沢線24号より架空線連系 | O69: 70400000 | P69: 税込 | Q69: =IF(O69="","",IF(P69="税抜",O69*1.1,O69)/10000) -> 7040 | R69: =IF(Q69="","不明",IF(Q69<=500,"〜500万",IF(Q69<=1000,"500〜1,000万",IF(Q69<=3000,"1,000〜3,000万","3,000万〜")))) -> 3,000万〜 | S69: 工事費負担金の総額 70.4百万円(消費税等相当額 6.4百万円を含む)、税抜64.0百万円（架空線54.6/変電設備1.1/計量0.3/一般負担の上限超過分8.0）。概算工事費の総額 168.6百万円(税込)。別紙「概算工事費及び工事費負担金の総額」より | U69: 24 | V69: =IF(U69="","不明",IF(U69<=6,"〜6ヶ月",IF(U69<=12,"7〜12ヶ月",IF(U69<=24,"13〜24ヶ月","25ヶ月〜")))) -> 13〜24ヶ月 | W69: 配電設備工事 2年程度 ／ 上位系統増強工事 2年7か月程度 ／ 混雑管理システム(ローカル系統) 運開時期は別途HP等でお知らせします。（契約手続き期間は含まず。工事費負担金入金後の期間） | X69: 希望2026年4月6日。回答日＋配電設備工期24か月の単純計算で2027年3月頃（契約手続き期間は含まず）→希望日に間に合わず。上位系統増強工事 2年7か月程度は別途 | Y69: 電柱1本／1本、高圧線3,150m(AL-OC-L200mm2)、高圧引込線20m、電圧調整器1台(SVRII型5,000kVA)、高圧ケーブル158m(CVT325mm2)、計量器2台・計器用変成器1台(200A)、上位系統増強工事1式（仙台港(変)塩釜線）。高圧線延長、電圧調整器新設 | Z69: あり: 仙台港(変)66kV塩釜線1、2号直列機器増強工事(800A→1200A)（充電側連系で運用容量超過のため）。上位系統増強工事2年7か月程度。変電設備工事の負担金概算1.1百万円、一般負担の上限超過分8.0百万円 | AA69: ノンファーム型接続適用（基幹系統:別紙1-1グループ[宮城2]、ローカル系統:なし）、再給電方式（一定の順序）、PCS力率一定制御 97%（有効出力1,998kW程度）、非認証PCSの実機試験成績書提出、出力制御設定の確認書類提出、書類不備による未検討項目あり（系統連系申込時に技術検討）、N-1電制本格適用、運用上の制約あり（作業停止時等の発電抑制・停止） | AB69: 接続検討の回答日から1年を経過した場合は契約申込不可 | AC69: high | AE69: 状態: 保留（【保留】フォルダ内）。検討対象年度2023~2024年度。発電場所は本文テキスト層「石田沢-17-1他」、フォルダ・ファイル名は「石田沢一17-1他」。 | AF69: ○ | AG69: 運開希望日に間に合わず / 工期と別にバンク/上位系対策待ち | AH69: =IF(AD69<>"","未読",IF(AND(D69<>"接続検討回答",D69<>"再接続検討",D69<>"契約申込回答"),"",TRIM(IF(O69="","負担金なし ","")&IF(U69="","工期なし ","")&IF(AND(O69<>"",OR(P69="",P69="不明")),"税区分不明 ","")&IF(AC69="low","信頼度low","")))) | AJ69: 未確認 | AM69: 開く | AN69: 【接続検討回答書】No055_松島町高城字石田沢一17-1他（A41224038）.pdf | AO69: 03_電力/02_接続検討/04_回答/【接続検討回答書】No055_松島町高城字石田沢一17-1他（A41224038）.pdf
A70: 69 | B70: 056 | C70: 【保留】/056_雫石町中黒沢川191-42（岩手県）_高圧蓄電所 | D70: 接続検討回答 | E70: 東北 | F70: 2025-03-13 | G70: 2024-12-13 | H70: 株式会社パワーエックス（PX雫石BESS1, 受付番号A21124099） | I70: 岩手県雫石町中黒沢川191-42 | J70: 1996 | K70: 1995 | L70: 高圧（高圧版回答書） | M70: 雫石変電所（2号変圧器が逆潮流。本文(c)より） | N70: 七つ森線（延長。本文(c)より） | O70: 1172500000 | P70: 税込 | Q70: =IF(O70="","",IF(P70="税抜",O70*1.1,O70)/10000) -> 117250 | R70: =IF(Q70="","不明",IF(Q70<=500,"〜500万",IF(Q70<=1000,"500〜1,000万",IF(Q70<=3000,"1,000〜3,000万","3,000万〜")))) -> 3,000万〜 | S70: 工事費負担金の総額 1,172.5百万円(消費税等相当額 106.6百万円を含む)、税抜1,065.9百万円（架空線69.4/地中線40.2/バンク逆潮流対策7.0/変電設備949.0/計量0.3）。概算工事費の総額 1,182.6百万円(税込)。別紙「概算工事費及び工事費負担金の総額」より | U70: 24 | V70: =IF(U70="","不明",IF(U70<=6,"〜6ヶ月",IF(U70<=12,"7〜12ヶ月",IF(U70<=24,"13〜24ヶ月","25ヶ月〜")))) -> 13〜24ヶ月 | W70: 配電設備工事 2年程度 ／ バンク逆潮流対策工事 1年5か月 ／ 上位系統工事 6年5か月 ／ 混雑管理システム(ローカル系統) 運開時期は別途HP等でお知らせします。（契約手続き期間は含まず。工事費負担金入金後の期間） | X70: 希望2026年4月6日。回答日＋配電設備工期24か月の単純計算で2027年3月頃（契約手続き期間は含まず）→希望日に間に合わず。バンク逆潮流対策工事 1年5か月、上位系統工事 6年5か月は別途 | Y70: 電柱19本／37本(コン柱)、高圧線2,580m／274m(AL-ACSR-L120mm2／AL-OC-L200mm2)、高圧引込線25m、開閉器1台／2台(400A、逆潮流対応型事故区間表示器)、柱上変圧器タップ変更2台・B種接地改修3個所、電圧調整器2台(逆潮流対応II型SVR 3,000kVA・5,000kVA)、管路159m(100φ)、マンホール1個所、高圧ケーブル191m(CVT100mm2)、バンク逆潮流対策1式、計量器2台・計器用変成器1台(200A)、上位系統増強工事1式（盛岡(変)主要変圧器） | Z70: あり: 盛岡(変)154/66kV主要変圧器(MT4)増設工事（変電設備工事の負担金概算949.0百万円）、雫石変電所2号変圧器バンク逆潮流対策(7.0百万円)。上位系統工事6年5か月、バンク逆潮流対策工事1年5か月 | AA70: ノンファーム型接続適用（基幹系統:別紙1-1グループ[岩手2]、ローカル系統:154kV盛岡線(0535)、66kV雫石線(232A)）、再給電方式（一定の順序）、PCS力率一定制御 91%（有効出力1,998kW程度）、非認証PCSの実機試験成績書提出、出力制御設定の確認書類提出、書類不備による未検討項目あり（系統連系申込時に技術検討）、N-1電制本格適用、運用上の制約あり（作業停止時等の発電抑制・停止）、前提条件: 先行する他発電設備が連系したものとして検討 | AB70: 接続検討の回答日から1年を経過した場合は契約申込不可 | AC70: high | AE70: 状態: 保留（【保留】フォルダ内）。検討対象年度2023~2024年度。負担金は上位系統増強に係る一般負担の上限超過分を含むため極めて高額。 | AF70: ○ | AG70: 運開希望日に間に合わず / 工期と別にバンク/上位系対策待ち | AH70: =IF(AD70<>"","未読",IF(AND(D70<>"接続検討回答",D70<>"再接続検討",D70<>"契約申込回答"),"",TRIM(IF(O70="","負担金なし ","")&IF(U70="","工期なし ","")&IF(AND(O70<>"",OR(P70="",P70="不明")),"税区分不明 ","")&IF(AC70="low","信頼度low","")))) | AJ70: 未確認 | AM70: 開く | AN70: 【接続検討回答書】No056_雫石町中黒沢川191-42（A21124099）.pdf | AO70: 03_電力/02_接続検討/04_回答/【接続検討回答書】No056_雫石町中黒沢川191-42（A21124099）.pdf
A71: 70 | B71: 059 | C71: 【保留】/059_八幡平市松尾寄木第1地割589-3（岩手県）_高圧蓄電所 | D71: 接続検討回答 | E71: 東北 | F71: 2025-03-12 | G71: 2024-12-13 | H71: 株式会社パワーエックス（PX八幡平BESS1, 受付番号A21124100） | I71: 岩手県八幡平市松尾寄木第1地割589-3 | J71: 1996 | K71: 1995 | L71: 高圧（高圧版回答書） | M71: 柏台変電所（1号変圧器が逆潮流。本文(c)より） | N71: 下倉線（延長。本文(c)より） | O71: 50200000 | P71: 税込 | Q71: =IF(O71="","",IF(P71="税抜",O71*1.1,O71)/10000) -> 5020 | R71: =IF(Q71="","不明",IF(Q71<=500,"〜500万",IF(Q71<=1000,"500〜1,000万",IF(Q71<=3000,"1,000〜3,000万","3,000万〜")))) -> 3,000万〜 | S71: 工事費負担金の総額 50.2百万円(消費税等相当額 4.6百万円を含む)、税抜45.6百万円（架空線10.1/地中線28.2/バンク逆潮流対策7.0/計量0.3）。概算工事費の総額 50.4百万円(税込)。別紙「概算工事費及び工事費負担金の総額」より | U71: 15 | V71: =IF(U71="","不明",IF(U71<=6,"〜6ヶ月",IF(U71<=12,"7〜12ヶ月",IF(U71<=24,"13〜24ヶ月","25ヶ月〜")))) -> 13〜24ヶ月 | W71: 配電設備工事 1年3か月程度 ／ バンク逆潮流対策工事 1年5か月程度 ／ 混雑管理システム(ローカル系統) 運開時期は別途HP等でお知らせします。（契約手続き期間は含まず。工事費負担金入金後の期間） | X71: 希望2026年4月6日。回答日＋配電設備工期15か月の単純計算で2026年6月頃（契約手続き期間は含まず）→希望日に間に合わず。バンク逆潮流対策工事 1年5か月程度は別途 | Y71: 電柱4本(コン柱)、高圧線126m(AL-ACSR-L120mm2)、高圧引込線10m、柱上変圧器タップ変更4台、電圧調整器1台／1台(逆潮流対応II型SVR 5,000kVA・サイリスタ型3,000kVA)、管路122m(100φ)、マンホール1個所、高圧ケーブル146m(CVT100mm2)、バンク逆潮流対策1式(系統地絡検出リレー設置、変圧器盤・電調盤改造)、計量器2台・計器用変成器1台(200A)。下倉線延長、景観形成基準により一部は高圧ケーブル地中埋設、自動電圧調整器取替 | Z71: 上位系統増強工事なし。バンク逆潮流対策工事あり（柏台変電所1号変圧器、1年5か月程度、負担金概算7.0百万円） | AA71: ノンファーム型接続適用（基幹系統:別紙1-1グループ[岩手1]、ローカル系統:154kV姫神線(0530)、154kV盛岡線(0535)、66kV渋民線(223A)66kV沼宮内線(223E)、66kV好摩支線(223F)）、再給電方式（一定の順序）、PCS力率一定制御 96%（有効出力1,998kW程度）、非認証PCSの実機試験成績書提出、出力制御設定の確認書類提出、書類不備による未検討項目あり（系統連系申込時に技術検討）、N-1電制本格適用、運用上の制約あり（作業停止時等の発電抑制・停止） | AB71: 接続検討の回答日から1年を経過した場合は契約申込不可 | AC71: high | AE71: 状態: 保留（【保留】フォルダ内）。検討対象年度2023~2024年度。 | AF71: ○ | AG71: 運開希望日に間に合わず / 工期と別にバンク/上位系対策待ち | AH71: =IF(AD71<>"","未読",IF(AND(D71<>"接続検討回答",D71<>"再接続検討",D71<>"契約申込回答"),"",TRIM(IF(O71="","負担金なし ","")&IF(U71="","工期なし ","")&IF(AND(O71<>"",OR(P71="",P71="不明")),"税区分不明 ","")&IF(AC71="low","信頼度low","")))) | AJ71: 未確認 | AM71: 開く | AN71: 【接続検討回答書】No059_八幡平市松尾寄木第1地割589-3（A21124100）.pdf | AO71: 03_電力/02_接続検討/04_回答/【接続検討回答書】No059_八幡平市松尾寄木第1地割589-3（A21124100）.pdf
A72: 71 | B72: 061 | C72: 【保留】/061_伊達市月舘町糠田字後田35-1（福島県）_高圧蓄電所 | D72: 接続検討回答 | E72: 東北 | F72: 2025-04-10 | G72: 2025-01-10 | H72: 株式会社パワーエックス（PX伊達BESS1, 受付番号A61124146） | I72: 福島県伊達市月舘町糠田字後田35-1 | J72: 1996 | K72: 1995 | L72: 高圧（高圧版回答書） | M72: 川俣変電所（配電用変圧器を15⇒20MVAへ更新。本文(c)より） | N72: 月館線（延長。本文(c)より） | O72: 208000000 | P72: 税込 | Q72: =IF(O72="","",IF(P72="税抜",O72*1.1,O72)/10000) -> 20800 | R72: =IF(Q72="","不明",IF(Q72<=500,"〜500万",IF(Q72<=1000,"500〜1,000万",IF(Q72<=3000,"1,000〜3,000万","3,000万〜")))) -> 3,000万〜 | S72: 工事費負担金の総額 208.0百万円(消費税等相当額 18.9百万円を含む)、税抜189.1百万円（架空線188.8/計量0.3）。概算工事費の総額 208.2百万円(税込)。別紙「概算工事費及び工事費負担金の総額」より | U72: 44 | V72: =IF(U72="","不明",IF(U72<=6,"〜6ヶ月",IF(U72<=12,"7〜12ヶ月",IF(U72<=24,"13〜24ヶ月","25ヶ月〜")))) -> 25ヶ月〜 | W72: 配電設備工事 44か月程度 ／ 変電設備工事(自社工事) 2027年度工事完了予定 ／ 混雑管理システム(ローカル系統) 運開時期は別途HP等でお知らせします。（契約手続き期間は含まず。工事費負担金入金後の期間） | X72: 希望2026年5月11日。回答日＋配電設備工期44か月の単純計算で2028年12月頃（契約手続き期間は含まず）→希望日に間に合わず | Y72: 電柱42本／113本、高圧線3,900m／8,000m(AL-ACSR-L120mm2・AL-OC-L200mm2)、高圧引込線25m、開閉器2台／2台(逆潮流対応型事故区間表示器・開閉器本体400A)、柱上変圧器タップ変更19箇所、電圧調整器1台／3台(取替:逆潮流対応II型SVR5000kVA、新設:サイリスタ型3000kVA)、計量器2台・計器用変成器1台(200A)。月館線延長、高圧線張替、電圧調整器新設・取替、逆潮流対応型機器への取替 | Z72: 上位系統増強工事なし。川俣変電所配電用変圧器の更新(15⇒20MVA)が必要（2027年度に自社工事でLT2取替予定、変電設備工事は2027年度工事完了予定） | AA72: ノンファーム型接続適用（基幹系統:別紙1-1グループ[福島1]、ローカル系統:66kV南相線(651A)）、再給電方式（一定の順序）、PCS力率一定制御 94%（有効出力1,998kW程度）、非認証PCSの実機試験成績書提出、出力制御設定の確認書類提出、書類不備による未検討項目あり（系統連系申込時に技術検討）、N-1電制本格適用、運用上の制約あり（作業停止時等の発電抑制・停止） | AB72: 接続検討の回答日から1年を経過した場合は契約申込不可 | AC72: high | AE72: 状態: 保留（【保留】フォルダ内）。検討対象年度2023~2024年度。 | AF72: ○ | AG72: 運開希望日に間に合わず | AH72: =IF(AD72<>"","未読",IF(AND(D72<>"接続検討回答",D72<>"再接続検討",D72<>"契約申込回答"),"",TRIM(IF(O72="","負担金なし ","")&IF(U72="","工期なし ","")&IF(AND(O72<>"",OR(P72="",P72="不明")),"税区分不明 ","")&IF(AC72="low","信頼度low","")))) | AJ72: 未確認 | AM72: 開く | AN72: 【接続検討回答書】No061_伊達市月舘町糠田字後田35-1（A61124146）.pdf | AO72: 03_電力/02_接続検討/04_回答/【接続検討回答書】No061_伊達市月舘町糠田字後田35-1（A61124146）.pdf
A73: 72 | B73: 065 | C73: 【保留】/065_奥州市江刺藤里字外ノ沢539（岩手県）_高圧蓄電所 | D73: 接続検討回答 | E73: 東北 | F73: 2025-05-02 | G73: 2025-02-06 | H73: 株式会社パワーエックス（PX奥州BESS2, 受付番号A23124078） | I73: 岩手県奥州市江刺藤里字外ノ沢539 | J73: 1996 | K73: 1995 | L73: 高圧（高圧版回答書） | O73: 4990300000 | P73: 税込 | Q73: =IF(O73="","",IF(P73="税抜",O73*1.1,O73)/10000) -> 499030 | R73: =IF(Q73="","不明",IF(Q73<=500,"〜500万",IF(Q73<=1000,"500〜1,000万",IF(Q73<=3000,"1,000〜3,000万","3,000万〜")))) -> 3,000万〜 | S73: 工事費負担金の総額 4,990.3百万円(消費税等相当額 453.7百万円を含む)、税抜4,536.6百万円（架空線50.1/計量0.3/一般負担の上限超過分4,486.2）。概算工事費の総額 5,080.6百万円(税込)。別紙「概算工事費及び工事費負担金の総額」より | U73: 36 | V73: =IF(U73="","不明",IF(U73<=6,"〜6ヶ月",IF(U73<=12,"7〜12ヶ月",IF(U73<=24,"13〜24ヶ月","25ヶ月〜")))) -> 25ヶ月〜 | W73: 配電設備工事 36カ月程度 ／ 混雑管理システム(ローカル系統) 運開時期は別途HP等でお知らせします。 ／ 上位系統増強工事 96カ月（契約手続き期間は含まず。工事費負担金入金後の期間） | X73: 希望2026年6月8日。回答日＋配電設備工期36か月の単純計算で2028年5月頃（契約手続き期間は含まず）→希望日に間に合わず。上位系統増強工事 96カ月は別途 | Y73: 電柱16本、高圧線2,819m(AL-ACSR-L120mm2／AL-OC-L200mm2)、高圧引込線12m、開閉器1台(300A→400A)、電圧調整器1台／1台(逆潮流対応II型SVR 3000kVA→5000kVA)、計量器2台・計器用変成器1台(200A)、上位系統増強工事1式（水沢(変)主要変圧器）。高圧線延長、高圧線張替・自動電圧調整器取替、電柱建替、柱上変圧器タップ変更 | Z73: あり: 水沢(変)275/154kV主要変圧器(MT3)増設工事（充電側連系で運用容量超過のため）。上位系統増強工事96カ月。一般負担の上限超過分4,486.2百万円 | AA73: ノンファーム型接続適用（基幹系統:別紙1-1グループ[岩手3]、ローカル系統:なし）、再給電方式（一定の順序）、PCS力率一定制御 89%（有効出力1,998kW程度）、非認証PCSの実機試験成績書提出、出力制御設定の確認書類提出、書類不備による未検討項目あり（系統連系申込時に技術検討）、N-1電制本格適用、運用上の制約あり（作業停止時等の発電抑制・停止）、前提条件: 先行する他発電設備が連系すること | AB73: 接続検討の回答日から1年を経過した場合は契約申込不可 | AC73: high | AE73: 状態: 保留（【保留】フォルダ内）。検討対象年度2023~2024年度。負担金は上位系統増強に係る一般負担の上限超過分を含むため極めて高額。 | AF73: ○ | AG73: 運開希望日に間に合わず / 工期と別にバンク/上位系対策待ち | AH73: =IF(AD73<>"","未読",IF(AND(D73<>"接続検討回答",D73<>"再接続検討",D73<>"契約申込回答"),"",TRIM(IF(O73="","負担金なし ","")&IF(U73="","工期なし ","")&IF(AND(O73<>"",OR(P73="",P73="不明")),"税区分不明 ","")&IF(AC73="low","信頼度low","")))) | AJ73: 未確認 | AM73: 開く | AN73: 【接続検討回答書】No065_奥州市江刺藤里字外ノ沢539（A23124078）.pdf | AO73: 03_電力/02_接続検討/04_回答/【接続検討回答書】No065_奥州市江刺藤里字外ノ沢539（A23124078）.pdf
A74: 73 | B74: 070 | C74: 【保留】/070_五戸町字平佐窪89-1（青森県）_高圧蓄電所 | D74: 接続検討回答 | E74: 東北 | F74: 2025-04-10 | G74: 2025-01-10 | H74: 株式会社パワーエックス（PX五戸BESS1, 受付番号A13124082） | I74: 青森県五戸町字平佐窪89-1 | J74: 1996 | K74: 1995 | L74: 高圧（高圧版回答書） | M74: 南部古館変電所（1号変圧器を10MVA→20MVAへ更新。本文(c)より） | O74: 51800000 | P74: 税込 | Q74: =IF(O74="","",IF(P74="税抜",O74*1.1,O74)/10000) -> 5180 | R74: =IF(Q74="","不明",IF(Q74<=500,"〜500万",IF(Q74<=1000,"500〜1,000万",IF(Q74<=3000,"1,000〜3,000万","3,000万〜")))) -> 3,000万〜 | S74: 工事費負担金の総額 51.8百万円(消費税等相当額 4.7百万円を含む)、税抜47.1百万円（架空線7.7/変電設備15.0/計量0.3/一般負担の上限超過分24.1）。概算工事費の総額 144.4百万円(税込)。別紙「概算工事費及び工事費負担金の総額」より | U74: 12 | V74: =IF(U74="","不明",IF(U74<=6,"〜6ヶ月",IF(U74<=12,"7〜12ヶ月",IF(U74<=24,"13〜24ヶ月","25ヶ月〜")))) -> 7〜12ヶ月 | W74: 配電設備工事 12か月程度 ／ 変電設備工事 37か月程度 ／ 混雑管理システム(ローカル系統) 運開時期は別途HP等でお知らせします。（契約手続き期間は含まず。工事費負担金入金後の期間） | X74: 希望2026年5月11日。回答日＋配電設備工期12か月の単純計算で2026年4月頃（契約手続き期間は含まず）。変電設備工事 37か月程度は別途 | Y74: 電柱1本、高圧引込線15m(AL-ACSR-L120mm2)、電圧調整器1台(逆潮流対応II型SVR 3000kVA)、変圧器増強1台(10MVA→20MVA)、計量器2台・計器用変成器1台(200A)。電圧調整器新設 | Z74: あり: 南部古館変電所1号変圧器の容量更新(10MVA→20MVA)（充電側で負荷上限値超過のため）。変電設備工事37か月程度、変電設備工事の負担金概算15.0百万円、一般負担の上限超過分24.1百万円 | AA74: ノンファーム型接続適用（基幹系統:別紙1-1グループ[青森1]、ローカル系統:154kV西八戸線(0521)、南八戸変電所154/66kV主要変圧器(110)、66kV馬渕線(1A3A)）、再給電方式（一定の順序）、PCS力率一定制御 94%（有効出力1,998kW程度）、非認証PCSの実機試験成績書提出、出力制御設定の確認書類提出、書類不備による未検討項目あり（系統連系申込時に技術検討）、N-1電制本格適用、運用上の制約あり（作業停止時等の発電抑制・停止）、前提条件: 先行する他発電設備が連系すること | AB74: 接続検討の回答日から1年を経過した場合は契約申込不可 | AC74: high | AE74: 状態: 保留（【保留】フォルダ内）。検討対象年度2023~2024年度。 | AF74: ○ | AG74: 工期と別にバンク/上位系対策待ち | AH74: =IF(AD74<>"","未読",IF(AND(D74<>"接続検討回答",D74<>"再接続検討",D74<>"契約申込回答"),"",TRIM(IF(O74="","負担金なし ","")&IF(U74="","工期なし ","")&IF(AND(O74<>"",OR(P74="",P74="不明")),"税区分不明 ","")&IF(AC74="low","信頼度low","")))) | AJ74: 未確認 | AM74: 開く | AN74: 【接続検討回答書】No070_五戸町字平佐窪89-1（A13124082）.pdf | AO74: 03_電力/02_接続検討/04_回答/【接続検討回答書】No070_五戸町字平佐窪89-1（A13124082）.pdf
A75: 74 | B75: 071 | C75: 071_喜多方市松山町鳥見山字中村道下堰西5045-1（福島県）_高圧蓄電所 | D75: 接続検討回答 | E75: 東北 | F75: 2025-04-10 | G75: 2025-01-10 | H75: 株式会社パワーエックス（PX喜多方BESS1, 受付番号A64224019） | I75: 福島県喜多方市松山町鳥見山字中村道下堰西5045-1 | J75: 1996 | K75: 1995 | L75: 高圧（高圧版回答書） | O75: 11000000 | P75: 税込 | Q75: =IF(O75="","",IF(P75="税抜",O75*1.1,O75)/10000) -> 1100 | R75: =IF(Q75="","不明",IF(Q75<=500,"〜500万",IF(Q75<=1000,"500〜1,000万",IF(Q75<=3000,"1,000〜3,000万","3,000万〜")))) -> 1,000〜3,000万 | S75: 工事費負担金の総額 11.0百万円(消費税等相当額 1.0百万円を含む)、税抜10.0百万円（架空線9.7/計量0.3）。概算工事費の総額 11.2百万円(税込)。別紙「概算工事費及び工事費負担金の総額」より | U75: 12 | V75: =IF(U75="","不明",IF(U75<=6,"〜6ヶ月",IF(U75<=12,"7〜12ヶ月",IF(U75<=24,"13〜24ヶ月","25ヶ月〜")))) -> 7〜12ヶ月 | W75: 配電設備工事 12か月程度 ／ 混雑管理システム(ローカル系統) 運開時期は別途HP等でお知らせします。（契約手続き期間は含まず。工事費負担金入金後の期間） | X75: 希望2026年5月11日。回答日＋配電設備工期12か月の単純計算で2026年4月頃（契約手続き期間は含まず） | Y75: 高圧引込線20m(AL-ACSR-L120mm2)、開閉器1台(逆潮流対応型事故区間表示器)、電圧調整器1台(逆潮流対応II型SVR 5000kVA)、計量器2台・計器用変成器1台(200A)。電圧調整器新設、逆潮流対応型機器への取替。冬季は除雪・鉄板敷追加の可能性 | Z75: 上位系統増強工事なし（対象設備表の上位系統増強工事・バンク逆潮流対策は空欄） | AA75: ノンファーム型接続適用（基幹系統:別紙1-1グループ[福島4]、ローカル系統:154kV第一、第二福島線(0626)）、再給電方式（一定の順序）、PCS力率一定制御 93%（有効出力1,998kW程度）、非認証PCSの実機試験成績書提出、出力制御設定の確認書類提出、書類不備による未検討項目あり（系統連系申込時に技術検討）、N-1電制本格適用、運用上の制約あり（作業停止時等の発電抑制・停止） | AB75: 接続検討の回答日から1年を経過した場合は契約申込不可 | AC75: high | AE75: 状態: 進行中（対象フォルダ直下）。検討対象年度2023~2024年度。発電場所の「鳥」は本文テキスト層で欠落しているため、ファイル名・再回答書に合わせて補記。 | AF75: － | AH75: =IF(AD75<>"","未読",IF(AND(D75<>"接続検討回答",D75<>"再接続検討",D75<>"契約申込回答"),"",TRIM(IF(O75="","負担金なし ","")&IF(U75="","工期なし ","")&IF(AND(O75<>"",OR(P75="",P75="不明")),"税区分不明 ","")&IF(AC75="low","信頼度low","")))) | AI75: メモは再接続検討回答(A64225404)側に対応（メモ:喜多方市松山 No071） | AJ75: 未確認 | AM75: 開く | AN75: 【接続検討回答書】No071_喜多方市松山町鳥見山字中村道下堰西5045-1（A64224019）.pdf | AO75: 03_電力/02_接続検討/04_回答/【接続検討回答書】No071_喜多方市松山町鳥見山字中村道下堰西5045-1（A64224019）.pdf
A76: 75 | B76: 071 | C76: 071_喜多方市松山町鳥見山字中村道下堰西5045-1（福島県）_高圧蓄電所 | D76: 再接続検討 | E76: 東北 | F76: 2025-09-30 | G76: 2025-06-30 | H76: 株式会社パワーエックス（PX喜多方BESS1, 受付番号A64225404） | I76: 福島県喜多方市松山町鳥見山字中村道下堰西5045-1 | J76: 1996 | K76: 1995 | L76: 高圧（高圧版回答書） | O76: 4573300000 | P76: 税込 | Q76: =IF(O76="","",IF(P76="税抜",O76*1.1,O76)/10000) -> 457330 | R76: =IF(Q76="","不明",IF(Q76<=500,"〜500万",IF(Q76<=1000,"500〜1,000万",IF(Q76<=3000,"1,000〜3,000万","3,000万〜")))) -> 3,000万〜 | S76: 工事費負担金の総額 4,573.3百万円(消費税等相当額 415.8百万円を含む)、税抜4,157.5百万円（架空線10.0/計量0.3/一般負担の上限超過分4,147.2）。概算工事費の総額 4,677.9百万円(税込)。別紙「概算工事費及び工事費負担金の総額」より | U76: 7 | V76: =IF(U76="","不明",IF(U76<=6,"〜6ヶ月",IF(U76<=12,"7〜12ヶ月",IF(U76<=24,"13〜24ヶ月","25ヶ月〜")))) -> 7〜12ヶ月 | W76: 配電設備工事 7か月程度 ／ 混雑管理システム(ローカル系統) 運開時期は別途HP等でお知らせします。 ／ 上位系統増強工事 (先行する系統利用者の為の増強工事を含む) 10年2ヵ月（契約手続き期間は含まず。工事費負担金入金後の期間） | X76: 希望2026年5月11日。回答日＋配電設備工期7か月の単純計算で2026年4月頃（契約手続き期間は含まず）。上位系統増強工事 (先行する系統利用者の為の増強工事を含む) 10年2ヵ月は別途 | Y76: 高圧引込線20m(AL-ACSR-L120mm2)、開閉器1台(逆潮流対応型事故区間表示器)、柱上変圧器タップ変更2箇所、電圧調整器1台(逆潮流対応II型SVR 5000kVA)、計量器2台・計器用変成器1台(200A)、上位系統増強工事1式（須賀川(変)MT2台取替） | Z76: あり: 須賀川(変)275/154kV主要変圧器取替(2台)が貴社連系のため必要。先行利用者の連系に伴い須賀川(変)・東福島(変)275/154kV主要変圧器増設(各1台)ほかを予定（当社工事・当社負担）。上位系統増強工事10年2ヵ月（先行利用者向け増強を含む）。一般負担の上限超過分4,147.2百万円 | AA76: ノンファーム型接続適用（基幹系統:別紙1-1グループ[福島4]、ローカル系統:154kV第一、第二福島線(0626)）、再給電方式（一定の順序）、PCS力率一定制御 94%（有効出力1,998kW程度）、非認証PCSの実機試験成績書提出、出力制御設定の確認書類提出、早期連系追加対策(充電制限)は適用不可、N-1電制本格適用、運用上の制約あり（作業停止時等の発電抑制・停止） | AB76: 接続検討の回答日から1年を経過した場合は契約申込不可 | AC76: high | AE76: 状態: 進行中（対象フォルダ直下）。検討対象年度2024~2025年度。負担金は上位系統増強に係る一般負担の上限超過分を含むため極めて高額。初回回答(A64224019, 2025-04-10)からの再接続検討。 | AF76: ○ | AG76: 工期と別にバンク/上位系対策待ち | AH76: =IF(AD76<>"","未読",IF(AND(D76<>"接続検討回答",D76<>"再接続検討",D76<>"契約申込回答"),"",TRIM(IF(O76="","負担金なし ","")&IF(U76="","工期なし ","")&IF(AND(O76<>"",OR(P76="",P76="不明")),"税区分不明 ","")&IF(AC76="low","信頼度low","")))) | AI76: 工期一致(7ヶ月)・上位系統増強10年2ヶ月も一致。負担金はメモに値なし（メモ:喜多方市松山 No071） | AJ76: 未確認 | AM76: 開く | AN76: 【再接続検討回答書】No071_喜多方市松山町鳥見山字中村道下堰西5045-1（A64225404）.pdf | AO76: 03_電力/02_接続検討/12_回答（2回目）/【再接続検討回答書】No071_喜多方市松山町鳥見山字中村道下堰西5045-1（A64225404）.pdf
A77: 76 | B77: 072 | C77: 072_福島市小倉寺字中大巻5-1他（福島県）_高圧蓄電所 | D77: 接続検討回答 | E77: 東北 | F77: 2025-05-01 | G77: 2025-02-06 | H77: 株式会社パワーエックス（PX福島BESS1, 受付番号A61124161） | I77: 福島県福島市小倉寺字中大巻5-1他 | J77: 1996 | K77: 1995 | L77: 高圧（高圧版回答書） | N77: 黒岩線（延長。本文(c)より） | O77: 27500000 | P77: 税込 | Q77: =IF(O77="","",IF(P77="税抜",O77*1.1,O77)/10000) -> 2750 | R77: =IF(Q77="","不明",IF(Q77<=500,"〜500万",IF(Q77<=1000,"500〜1,000万",IF(Q77<=3000,"1,000〜3,000万","3,000万〜")))) -> 1,000〜3,000万 | S77: 工事費負担金の総額 27.5百万円(消費税等相当額 2.5百万円を含む)、税抜25.0百万円（架空線24.7/計量0.3）。概算工事費の総額 27.8百万円(税込)。別紙「概算工事費及び工事費負担金の総額」より | U77: 11 | V77: =IF(U77="","不明",IF(U77<=6,"〜6ヶ月",IF(U77<=12,"7〜12ヶ月",IF(U77<=24,"13〜24ヶ月","25ヶ月〜")))) -> 7〜12ヶ月 | W77: 配電設備工事 11か月程度 ／ 混雑管理システム(ローカル系統) 運開時期は別途HP等でお知らせします。（契約手続き期間は含まず。工事費負担金入金後の期間） | X77: 希望2026年6月8日。回答日＋配電設備工期11か月の単純計算で2026年4月頃（契約手続き期間は含まず） | Y77: 電柱3本／5本、高圧線958m／79m(AL-ACSR-L120mm2)、高圧引込線8m、開閉器2台(逆潮流対応型事故区間表示器)、電圧調整器1台(逆潮流対応II型SVR 5000kVA)、計量器2台・計器用変成器1台(200A)。黒岩線延長（高圧線新設、電柱新設・建替）、電圧調整器新設、高圧線張替、逆潮流対応型機器への取替 | Z77: 上位系統増強工事なし（対象設備表の上位系統増強工事・バンク逆潮流対策は空欄） | AA77: ノンファーム型接続適用（基幹系統:別紙1-1グループ[福島4]、ローカル系統:なし）、再給電方式（一定の順序）、PCS力率一定制御 90%（有効出力1,998kW程度）、非認証PCSの実機試験成績書提出、出力制御設定の確認書類提出、書類不備による未検討項目あり（系統連系申込時に技術検討）、N-1電制本格適用、運用上の制約あり（作業停止時等の発電抑制・停止） | AB77: 接続検討の回答日から1年を経過した場合は契約申込不可 | AC77: high | AE77: 状態: 進行中（対象フォルダ直下）。検討対象年度2023~2024年度。2回目の回答(A61125540, 2026-01-15)は「12_回答（2回目）※無効」フォルダにあるため、本行を集計対象とした。 | AF77: ○ | AH77: =IF(AD77<>"","未読",IF(AND(D77<>"接続検討回答",D77<>"再接続検討",D77<>"契約申込回答"),"",TRIM(IF(O77="","負担金なし ","")&IF(U77="","工期なし ","")&IF(AND(O77<>"",OR(P77="",P77="不明")),"税区分不明 ","")&IF(AC77="low","信頼度low","")))) | AJ77: 未確認 | AM77: 開く | AN77: 【接続検討回答書】No072_福島市小倉寺字中大巻5-1他（A61124161）.pdf | AO77: 03_電力/02_接続検討/04_回答/【接続検討回答書】No072_福島市小倉寺字中大巻5-1他（A61124161）.pdf
A78: 77 | B78: 072 | C78: 072_福島市小倉寺字中大巻5-1他（福島県）_高圧蓄電所 | D78: 再接続検討 | E78: 東北 | F78: 2026-01-15 | G78: 2025-10-15 | H78: 株式会社パワーエックス（PX福島BESS1, 受付番号A61125540） | I78: 福島県福島市小倉寺字中大巻5-1他 | J78: 1996 | K78: 1995 | L78: 高圧（高圧版回答書） | N78: 黒岩線（延長。本文(c)より） | O78: 57600000 | P78: 税込 | Q78: =IF(O78="","",IF(P78="税抜",O78*1.1,O78)/10000) -> 5760 | R78: =IF(Q78="","不明",IF(Q78<=500,"〜500万",IF(Q78<=1000,"500〜1,000万",IF(Q78<=3000,"1,000〜3,000万","3,000万〜")))) -> 3,000万〜 | S78: 工事費負担金の総額 57.6百万円(消費税等相当額 5.2百万円を含む)、税抜52.4百万円（架空線52.1/計量0.3）。概算工事費の総額 58.0百万円(税込)。別紙「概算工事費及び工事費負担金の総額」より | U78: 24 | V78: =IF(U78="","不明",IF(U78<=6,"〜6ヶ月",IF(U78<=12,"7〜12ヶ月",IF(U78<=24,"13〜24ヶ月","25ヶ月〜")))) -> 13〜24ヶ月 | W78: 配電設備工事 2年程度 ／ 混雑管理システム(ローカル系統) 運開時期は別途HP等でお知らせします。（契約手続き期間は含まず。工事費負担金入金後の期間） | X78: 希望2026年6月8日。回答日＋配電設備工期24か月の単純計算で2028年1月頃（契約手続き期間は含まず）→希望日に間に合わず | Y78: 電柱3本／7本、高圧線958m／79m(AL-ACSR-L120mm2)、高圧引込線8m、開閉器2台(逆潮流対応型事故区間表示器)、電圧調整器1台(逆潮流対応II型SVR 5,000kVA)、計量器2台・計器用変成器1台(200A)。黒岩線延長（高圧線新設、電柱新設・建替）、河川横断個所の高圧線二回線化のため長尺ポールへ建替、電圧調整器新設、高圧線張替、逆潮流対応型機器への取替 | Z78: 上位系統増強工事なし（対象設備表の上位系統増強工事・バンク逆潮流対策は空欄） | AA78: ノンファーム型接続適用（基幹系統:別紙1-1グループ[福島4]、ローカル系統:なし）、再給電方式（一定の順序）、PCS力率一定制御 92%、非認証PCSの実機試験成績書提出、出力制御設定の確認書類提出、早期連系追加対策(充電制限)は現時点不要、N-1電制本格適用、運用上の制約あり（作業停止時等の発電抑制・停止） | AB78: 接続検討の回答日から1年を経過した場合は契約申込不可 | AC78: high | AE78: 状態: 進行中（対象フォルダ直下）。検討対象年度2024~2025年度。格納フォルダ名が「12_回答（2回目）※無効」（無効の理由は回答書本文からは不明）。ファイル名は「接続検討回答書」だが2回目の回答のため種別は再接続検討とした。河川横断の許可が得られない場合は工期・概算工事費が大幅変更の可能性。初回回答(A61124161, 2025-05-01)あり。 | AF78: － | AG78: 運開希望日に間に合わず | AH78: =IF(AD78<>"","未読",IF(AND(D78<>"接続検討回答",D78<>"再接続検討",D78<>"契約申込回答"),"",TRIM(IF(O78="","負担金なし ","")&IF(U78="","工期なし ","")&IF(AND(O78<>"",OR(P78="",P78="不明")),"税区分不明 ","")&IF(AC78="low","信頼度low","")))) | AJ78: 未確認 | AM78: 開く | AN78: 【接続検討回答書】No072_福島市小倉寺字中大巻5-1他（A61125540）.pdf | AO78: 03_電力/02_接続検討/12_回答（2回目）※無効/【接続検討回答書】No072_福島市小倉寺字中大巻5-1他（A61125540）.pdf
A79: 78 | B79: 073 | C79: 【保留】/073_六戸町大字犬落瀬字四木62-1（青森県）_高圧蓄電所 | D79: 接続検討回答 | E79: 東北 | F79: 2025-05-02 | G79: 2025-02-06 | H79: 株式会社パワーエックス（PX六戸BESS1, 受付番号A13324073） | I79: 青森県六戸町大字犬落瀬字四木62-1 | J79: 1996 | K79: 1995 | L79: 高圧（高圧版回答書） | M79: 六戸変電所（1号変圧器を15MVA→20MVAへ更新。本文(c)より） | O79: 997500000 | P79: 税込 | Q79: =IF(O79="","",IF(P79="税抜",O79*1.1,O79)/10000) -> 99750 | R79: =IF(Q79="","不明",IF(Q79<=500,"〜500万",IF(Q79<=1000,"500〜1,000万",IF(Q79<=3000,"1,000〜3,000万","3,000万〜")))) -> 3,000万〜 | S79: 工事費負担金の総額 997.5百万円(消費税等相当額 90.7百万円を含む)、税抜906.8百万円（架空線63.4/変電設備803.0/計量0.3/一般負担の上限超過分40.1）。概算工事費の総額 1,090.1百万円(税込)。別紙「概算工事費及び工事費負担金の総額」より | U79: 48 | V79: =IF(U79="","不明",IF(U79<=6,"〜6ヶ月",IF(U79<=12,"7〜12ヶ月",IF(U79<=24,"13〜24ヶ月","25ヶ月〜")))) -> 25ヶ月〜 | W79: 配電設備工事 48か月程度 ／ 変電設備工事 37か月程度 ／ 上位系統増強工事 53か月程度 ／ 混雑管理システム(ローカル系統) 運開時期は別途HP等でお知らせします。（契約手続き期間は含まず。工事費負担金入金後の期間） | X79: 希望2026年6月8日。回答日＋配電設備工期48か月の単純計算で2029年5月頃（契約手続き期間は含まず）→希望日に間に合わず。変電設備工事 37か月程度、上位系統増強工事 53か月程度は別途 | Y79: 電柱2本／27本、高圧線1,391m(AL-ACSR-L120mm2)、高圧引込線5m、柱上変圧器タップ変更14個所、電圧調整器1台(逆潮流対応II型SVR 5000kVA)、変圧器増強1台(15MVA→20MVA)、計量器2台・計器用変成器1台(200A)、上位系統増強工事1式（六戸(変)主要変圧器他）。高圧線張替・電柱建替、電圧調整器新設 | Z79: あり: 六戸(変)154/66kV主要変圧器3号増設工事(1台、100MVA)、六戸変電所1号変圧器更新(15MVA→20MVA)。上位系統増強工事53か月程度、変電設備工事37か月程度。変電設備工事の負担金概算803.0百万円、一般負担の上限超過分40.1百万円 | AA79: ノンファーム型接続適用（基幹系統:別紙1-1グループ[青森1]、ローカル系統:154kV南八戸線(0520)、154kV西八戸線(0521)、六戸変電所154/66kV主要変圧器(108)）、再給電方式（一定の順序）、PCS力率一定制御 89%（有効出力1,998kW程度）、非認証PCSの実機試験成績書提出、出力制御設定の確認書類提出、書類不備による未検討項目あり（系統連系申込時に技術検討）、N-1電制本格適用、運用上の制約あり（作業停止時等の発電抑制・停止） | AB79: 接続検討の回答日から1年を経過した場合は契約申込不可 | AC79: high | AE79: 状態: 保留（【保留】フォルダ内）。検討対象年度2023~2024年度。 | AF79: ○ | AG79: 運開希望日に間に合わず / 工期と別にバンク/上位系対策待ち | AH79: =IF(AD79<>"","未読",IF(AND(D79<>"接続検討回答",D79<>"再接続検討",D79<>"契約申込回答"),"",TRIM(IF(O79="","負担金なし ","")&IF(U79="","工期なし ","")&IF(AND(O79<>"",OR(P79="",P79="不明")),"税区分不明 ","")&IF(AC79="low","信頼度low","")))) | AJ79: 未確認 | AM79: 開く | AN79: 【接続検討回答書】No073_六戸町大字犬落瀬字四木62-1（A13324073）.pdf | AO79: 03_電力/02_接続検討/04_回答/【接続検討回答書】No073_六戸町大字犬落瀬字四木62-1（A13324073）.pdf
A80: 79 | B80: 074 | C80: 【保留】/074_階上町大字道仏字耳ケ吠1-15（青森県）_高圧蓄電所 | D80: 接続検討回答 | E80: 東北 | F80: 2025-06-04 | G80: 2025-03-05 | H80: 株式会社パワーエックス（PX階上BESS1, 受付番号A13124109） | I80: 青森県階上町大字道仏字耳ケ吠1-15 | J80: 1996 | K80: 1995 | L80: 高圧（高圧版回答書） | N80: 岩渕線（延長。本文(c)より） | O80: 688200000 | P80: 税込 | Q80: =IF(O80="","",IF(P80="税抜",O80*1.1,O80)/10000) -> 68820 | R80: =IF(Q80="","不明",IF(Q80<=500,"〜500万",IF(Q80<=1000,"500〜1,000万",IF(Q80<=3000,"1,000〜3,000万","3,000万〜")))) -> 3,000万〜 | S80: 工事費負担金の総額 688.2百万円(消費税等相当額 62.6百万円を含む)、税抜625.6百万円（架空線128.8/地中線496.5/計量0.3）。概算工事費の総額 688.5百万円(税込)。別紙「概算工事費及び工事費負担金の総額」より | U80: 50 | V80: =IF(U80="","不明",IF(U80<=6,"〜6ヶ月",IF(U80<=12,"7〜12ヶ月",IF(U80<=24,"13〜24ヶ月","25ヶ月〜")))) -> 25ヶ月〜 | W80: 配電設備工事 50か月程度 ／ 配電設備工事(自社工事) 2027年2月運開予定 ／ 混雑管理システム(ローカル系統) 運開時期は別途HP等でお知らせします。（契約手続き期間は含まず。工事費負担金入金後の期間） | X80: 希望2026年7月6日。回答日＋配電設備工期50か月の単純計算で2029年8月頃（契約手続き期間は含まず）→希望日に間に合わず | Y80: 電柱129本／19本(共架事業者柱含む)、高圧線6,441m(AL-ACSR-L120mm2)、高圧引込線5m、B種接地改修22個所、電圧調整器3台(逆潮流対応II型SVR 3000kVA・サイリスタ型3000kVA)、管路2,293m(3条以下)、マンホール8個所(プレハブMH)、高圧ケーブル2,678m(CVT100mm2)、計量器2台・計器用変成器1台(200A)。岩渕線延長、緊急輸送道路等は地中線路、電圧調整器新設 | Z80: 上位系統増強工事なし。別途、配電設備工事（自社工事）2027年2月運開予定 | AA80: ノンファーム型接続適用（基幹系統:別紙1-1グループ[青森1]、ローカル系統:154kV南八戸線(0520)、154kV西八戸線(0521)八戸変電所154/66kV主要変圧器(109)）、再給電方式（一定の順序）、PCS力率一定制御 93%（有効出力1,998kW程度）、非認証PCSの実機試験成績書提出、出力制御設定の確認書類提出、書類不備による未検討項目あり（系統連系申込時に技術検討）、N-1電制本格適用、運用上の制約あり（作業停止時等の発電抑制・停止） | AB80: 接続検討の回答日から1年を経過した場合は契約申込不可 | AC80: high | AE80: 状態: 保留（【保留】フォルダ内）。検討対象年度2023~2024年度。 | AF80: ○ | AG80: 運開希望日に間に合わず | AH80: =IF(AD80<>"","未読",IF(AND(D80<>"接続検討回答",D80<>"再接続検討",D80<>"契約申込回答"),"",TRIM(IF(O80="","負担金なし ","")&IF(U80="","工期なし ","")&IF(AND(O80<>"",OR(P80="",P80="不明")),"税区分不明 ","")&IF(AC80="low","信頼度low","")))) | AJ80: 未確認 | AM80: 開く | AN80: 【接続検討回答書】No074_階上町大字道仏字耳ケ吠1-15（A13124109）.pdf | AO80: 03_電力/02_接続検討/04_回答/【接続検討回答書】No074_階上町大字道仏字耳ケ吠1-15（A13124109）.pdf
A81: 80 | B81: 075 | C81: 【保留】/075_南部町大字剣吉字蒼前上17-2（青森県）_高圧蓄電所 | D81: 接続検討回答 | E81: 東北 | F81: 2025-06-05 | G81: 2025-03-05 | H81: 株式会社パワーエックス（PX南部BESS1, 受付番号A13124111） | I81: 青森県南部町大字剣吉字蒼前上17-2 | J81: 1996 | K81: 1995 | L81: 高圧（高圧版回答書） | O81: 37100000 | P81: 税込 | Q81: =IF(O81="","",IF(P81="税抜",O81*1.1,O81)/10000) -> 3710 | R81: =IF(Q81="","不明",IF(Q81<=500,"〜500万",IF(Q81<=1000,"500〜1,000万",IF(Q81<=3000,"1,000〜3,000万","3,000万〜")))) -> 3,000万〜 | S81: 工事費負担金の総額 37.1百万円(消費税等相当額 3.4百万円を含む)、税抜33.7百万円（架空線33.4/計量0.3）。概算工事費の総額 37.4百万円(税込)。別紙「概算工事費及び工事費負担金の総額」より | U81: 16 | V81: =IF(U81="","不明",IF(U81<=6,"〜6ヶ月",IF(U81<=12,"7〜12ヶ月",IF(U81<=24,"13〜24ヶ月","25ヶ月〜")))) -> 13〜24ヶ月 | W81: 配電設備工事 16か月程度 ／ 混雑管理システム(ローカル系統) 運開時期は別途HP等でお知らせします。（契約手続き期間は含まず。工事費負担金入金後の期間） | X81: 希望2026年7月6日。回答日＋配電設備工期16か月の単純計算で2026年10月頃（契約手続き期間は含まず）→希望日に間に合わず | Y81: 電柱1本、高圧線2,826m(AL-OC-L200mm2)、高圧引込線5m、柱上変圧器タップ変更1個所、電圧調整器1台(逆潮流対応II型SVR 5000kVA)、計量器2台・計器用変成器1台(200A)。許容電流超過の高圧線張替・自動電圧調整器取替、荷重超過の電柱建替 | Z81: 上位系統増強工事なし（対象設備表の上位系統増強工事・バンク逆潮流対策は空欄） | AA81: ノンファーム型接続適用（基幹系統:別紙1-1グループ[青森1]、ローカル系統:154kV西八戸線(0521)、66kV馬渕線(1A3A)南八戸変電所154/66kV主要変圧器(110)）、再給電方式（一定の順序）、PCS力率一定制御 88%（有効出力1,998kW程度）、非認証PCSの実機試験成績書提出、出力制御設定の確認書類提出、書類不備による未検討項目あり（系統連系申込時に技術検討）、N-1電制本格適用、運用上の制約あり（作業停止時等の発電抑制・停止） | AB81: 接続検討の回答日から1年を経過した場合は契約申込不可 | AC81: high | AE81: 状態: 保留（【保留】フォルダ内）。検討対象年度2023~2024年度。 | AF81: ○ | AG81: 運開希望日に間に合わず | AH81: =IF(AD81<>"","未読",IF(AND(D81<>"接続検討回答",D81<>"再接続検討",D81<>"契約申込回答"),"",TRIM(IF(O81="","負担金なし ","")&IF(U81="","工期なし ","")&IF(AND(O81<>"",OR(P81="",P81="不明")),"税区分不明 ","")&IF(AC81="low","信頼度low","")))) | AJ81: 未確認 | AM81: 開く | AN81: 【接続検討回答書】No075_南部町大字剣吉字蒼前上17-2（A13124111）.pdf | AO81: 03_電力/02_接続検討/04_回答/【接続検討回答書】No075_南部町大字剣吉字蒼前上17-2（A13124111）.pdf
A82: 81 | B82: 077 | C82: 【保留】/077_階上町大字赤保内字西山12-1（青森県）_高圧蓄電所 | D82: 接続検討回答 | E82: 東北 | F82: 2025-06-04 | G82: 2025-03-05 | H82: 株式会社パワーエックス（PX階上BESS2, 受付番号A13124110） | I82: 青森県階上町大字赤保内字西山12-1 | J82: 1996 | K82: 1995 | L82: 高圧（高圧版回答書） | N82: 岩渕線（延長。本文(c)より） | O82: 739400000 | P82: 税込 | Q82: =IF(O82="","",IF(P82="税抜",O82*1.1,O82)/10000) -> 73940 | R82: =IF(Q82="","不明",IF(Q82<=500,"〜500万",IF(Q82<=1000,"500〜1,000万",IF(Q82<=3000,"1,000〜3,000万","3,000万〜")))) -> 3,000万〜 | S82: 工事費負担金の総額 739.4百万円(消費税等相当額 67.2百万円を含む)、税抜672.2百万円（架空線206.9/地中線465.0/計量0.3）。概算工事費の総額 739.8百万円(税込)。別紙「概算工事費及び工事費負担金の総額」より | U82: 55 | V82: =IF(U82="","不明",IF(U82<=6,"〜6ヶ月",IF(U82<=12,"7〜12ヶ月",IF(U82<=24,"13〜24ヶ月","25ヶ月〜")))) -> 25ヶ月〜 | W82: 配電設備工事 55か月程度 ／ 変電設備工事(自社工事) 2027年2月運開予定 ／ 混雑管理システム(ローカル系統) 運開時期は別途HP等でお知らせします。（契約手続き期間は含まず。工事費負担金入金後の期間） | X82: 希望2026年7月6日。回答日＋配電設備工期55か月の単純計算で2030年1月頃（契約手続き期間は含まず）→希望日に間に合わず | Y82: 電柱202本／40本(共架事業者柱含む)、高圧線9,703m(AL-ACSR-L120mm2)、高圧引込線16m、B種接地改修7個所、電圧調整器4台(逆潮流対応II型SVR 3000kVA・サイリスタ型3000kVA)、管路2,266m(3条以下)、マンホール4個所(プレハブMH)、高圧ケーブル2,296m(CVT100mm2)、計量器2台・計器用変成器1台(200A)。岩渕線延長、緊急輸送道路等は地中線路、電圧調整器新設 | Z82: 上位系統増強工事なし。別途、変電設備工事（自社工事）2027年2月運開予定 | AA82: ノンファーム型接続適用（基幹系統:別紙1-1グループ[青森1]、ローカル系統:154kV南八戸線(0520)、154kV西八戸線(0521)八戸変電所154/66kV主要変圧器(109)）、再給電方式（一定の順序）、PCS力率一定制御 93%（有効出力1,998kW程度）、非認証PCSの実機試験成績書提出、出力制御設定の確認書類提出、書類不備による未検討項目あり（系統連系申込時に技術検討）、N-1電制本格適用、運用上の制約あり（作業停止時等の発電抑制・停止） | AB82: 接続検討の回答日から1年を経過した場合は契約申込不可 | AC82: high | AE82: 状態: 保留（【保留】フォルダ内）。検討対象年度2023~2024年度。 | AF82: ○ | AG82: 運開希望日に間に合わず | AH82: =IF(AD82<>"","未読",IF(AND(D82<>"接続検討回答",D82<>"再接続検討",D82<>"契約申込回答"),"",TRIM(IF(O82="","負担金なし ","")&IF(U82="","工期なし ","")&IF(AND(O82<>"",OR(P82="",P82="不明")),"税区分不明 ","")&IF(AC82="low","信頼度low","")))) | AJ82: 未確認 | AM82: 開く | AN82: 【接続検討回答書】No077_階上町大字赤保内字西山12-1（A13124110）.pdf | AO82: 03_電力/02_接続検討/04_回答/【接続検討回答書】No077_階上町大字赤保内字西山12-1（A13124110）.pdf
A83: 82 | B83: 083 | C83: 083_八戸市大字白銀町字佐部長根24-169（青森県）_高圧蓄電所 | D83: 接続検討回答 | E83: 東北 | F83: 2025-06-05 | G83: 2025-03-05 | H83: 株式会社パワーエックス（PX八戸BESS1, 受付番号A13124112） | I83: 青森県八戸市大字白銀町字佐部長根24-169 | J83: 1996 | K83: 1995 | L83: 高圧（高圧版回答書） | O83: 27600000 | P83: 税込 | Q83: =IF(O83="","",IF(P83="税抜",O83*1.1,O83)/10000) -> 2760 | R83: =IF(Q83="","不明",IF(Q83<=500,"〜500万",IF(Q83<=1000,"500〜1,000万",IF(Q83<=3000,"1,000〜3,000万","3,000万〜")))) -> 1,000〜3,000万 | S83: 工事費負担金の総額 27.6百万円(消費税等相当額 2.5百万円を含む)、税抜25.1百万円（架空線24.8/計量0.3）。概算工事費の総額 27.9百万円(税込)。別紙「概算工事費及び工事費負担金の総額」より | U83: 14 | V83: =IF(U83="","不明",IF(U83<=6,"〜6ヶ月",IF(U83<=12,"7〜12ヶ月",IF(U83<=24,"13〜24ヶ月","25ヶ月〜")))) -> 13〜24ヶ月 | W83: 配電設備工事 14か月程度 ／ 変電設備工事(自社工事) 2027年2月運開予定 ／ 混雑管理システム(ローカル系統) 運開時期は別途HP等でお知らせします。（契約手続き期間は含まず。工事費負担金入金後の期間） | X83: 希望2026年7月6日。回答日＋配電設備工期14か月の単純計算で2026年8月頃（契約手続き期間は含まず）→希望日に間に合わず。変電設備工事(自社工事) 2027年2月運開予定は別途 | Y83: 電柱3本、高圧引込線15m(AL-ACSR-L120mm2)、開閉器2台(逆潮流対応型事故区間表示器)、柱上変圧器タップ変更103個所、電圧調整器1台(逆潮流対応II型SVR 5000kVA)、計量器2台・計器用変成器1台(200A)。電圧調整器新設（電柱新設）、逆潮流対応型機器への取替 | Z83: 上位系統増強工事なし。別途、変電設備工事（自社工事）2027年2月運開予定 | AA83: ノンファーム型接続適用（基幹系統:別紙1-1グループ[青森1]、ローカル系統:154kV南八戸線(0520)、154kV西八戸線(0521)、八戸変電所154/66kV主要変圧器(109)）、再給電方式（一定の順序）、PCS力率一定制御 89%（有効出力1,998kW程度）、非認証PCSの実機試験成績書提出、出力制御設定の確認書類提出、書類不備による未検討項目あり（系統連系申込時に技術検討）、N-1電制本格適用、運用上の制約あり（作業停止時等の発電抑制・停止） | AB83: 接続検討の回答日から1年を経過した場合は契約申込不可 | AC83: high | AE83: 状態: 進行中（対象フォルダ直下）。検討対象年度2023~2024年度。 | AF83: ○ | AG83: 運開希望日に間に合わず / 工期と別にバンク/上位系対策待ち | AH83: =IF(AD83<>"","未読",IF(AND(D83<>"接続検討回答",D83<>"再接続検討",D83<>"契約申込回答"),"",TRIM(IF(O83="","負担金なし ","")&IF(U83="","工期なし ","")&IF(AND(O83<>"",OR(P83="",P83="不明")),"税区分不明 ","")&IF(AC83="low","信頼度low","")))) | AJ83: 未確認 | AM83: 開く | AN83: 【接続検討回答書】No083_八戸市大字白銀町字佐部長根24-169（A13124112）.pdf | AO83: 03_電力/02_接続検討/04_回答/【接続検討回答書】No083_八戸市大字白銀町字佐部長根24-169（A13124112）.pdf
A84: 83 | B84: 087 | C84: 【中止】/087_陸前高田市米崎町字糠塚沢97-1（岩手県）_高圧蓄電所 | D84: 接続検討回答 | E84: 東北 | F84: 2025-07-18 | G84: 2025-04-18 | H84: 株式会社パワーエックス（PX陸前高田BESS1, 受付番号A22324067） | I84: 岩手県陸前高田市米崎町字糠塚沢97-1 | J84: 1996 | K84: 1995 | L84: 高圧（高圧版回答書） | O84: 4951900000 | P84: 税込 | Q84: =IF(O84="","",IF(P84="税抜",O84*1.1,O84)/10000) -> 495190 | R84: =IF(Q84="","不明",IF(Q84<=500,"〜500万",IF(Q84<=1000,"500〜1,000万",IF(Q84<=3000,"1,000〜3,000万","3,000万〜")))) -> 3,000万〜 | S84: 工事費負担金の総額 4,951.9百万円(消費税等相当額 450.2百万円を含む)、税抜4,501.7百万円（架空線15.2/計量0.3/一般負担の上限超過分4,486.2）。概算工事費の総額 5,042.2百万円(税込)。別紙「概算工事費及び工事費負担金の総額」より | U84: 7 | V84: =IF(U84="","不明",IF(U84<=6,"〜6ヶ月",IF(U84<=12,"7〜12ヶ月",IF(U84<=24,"13〜24ヶ月","25ヶ月〜")))) -> 7〜12ヶ月 | W84: 配電設備工事 7か月程度 ／ 上位系統増強工事 8年程度 ／ 混雑管理システム(ローカル系統) 運開時期は別途HP等でお知らせします。（契約手続き期間は含まず。工事費負担金入金後の期間） | X84: 希望2026年8月10日。回答日＋配電設備工期7か月の単純計算で2026年2月頃（契約手続き期間は含まず）。上位系統増強工事 8年程度は別途 | Y84: 電柱1本、高圧線157m／138m(AL-ACSR-L120mm2)、高圧引込線15m、開閉器1台(逆潮流対応型事故区間表示器)、電圧調整器1台(逆潮流対応II型SVR 5000kVA)、計量器2台・計器用変成器1台(200A)、上位系統増強工事1式（水沢(変)主要変圧器）。配電線機器の逆潮流対応化、電圧調整器新設、高圧線張替、電柱建替（困難箇所は高圧線ルート変更） | Z84: あり: 水沢(変)275/154kV主要変圧器(MT3)増設工事（充電側連系で運用容量超過のため）。上位系統増強工事8年程度。一般負担の上限超過分4,486.2百万円 | AA84: ノンファーム型接続適用（基幹系統:別紙1-1グループ[岩手3]、ローカル系統:なし）、再給電方式（一定の順序）、PCS力率一定制御 94%（有効出力1,998kW程度）、非認証PCSの実機試験成績書提出、出力制御設定の確認書類提出、書類不備による未検討項目あり（系統連系申込時に技術検討）、N-1電制本格適用、運用上の制約あり（作業停止時等の発電抑制・停止） | AB84: 接続検討の回答日から1年を経過した場合は契約申込不可 | AC84: high | AE84: 状態: 中止（【中止】フォルダ内）。検討対象年度2023~2024年度。負担金は上位系統増強に係る一般負担の上限超過分を含むため極めて高額。 | AF84: ○ | AG84: 工期と別にバンク/上位系対策待ち | AH84: =IF(AD84<>"","未読",IF(AND(D84<>"接続検討回答",D84<>"再接続検討",D84<>"契約申込回答"),"",TRIM(IF(O84="","負担金なし ","")&IF(U84="","工期なし ","")&IF(AND(O84<>"",OR(P84="",P84="不明")),"税区分不明 ","")&IF(AC84="low","信頼度low","")))) | AJ84: 未確認 | AM84: 開く | AN84: 【接続検討回答書】No087_陸前高田市米崎町字糠塚沢97-1（A22324067）.pdf | AO84: 03_電力/02_接続検討/04_回答/【接続検討回答書】No087_陸前高田市米崎町字糠塚沢97-1（A22324067）.pdf
A85: 84 | B85: 088 | C85: 【保留】/088_遠野市遠野町31地割47-1（岩手県）_高圧蓄電所 | D85: 接続検討回答 | E85: 東北 | F85: 2025-07-18 | G85: 2025-04-18 | H85: 株式会社パワーエックス（PX遠野BESS1, 受付番号A23524011） | I85: 岩手県遠野市遠野町31地割47-1 | J85: 1996 | K85: 1995 | L85: 高圧（高圧版回答書） | M85: 遠野変電所（2号変圧器が逆潮流。本文(c)より） | O85: 1075700000 | P85: 税込 | Q85: =IF(O85="","",IF(P85="税抜",O85*1.1,O85)/10000) -> 107570 | R85: =IF(Q85="","不明",IF(Q85<=500,"〜500万",IF(Q85<=1000,"500〜1,000万",IF(Q85<=3000,"1,000〜3,000万","3,000万〜")))) -> 3,000万〜 | S85: 工事費負担金の総額 1,075.7百万円(消費税等相当額 97.8百万円を含む)、税抜977.9百万円（架空線26.4/バンク逆潮流対策7.0/変電設備226.7/計量0.3/一般負担の上限超過分717.5）。概算工事費の総額 1,170.4百万円(税込)。別紙「概算工事費及び工事費負担金の総額」より | U85: 12 | V85: =IF(U85="","不明",IF(U85<=6,"〜6ヶ月",IF(U85<=12,"7〜12ヶ月",IF(U85<=24,"13〜24ヶ月","25ヶ月〜")))) -> 7〜12ヶ月 | W85: 配電設備工事 1年程度 ／ バンク逆潮流対策工事 1年5か月程度 ／ 上位系統増強工事 4年5か月程度 ／ 混雑管理システム(ローカル系統) 運開時期は別途HP等でお知らせします。（契約手続き期間は含まず。工事費負担金入金後の期間） | X85: 希望2026年8月10日。回答日＋配電設備工期12か月の単純計算で2026年7月頃（契約手続き期間は含まず）。バンク逆潮流対策工事 1年5か月程度、上位系統増強工事 4年5か月程度は別途 | Y85: 電柱4本、高圧引込線5m(AL-ACSR-L120mm2)、開閉器2箇所(逆潮流対応型事故区間表示器)、柱上変圧器タップ変更7箇所、電圧調整器2台(逆潮流対応II型SVR 5000kVA・サイリスタ型3000kVA)、バンク逆潮流対策1式(系統地絡検出リレー設置、変圧器盤・電調盤改造)、計量器2台・計器用変成器1台(200A)、上位系統増強工事1式（北上(変)主要変圧器） | Z85: あり: 北上(変)154/66kV主要変圧器(MT2)容変工事(100MVA→150MVA)、遠野変電所2号変圧器バンク逆潮流対策。上位系統増強工事4年5か月程度、バンク逆潮流対策工事1年5か月程度。変電設備工事の負担金概算226.7百万円、一般負担の上限超過分717.5百万円 | AA85: ノンファーム型接続適用（基幹系統:別紙1-1グループ[岩手2]、ローカル系統:なし）、再給電方式（一定の順序）、PCS力率一定制御 86%（有効出力1,998kW程度）、非認証PCSの実機試験成績書提出、出力制御設定の確認書類提出、書類不備による未検討項目あり（系統連系申込時に技術検討）、N-1電制本格適用、運用上の制約あり（作業停止時等の発電抑制・停止） | AB85: 接続検討の回答日から1年を経過した場合は契約申込不可 | AC85: high | AE85: 状態: 保留（【保留】フォルダ内）。検討対象年度2024~2025年度。負担金は上位系統増強に係る一般負担の上限超過分を含むため極めて高額。 | AF85: － | AG85: 工期と別にバンク/上位系対策待ち | AH85: =IF(AD85<>"","未読",IF(AND(D85<>"接続検討回答",D85<>"再接続検討",D85<>"契約申込回答"),"",TRIM(IF(O85="","負担金なし ","")&IF(U85="","工期なし ","")&IF(AND(O85<>"",OR(P85="",P85="不明")),"税区分不明 ","")&IF(AC85="low","信頼度low","")))) | AJ85: 未確認 | AM85: 開く | AN85: 【接続検討回答書】No088_遠野市遠野町31地割47-1（A23524011）.pdf | AO85: 03_電力/02_接続検討/04_回答/【接続検討回答書】No088_遠野市遠野町31地割47-1（A23524011）.pdf
A86: 85 | B86: 088 | C86: 【保留】/088_遠野市遠野町31地割47-1（岩手県）_高圧蓄電所 | D86: 再接続検討 | E86: 東北 | F86: 2026-03-23 | G86: 2025-12-23 | H86: 株式会社パワーエックス（PX遠野BESS1, 受付番号A23525414） | I86: 岩手県遠野市遠野町31地割47-1 | J86: 1998 | K86: 1998 | L86: 高圧（高圧版回答書） | M86: 遠野変電所（2号変圧器が逆潮流。本文(c)より） | O86: 8083900000 | P86: 税込 | Q86: =IF(O86="","",IF(P86="税抜",O86*1.1,O86)/10000) -> 808390 | R86: =IF(Q86="","不明",IF(Q86<=500,"〜500万",IF(Q86<=1000,"500〜1,000万",IF(Q86<=3000,"1,000〜3,000万","3,000万〜")))) -> 3,000万〜 | S86: 工事費負担金の総額 8,083.9百万円(消費税等相当額 734.9百万円を含む)、税抜7,349.0百万円（架空線9.6/バンク逆潮流対策7.0/変電設備22.0/計量0.3/一般負担の上限超過分7,310.1）。概算工事費の総額 8,175.4百万円(税込)。別紙「概算工事費及び工事費負担金の総額」より | U86: 7 | V86: =IF(U86="","不明",IF(U86<=6,"〜6ヶ月",IF(U86<=12,"7〜12ヶ月",IF(U86<=24,"13〜24ヶ月","25ヶ月〜")))) -> 7〜12ヶ月 | W86: 配電設備工事 7か月程度 ／ バンク逆潮流対策工事 1年5か月程度 ／ 上位系統増強工事 7年3か月程度 ／ 混雑管理システム(ローカル系統) 運開時期は別途HP等でお知らせします。（契約手続き期間は含まず。工事費負担金入金後の期間） | X86: 希望2027年4月12日。回答日＋配電設備工期7か月の単純計算で2026年10月頃（契約手続き期間は含まず）。バンク逆潮流対策工事 1年5か月程度、上位系統増強工事 7年3か月程度は別途 | Y86: 電柱1本／1本、高圧引込線6m(AL-ACSR-L120mm2)、開閉器1箇所(逆潮流対応型事故区間表示器)、柱上変圧器タップ変更3箇所、電圧調整器1箇所(逆潮流対応II型SVR 3000kVA)、バンク逆潮流対策1式(系統地絡検出リレー設置、変圧器盤・電調盤改造)、計量器2台・計器用変成器1台(200A)、上位系統増強工事1式（岩手(変)主要変圧器） | Z86: あり: 岩手(変)275/154kV主要変圧器(MT4、5)取替工事(300MVA→300MVA)、同LA(避雷器)移設工事、遠野変電所2号変圧器バンク逆潮流対策。上位系統増強工事7年3か月程度、バンク逆潮流対策工事1年5か月程度。変電設備工事の負担金概算22.0百万円、一般負担の上限超過分7,310.1百万円 | AA86: ノンファーム型接続適用（基幹系統:別紙1-1グループ[岩手2]、ローカル系統:なし）、再給電方式（一定の順序）、PCS力率一定制御 88%、非認証PCSの実機試験成績書提出、出力制御設定の確認書類提出、早期連系追加対策(充電制限)は適用不可、N-1電制本格適用、運用上の制約あり（作業停止時等の発電抑制・停止） | AB86: 接続検討の回答日から1年を経過した場合は契約申込不可 | AC86: high | AE86: 状態: 保留（【保留】フォルダ内）。検討対象年度2024~2025年度。負担金は上位系統増強に係る一般負担の上限超過分を含むため極めて高額。格納フォルダは「12_回答（2回目）」。ファイル名は「接続検討回答書」だが2回目の回答のため種別は再接続検討とした。初回回答(A23524011, 2025-07-18)あり。本文は「別紙3のとおり」だが負担金の表は別紙4。 | AF86: ○ | AG86: 工期と別にバンク/上位系対策待ち | AH86: =IF(AD86<>"","未読",IF(AND(D86<>"接続検討回答",D86<>"再接続検討",D86<>"契約申込回答"),"",TRIM(IF(O86="","負担金なし ","")&IF(U86="","工期なし ","")&IF(AND(O86<>"",OR(P86="",P86="不明")),"税区分不明 ","")&IF(AC86="low","信頼度low","")))) | AJ86: 未確認 | AM86: 開く | AN86: 【接続検討回答書】No088_遠野市遠野町31地割47-1（A23525414）.pdf | AO86: 03_電力/02_接続検討/12_回答（2回目）/【接続検討回答書】No088_遠野市遠野町31地割47-1（A23525414）.pdf
A87: 86 | B87: 089 | C87: 【保留】/089_盛岡市下田字仲平182-1（岩手県）_高圧蓄電所 | D87: 接続検討回答 | E87: 東北 | F87: 2025-07-18 | G87: 2025-04-18 | H87: 株式会社パワーエックス（PX盛岡BESS1, 受付番号A21124158） | I87: 岩手県盛岡市下田字仲平182-1 | J87: 1996 | K87: 1995 | L87: 高圧（高圧版回答書） | N87: 県立大学線（延長。本文(c)より） | O87: 168000000 | P87: 税込 | Q87: =IF(O87="","",IF(P87="税抜",O87*1.1,O87)/10000) -> 16800 | R87: =IF(Q87="","不明",IF(Q87<=500,"〜500万",IF(Q87<=1000,"500〜1,000万",IF(Q87<=3000,"1,000〜3,000万","3,000万〜")))) -> 3,000万〜 | S87: 工事費負担金の総額 168.0百万円(消費税等相当額 15.3百万円を含む)、税抜152.7百万円（架空線14.6/地中線137.8/計量0.3）。概算工事費の総額 168.3百万円(税込)。別紙「概算工事費及び工事費負担金の総額」より | U87: 24 | V87: =IF(U87="","不明",IF(U87<=6,"〜6ヶ月",IF(U87<=12,"7〜12ヶ月",IF(U87<=24,"13〜24ヶ月","25ヶ月〜")))) -> 13〜24ヶ月 | W87: 配電設備工事 2年程度 ／ 混雑管理システム(ローカル系統) 運開時期は別途HP等でお知らせします。（契約手続き期間は含まず。工事費負担金入金後の期間） | X87: 希望2026年8月10日。回答日＋配電設備工期24か月の単純計算で2027年7月頃（契約手続き期間は含まず）→希望日に間に合わず | Y87: 電柱23本、高圧線886m(AL-ACSR-L120mm2)、高圧引込線5m、B種接地改修79箇所、管路591m、高圧ケーブル615m(CVT100mm2)、計量器2台・計器用変成器1台(200A)。県立大学線延長（高圧線新設・電柱新設）、緊急輸送道路等は地中線路 | Z87: 上位系統増強工事なし（対象設備表の上位系統増強工事・バンク逆潮流対策は空欄） | AA87: ノンファーム型接続適用（基幹系統:別紙1-1グループ[岩手1]、ローカル系統:154kV姫神線(0530)、154kV盛岡線(0535)、66kV渋民線(223A)）、再給電方式（一定の順序）、PCS力率一定制御 85%（有効出力1,998kW程度）、非認証PCSの実機試験成績書提出、出力制御設定の確認書類提出、書類不備による未検討項目あり（系統連系申込時に技術検討）、N-1電制本格適用、運用上の制約あり（作業停止時等の発電抑制・停止） | AB87: 接続検討の回答日から1年を経過した場合は契約申込不可 | AC87: high | AE87: 状態: 保留（【保留】フォルダ内）。検討対象年度2024~2025年度。 | AF87: ○ | AG87: 運開希望日に間に合わず | AH87: =IF(AD87<>"","未読",IF(AND(D87<>"接続検討回答",D87<>"再接続検討",D87<>"契約申込回答"),"",TRIM(IF(O87="","負担金なし ","")&IF(U87="","工期なし ","")&IF(AND(O87<>"",OR(P87="",P87="不明")),"税区分不明 ","")&IF(AC87="low","信頼度low","")))) | AJ87: 未確認 | AM87: 開く | AN87: 【接続検討回答書】No089_盛岡市下田字仲平182-1（A21124158）.pdf | AO87: 03_電力/02_接続検討/04_回答/【接続検討回答書】No089_盛岡市下田字仲平182-1（A21124158）.pdf
A88: 87 | B88: 090 | C88: 【保留】/090_八幡平市松尾寄木第13地割391（岩手県）_高圧蓄電所 | D88: 接続検討回答 | E88: 東北 | F88: 2025-08-13 | G88: 2025-05-13 | H88: 株式会社パワーエックス（PX八幡平BESS2, 受付番号A21125409） | I88: 岩手県八幡平市松尾寄木第13地割391 | J88: 1998 | K88: 1998 | L88: 高圧（高圧版回答書） | M88: 柏台変電所（1号変圧器のバンク逆潮流対策。本文(c)より） | O88: 52000000 | P88: 税込 | Q88: =IF(O88="","",IF(P88="税抜",O88*1.1,O88)/10000) -> 5200 | R88: =IF(Q88="","不明",IF(Q88<=500,"〜500万",IF(Q88<=1000,"500〜1,000万",IF(Q88<=3000,"1,000〜3,000万","3,000万〜")))) -> 3,000万〜 | S88: 工事費負担金の総額 52.0百万円(消費税等相当額 4.7百万円を含む)、税抜47.3百万円（架空線40.0/バンク逆潮流対策7.0/計量0.3）。概算工事費の総額 52.4百万円(税込)。別紙「概算工事費及び工事費負担金の総額」より | U88: 21 | V88: =IF(U88="","不明",IF(U88<=6,"〜6ヶ月",IF(U88<=12,"7〜12ヶ月",IF(U88<=24,"13〜24ヶ月","25ヶ月〜")))) -> 13〜24ヶ月 | W88: 配電設備工事 1年9か月程度 ／ バンク逆潮流対策工事 2026年12月運開予定 ／ 混雑管理システム(ローカル系統) 運開時期は別途HP等でお知らせします。（契約手続き期間は含まず。工事費負担金入金後の期間） | X88: 希望2026年9月7日。回答日＋配電設備工期21か月の単純計算で2027年5月頃（契約手続き期間は含まず）→希望日に間に合わず | Y88: 電柱13本(コンクリート柱)、高圧線38m／3,086m(AL-ACSR-L120mm2／AL-OC-L200mm2)、高圧引込線12m、B種接地改修122箇所、バンク逆潮流対策1式(系統地絡検出リレー設置、変圧器盤・電調盤改造)、計量器2台・計器用変成器1台(200A)。高圧線延長・張替、電柱建替、電圧調整器新設・柱上変圧器タップ変更 | Z88: 上位系統増強工事なし。バンク逆潮流対策工事あり（柏台変電所1号変圧器。先行他社申込みによる対策後の設備を使用するため対策費用を負担、負担金概算7.0百万円、2026年12月運開予定） | AA88: ノンファーム型接続適用（基幹系統:別紙1-1グループ[岩手1]、ローカル系統:154kV姫神線(0530),154kV盛岡線(0535),66kV渋民線(223A)66kV沼宮内線(223E),66kV好摩支線(223F)）、再給電方式（一定の順序）、PCS力率一定制御 85%（有効出力1,998.00kW程度）、非認証PCSの実機試験成績書提出、出力制御設定の確認書類提出、書類不備による未検討項目あり（系統連系申込時に技術検討）、早期連系追加対策(充電制限)は現時点不要、N-1電制本格適用、運用上の制約あり（作業停止時等の発電抑制・停止）、前提条件: 先行する他発電設備が連系すること | AB88: 接続検討の回答日から1年を経過した場合は契約申込不可 | AC88: high | AE88: 状態: 保留（【保留】フォルダ内）。検討対象年度2024~2025年度。 | AF88: ○ | AG88: 運開希望日に間に合わず | AH88: =IF(AD88<>"","未読",IF(AND(D88<>"接続検討回答",D88<>"再接続検討",D88<>"契約申込回答"),"",TRIM(IF(O88="","負担金なし ","")&IF(U88="","工期なし ","")&IF(AND(O88<>"",OR(P88="",P88="不明")),"税区分不明 ","")&IF(AC88="low","信頼度low","")))) | AJ88: 未確認 | AM88: 開く | AN88: 【接続検討回答書】No090_八幡平市松尾寄木第13地割391（A21125409）.pdf | AO88: 03_電力/02_接続検討/04_回答/【接続検討回答書】No090_八幡平市松尾寄木第13地割391（A21125409）.pdf
A89: 88 | B89: 093 | C89: 093_八戸市大字櫛引字烏館場1-1（青森県）_高圧蓄電所 | D89: 接続検討回答 | E89: 東北 | F89: 2025-08-26 | G89: 2025-05-27 | H89: 株式会社パワーエックス（PX八戸BESS2, 受付番号A13125405） | I89: 青森県八戸市大字櫛引字烏館場1-1 | J89: 1998 | K89: 1998 | L89: 高圧（高圧版回答書） | O89: 17600000 | P89: 税込 | Q89: =IF(O89="","",IF(P89="税抜",O89*1.1,O89)/10000) -> 1760 | R89: =IF(Q89="","不明",IF(Q89<=500,"〜500万",IF(Q89<=1000,"500〜1,000万",IF(Q89<=3000,"1,000〜3,000万","3,000万〜")))) -> 1,000〜3,000万 | S89: 工事費負担金の総額 17.6百万円(消費税等相当額 1.6百万円を含む)、税抜16.0百万円（架空線15.7/計量0.3）。概算工事費の総額 17.9百万円(税込)。別紙「概算工事費及び工事費負担金の総額」より | U89: 13 | V89: =IF(U89="","不明",IF(U89<=6,"〜6ヶ月",IF(U89<=12,"7〜12ヶ月",IF(U89<=24,"13〜24ヶ月","25ヶ月〜")))) -> 13〜24ヶ月 | W89: 配電設備工事 1年1か月程度 ／ 混雑管理システム(ローカル系統) 運開時期は別途HP等でお知らせします。（契約手続き期間は含まず。工事費負担金入金後の期間） | X89: 希望2026年9月7日。回答日＋配電設備工期13か月の単純計算で2026年9月頃（契約手続き期間は含まず） | Y89: 電柱2本、高圧線740m(AL-ACSR-L120mm2／AL-OC-L200mm2)、高圧引込線15m、柱上変圧器タップ変更35個所、電圧調整器1台(逆潮流対応II型SVR 5,000kVA)、計量器2台・計器用変成器1台(200A)。許容電流超過の高圧線張替・電圧調整器取替、荷重超過の電柱建替 | Z89: 上位系統増強工事なし（対象設備表の上位系統増強工事・バンク逆潮流対策は空欄） | AA89: ノンファーム型接続適用（基幹系統:別紙1-1グループ[青森1]、ローカル系統:154kV西八戸線(0521)、南八戸変電所154/66kV主要変圧器(110)）、再給電方式（一定の順序）、PCS力率一定制御 94%（有効出力1,998.00kW程度）、非認証PCSの実機試験成績書提出、出力制御設定の確認書類提出、書類不備による未検討項目あり（系統連系申込時に技術検討）、早期連系追加対策(充電制限)は現時点不要、N-1電制本格適用、運用上の制約あり（作業停止時等の発電抑制・停止） | AB89: 接続検討の回答日から1年を経過した場合は契約申込不可 | AC89: high | AE89: 状態: 進行中（対象フォルダ直下）。検討対象年度2024~2025年度。 | AF89: ○ | AH89: =IF(AD89<>"","未読",IF(AND(D89<>"接続検討回答",D89<>"再接続検討",D89<>"契約申込回答"),"",TRIM(IF(O89="","負担金なし ","")&IF(U89="","工期なし ","")&IF(AND(O89<>"",OR(P89="",P89="不明")),"税区分不明 ","")&IF(AC89="low","信頼度low","")))) | AJ89: 未確認 | AM89: 開く | AN89: 【接続検討回答書】No093_八戸市大字櫛引字烏館場1-1（A13125405）.pdf | AO89: 03_電力/02_接続検討/04_回答/【接続検討回答書】No093_八戸市大字櫛引字烏館場1-1（A13125405）.pdf
A90: 89 | B90: 097 | C90: 【保留】/097_御前崎市比木1725-1（静岡県）_高圧蓄電所 | D90: 接続検討回答 | E90: 中部 | F90: 2025-09-02 | G90: 2025-06-10 | H90: 株式会社パワーエックス（PX御前崎BESS1, 受付番号AAD240655239） | I90: 静岡県御前崎市比木1725-1 | J90: 1998 | K90: 1998 | L90: 高圧（高圧版回答書） | M90: 佐倉変電所 | N90: 佐倉変電所F22 61タ211より分岐 | O90: 73276400 | P90: 税込 | Q90: =IF(O90="","",IF(P90="税抜",O90*1.1,O90)/10000) -> 7327.64 | R90: =IF(Q90="","不明",IF(Q90<=500,"〜500万",IF(Q90<=1000,"500〜1,000万",IF(Q90<=3000,"1,000〜3,000万","3,000万〜")))) -> 3,000万〜 | S90: 工事費負担金の総額 73,276.4千円(消費税相当額 6,661.5千円を含む)、税抜66,614.9千円（架空線工事66,462.9/計量設備工事152.0）。概算工事費の総額も同額 | T90: 3663000 | U90: 22 | V90: =IF(U90="","不明",IF(U90<=6,"〜6ヶ月",IF(U90<=12,"7〜12ヶ月",IF(U90<=24,"13〜24ヶ月","25ヶ月〜")))) -> 13〜24ヶ月 | W90: 工事費負担金の入金後 22ヶ月程度（契約手続き期間は含まず。別紙4「所要工期について」の工程表は架空線・計器・上位系統で〜24カ月） | X90: 希望2026年10月5日。回答日＋工期22か月の単純計算で2027年7月頃（契約手続き期間は含まず）→希望日に間に合わず | Y90: 電柱新設21本、高圧線新設984m・張替4,157m・撤去984m、高圧引込線18m(OCW-60mm2)、開閉器新設22台・撤去15台、電圧調整器新設2台・取替2台、計量器1台・計器用変成器1台。高圧線の太線化、開閉器取替、電柱建替、電圧調整器取付 | Z90: 上位系統増強工事なし（対象設備表は空欄。別紙4の工程表に上位系統の現場調査・設計／工事施工の行あり） | AA90: ノンファーム型接続適用、再給電方式（上位2電圧500kV・275kV、一定の順序）、PCS力率一定制御（放電時96%遅れ／充電時100%）、変圧器励磁突入電流による瞬時電圧変動対策要、出力変化速度0→100%で5秒以上（ステップ10%以下／ランプ20%/秒以下）、電力品質対策・保護装置は実機試験データで確認、運用上の制約なし、N-1電制本格適用 | AB90: 接続検討の回答日から1年を経過した場合は契約申込不可 | AC90: high | AE90: 状態: 保留（【保留】フォルダ内）。系統連系保証金3,663千円(消費税等相当額333千円を含む)。検討対象年度2025年度。別紙1〜5は別ファイル。同フォルダ[OLD]に差替前の回答書あり（行にしていない）。(5)力率の欄は「〇〇%」表記、電圧変動対策欄の96%を採用。 | AF90: ○ | AG90: 運開希望日に間に合わず | AH90: =IF(AD90<>"","未読",IF(AND(D90<>"接続検討回答",D90<>"再接続検討",D90<>"契約申込回答"),"",TRIM(IF(O90="","負担金なし ","")&IF(U90="","工期なし ","")&IF(AND(O90<>"",OR(P90="",P90="不明")),"税区分不明 ","")&IF(AC90="low","信頼度low","")))) | AJ90: 未確認 | AM90: 開く | AN90: 【接続検討回答書】No097_御前崎市比木1725-1（AAD240655239）.pdf | AO90: 03_電力/02_接続検討/04_回答/【接続検討回答書】No097_御前崎市比木1725-1（AAD240655239）.pdf
A91: 90 | B91: 099 | C91: 【保留】/099_八戸市大字白銀町字佐部長根24-86（青森県）_高圧蓄電所 | D91: 接続検討回答 | E91: 東北 | F91: 2025-09-10 | G91: 2025-06-10 | H91: 株式会社パワーエックス（PX八戸BESS3, 受付番号A13125435） | I91: 青森県八戸市大字白銀町字佐部長根24-86 | J91: 1998 | K91: 1998 | L91: 高圧（高圧版回答書） | N91: 灯台線（延長。本文(c)より） | O91: 30900000 | P91: 税込 | Q91: =IF(O91="","",IF(P91="税抜",O91*1.1,O91)/10000) -> 3090 | R91: =IF(Q91="","不明",IF(Q91<=500,"〜500万",IF(Q91<=1000,"500〜1,000万",IF(Q91<=3000,"1,000〜3,000万","3,000万〜")))) -> 3,000万〜 | S91: 工事費負担金の総額 30.9百万円(消費税等相当額 2.8百万円を含む)、税抜28.1百万円（架空線27.8/計量0.3）。概算工事費の総額 31.2百万円(税込)。別紙「概算工事費及び工事費負担金の総額」より | U91: 10 | V91: =IF(U91="","不明",IF(U91<=6,"〜6ヶ月",IF(U91<=12,"7〜12ヶ月",IF(U91<=24,"13〜24ヶ月","25ヶ月〜")))) -> 7〜12ヶ月 | W91: 配電設備工事 10か月程度 ／ 変電設備工事(負担金対象外) 2027年2月運開予定(自社工事) ／ 混雑管理システム(ローカル系統) 運開時期は別途HP等でお知らせします。（契約手続き期間は含まず。工事費負担金入金後の期間） | X91: 希望2026年10月5日。回答日＋配電設備工期10か月の単純計算で2026年7月頃（契約手続き期間は含まず）。変電設備工事(負担金対象外) 2027年2月運開予定(自社工事)は別途 | Y91: 電柱2本／3本(共架事業者柱含む)、高圧線45m(AL-ACSR-L120mm2)、高圧引込線10m、開閉器1台／2台(逆潮流対応型事故区間表示器・遠制開閉器)、柱上変圧器タップ変更105個所、電圧調整器1台(逆潮流対応II型SVR 5,000kVA)、計量器2台・計器用変成器1台(200A)。灯台線延長（高圧線新設・電柱建替）、電圧調整器新設、逆潮流対応型機器・遠制開閉器への取替 | Z91: 上位系統増強工事なし。別途、変電設備工事（負担金対象外・自社工事）2027年2月運開予定 | AA91: ノンファーム型接続適用（基幹系統:別紙1-1グループ[青森1]、ローカル系統:154kV南八戸線(0520)154kV西八戸線(0521)八戸変電所154/66kV主要変圧器(109)）、再給電方式（一定の順序）、PCS力率一定制御 88%（有効出力1,998.00kW程度）、非認証PCSの実機試験成績書提出、出力制御設定の確認書類提出、書類不備による未検討項目あり（系統連系申込時に技術検討）、早期連系追加対策(充電制限)は現時点不要、N-1電制本格適用、運用上の制約あり（作業停止時等の発電抑制・停止） | AB91: 接続検討の回答日から1年を経過した場合は契約申込不可 | AC91: high | AE91: 状態: 保留（【保留】フォルダ内）。検討対象年度2024~2025年度。 | AF91: － | AG91: 工期と別にバンク/上位系対策待ち | AH91: =IF(AD91<>"","未読",IF(AND(D91<>"接続検討回答",D91<>"再接続検討",D91<>"契約申込回答"),"",TRIM(IF(O91="","負担金なし ","")&IF(U91="","工期なし ","")&IF(AND(O91<>"",OR(P91="",P91="不明")),"税区分不明 ","")&IF(AC91="low","信頼度low","")))) | AJ91: 未確認 | AM91: 開く | AN91: 【接続検討回答書】No099_八戸市大字白銀町字佐部長根24-86（A13125435）.pdf | AO91: 03_電力/02_接続検討/04_回答/【接続検討回答書】No099_八戸市大字白銀町字佐部長根24-86（A13125435）.pdf
A92: 91 | B92: 099 | C92: 【保留】/099_八戸市大字白銀町字佐部長根24-86（青森県）_高圧蓄電所 | D92: 再接続検討 | E92: 東北 | F92: 2026-02-04 | G92: 2025-11-04 | H92: 株式会社パワーエックス（PX八戸BESS3, 受付番号A13125553） | I92: 青森県八戸市大字白銀町字佐部長根24-86 | J92: 1998 | K92: 1998 | L92: 高圧（高圧版回答書） | N92: 鮫線（延長。本文(c)より） | O92: 4120700000 | P92: 税込 | Q92: =IF(O92="","",IF(P92="税抜",O92*1.1,O92)/10000) -> 412070 | R92: =IF(Q92="","不明",IF(Q92<=500,"〜500万",IF(Q92<=1000,"500〜1,000万",IF(Q92<=3000,"1,000〜3,000万","3,000万〜")))) -> 3,000万〜 | S92: 工事費負担金の総額 4,120.7百万円(消費税等相当額 374.6百万円を含む)、税抜3,746.1百万円（架空線48.7/計量0.3/一般負担の上限超過分3,697.1）。概算工事費の総額 4,211.1百万円(税込)。別紙「概算工事費及び工事費負担金の総額」より | U92: 16 | V92: =IF(U92="","不明",IF(U92<=6,"〜6ヶ月",IF(U92<=12,"7〜12ヶ月",IF(U92<=24,"13〜24ヶ月","25ヶ月〜")))) -> 13〜24ヶ月 | W92: 配電設備工事 1年4か月程度 ／ 上位系統増強工事 7年6か月程度 ／ 混雑管理システム(ローカル系統) 運開時期は別途HP等でお知らせします。（契約手続き期間は含まず。工事費負担金入金後の期間） | X92: 希望2026年10月5日。回答日＋配電設備工期16か月の単純計算で2027年6月頃（契約手続き期間は含まず）→希望日に間に合わず。上位系統増強工事 7年6か月程度は別途 | Y92: 電柱2本／25本(共架事業者柱含む)、高圧線976m(AL-ACSR-L120mm2)、高圧引込線10m、電圧調整器1台(逆潮流対応II型SVR 3,000kVA)、計量器2台・計器用変成器1台(200A)、上位系統増強工事1式（青森(変)主要変圧器）。鮫線延長（高圧線新設・電柱建替）、電圧調整器新設 | Z92: あり: 青森(変)275/154kV主要変圧器(MT3)増設（充電側連系で運用容量超過のため）。上位系統増強工事7年6か月程度。一般負担の上限超過分3,697.1百万円 | AA92: ノンファーム型接続適用（基幹系統:別紙1-1グループ[青森1]、ローカル系統:154kV南八戸線(0520)154kV西八戸線(0521)八戸変電所154/66kV主要変圧器(109)）、再給電方式（一定の順序）、PCS力率一定制御 86%、非認証PCSの実機試験成績書提出、出力制御設定の確認書類提出、早期連系追加対策(充電制限)は適用不可、N-1電制本格適用、運用上の制約あり（作業停止時等の発電抑制・停止）、前提条件: 先行する他発電設備が連系すること | AB92: 接続検討の回答日から1年を経過した場合は契約申込不可 | AC92: high | AE92: 状態: 保留（【保留】フォルダ内）。検討対象年度2024~2025年度。負担金は上位系統増強に係る一般負担の上限超過分を含むため極めて高額。初回回答(A13125435, 2025-09-10)からの再接続検討。共架事業者電柱に特殊な電柱が含まれ、詳細設計で工期・工事費が大幅増の可能性。 | AF92: ○ | AG92: 運開希望日に間に合わず / 工期と別にバンク/上位系対策待ち | AH92: =IF(AD92<>"","未読",IF(AND(D92<>"接続検討回答",D92<>"再接続検討",D92<>"契約申込回答"),"",TRIM(IF(O92="","負担金なし ","")&IF(U92="","工期なし ","")&IF(AND(O92<>"",OR(P92="",P92="不明")),"税区分不明 ","")&IF(AC92="low","信頼度low","")))) | AJ92: 未確認 | AM92: 開く | AN92: 【再接続検討回答書】No099_八戸市大字白銀町字佐部長根24-86（A13125553）.pdf | AO92: 03_電力/02_接続検討/12_回答（2回目）/【再接続検討回答書】No099_八戸市大字白銀町字佐部長根24-86（A13125553）.pdf
A93: 92 | B93: 105 | C93: 【保留】/105_新地町谷地小屋字南狼沢2-2（福島県）_高圧蓄電所 | D93: 接続検討回答 | E93: 東北 | F93: 2025-09-09 | G93: 2025-06-10 | H93: 株式会社パワーエックス（PX新地BESS2, 受付番号A61225449） | I93: 福島県新地町谷地小屋字南狼沢2-2 | J93: 1998 | K93: 1998 | L93: 高圧（高圧版回答書） | N93: 埒崎線（延長。本文(c)より） | O93: 130800000 | P93: 税込 | Q93: =IF(O93="","",IF(P93="税抜",O93*1.1,O93)/10000) -> 13080 | R93: =IF(Q93="","不明",IF(Q93<=500,"〜500万",IF(Q93<=1000,"500〜1,000万",IF(Q93<=3000,"1,000〜3,000万","3,000万〜")))) -> 3,000万〜 | S93: 工事費負担金の総額 130.8百万円(消費税等相当額 11.9百万円を含む)、税抜118.9百万円（架空線118.6/計量0.3）。概算工事費の総額 188.2百万円(税込)。別紙「概算工事費及び工事費負担金の総額」より | U93: 58 | V93: =IF(U93="","不明",IF(U93<=6,"〜6ヶ月",IF(U93<=12,"7〜12ヶ月",IF(U93<=24,"13〜24ヶ月","25ヶ月〜")))) -> 25ヶ月〜 | W93: 配電設備工事 4年10か月程度 ／ 上位系統増強工事 2年5か月程度 ／ 混雑管理システム(ローカル系統) 運開時期は別途HP等でお知らせします。（契約手続き期間は含まず。工事費負担金入金後の期間） | X93: 希望2026年10月5日。回答日＋配電設備工期58か月の単純計算で2030年7月頃（契約手続き期間は含まず）→希望日に間に合わず | Y93: 電柱20本／86本、高圧線6,249m(AL-ACSR-L120mm2)、高圧引込線20m、柱上変圧器タップ変更6箇所、電圧調整器2台(逆潮流対応II型SVR 3,000kVA・5,000kVA)、計量器2台・計器用変成器1台(200A)、上位系統増強工事1式（154kV新駒線2号増強）。埒崎線延長（高圧線新設、電柱新設・建替）、電圧調整器新設 | Z93: あり: 154kV新駒線2号増強工事（先行他社申込みにより計画。充電側連系で増強容量の一部を使用するため、連系時期によっては費用一部負担）。上位系統増強工事2年5か月程度 | AA93: ノンファーム型接続適用（基幹系統:別紙1-1グループ[福島2]、ローカル系統:154kV新駒線(0624)、駒ヶ嶺変電所154/66kV主要変圧器(612)）、再給電方式（一定の順序）、PCS力率一定制御 91%（有効出力1,930kW程度）、非認証PCSの実機試験成績書提出、出力制御設定の確認書類提出、書類不備による未検討項目あり（系統連系申込時に技術検討）、早期連系追加対策(充電制限)は適用不可、N-1電制本格適用、運用上の制約あり（作業停止時等の発電抑制・停止） | AB93: 接続検討の回答日から1年を経過した場合は契約申込不可 | AC93: high | AE93: 状態: 保留（【保留】フォルダ内）。検討対象年度2024~2025年度。 | AF93: ○ | AG93: 運開希望日に間に合わず | AH93: =IF(AD93<>"","未読",IF(AND(D93<>"接続検討回答",D93<>"再接続検討",D93<>"契約申込回答"),"",TRIM(IF(O93="","負担金なし ","")&IF(U93="","工期なし ","")&IF(AND(O93<>"",OR(P93="",P93="不明")),"税区分不明 ","")&IF(AC93="low","信頼度low","")))) | AJ93: 未確認 | AM93: 開く | AN93: 【接続検討回答書】No105_新地町谷地小屋字南狼沢2-2（A61225449）.pdf | AO93: 03_電力/02_接続検討/04_回答/【接続検討回答書】No105_新地町谷地小屋字南狼沢2-2（A61225449）.pdf
A94: 93 | B94: 106 | C94: 【保留】/106_磐田市社山493-18（静岡県）_高圧蓄電所 | D94: 接続検討回答 | E94: 中部 | F94: 2025-12-01 | G94: 2025-09-11 | H94: 株式会社パワーエックス（PX磐田BESS1, 受付番号AAD241604839） | I94: 静岡県磐田市社山493-18 | J94: 1998 | K94: 1998 | L94: 高圧（高圧版回答書） | M94: 新平山変電所 | N94: 新平山変電所F35 54エ191より分岐（本文(b)では「新平山変電所FF26」と記載） | O94: 5144700 | P94: 税込 | Q94: =IF(O94="","",IF(P94="税抜",O94*1.1,O94)/10000) -> 514.47 | R94: =IF(Q94="","不明",IF(Q94<=500,"〜500万",IF(Q94<=1000,"500〜1,000万",IF(Q94<=3000,"1,000〜3,000万","3,000万〜")))) -> 500〜1,000万 | S94: 工事費負担金の総額 5,144.7千円(消費税相当額 467.7千円を含む)、税抜4,677.0千円（架空線工事4,525.0/計量設備工事152.0）。概算工事費の総額も同額 | T94: 257000 | U94: 12 | V94: =IF(U94="","不明",IF(U94<=6,"〜6ヶ月",IF(U94<=12,"7〜12ヶ月",IF(U94<=24,"13〜24ヶ月","25ヶ月〜")))) -> 7〜12ヶ月 | W94: 工事費負担金の入金後 12ヶ月程度（契約手続き期間は含まず。別紙4「所要工期について」の工程表は架空線・計器・上位系統で〜12カ月） | X94: 希望2027年1月11日。回答日＋工期12か月の単純計算で2026年12月頃（契約手続き期間は含まず） | Y94: 電柱建替8本、高圧線新設399m、高圧引込線15m(OCW-60mm2)、開閉器新設1台、計量器1台・計器用変成器1台。既設高圧線の容量不足のため高圧線新設、電柱建替 | Z94: 上位系統増強工事なし（対象設備表は空欄） | AA94: ノンファーム型接続適用、再給電方式（一定の順序）、PCS力率一定制御（放電時98%遅れ／充電時100%）、出力変化速度0→100%で5秒以上（ステップ10%以下／ランプ20%/秒以下）、電力品質対策・保護装置は実機試験データで確認、運用上の制約なし | AB94: 接続検討の回答日から1年を経過した場合は契約申込不可 | AC94: high | AE94: 状態: 保留（【保留】フォルダ内）。系統連系保証金257千円(消費税等相当額23.3千円を含む)。検討対象年度2025年度。同じ受付番号で2回目の回答(2026-05-11、「12_回答（2回目）」フォルダ)あり。同じ回答書の写しが03_系統連系/02_作成/添付書類にもある（行にしていない）。 | AF94: － | AH94: =IF(AD94<>"","未読",IF(AND(D94<>"接続検討回答",D94<>"再接続検討",D94<>"契約申込回答"),"",TRIM(IF(O94="","負担金なし ","")&IF(U94="","工期なし ","")&IF(AND(O94<>"",OR(P94="",P94="不明")),"税区分不明 ","")&IF(AC94="low","信頼度low","")))) | AJ94: 未確認 | AM94: 開く | AN94: 【接続検討回答書】No106_磐田市社山493-18（AAD241604839）.pdf | AO94: 03_電力/02_接続検討/04_回答/【接続検討回答書】No106_磐田市社山493-18（AAD241604839）.pdf
A95: 94 | B95: 106 | C95: 【保留】/106_磐田市社山493-18（静岡県）_高圧蓄電所 | D95: 再接続検討 | E95: 中部 | F95: 2026-05-11 | G95: 2026-02-12 | H95: 株式会社パワーエックス（PX磐田BESS1, 受付番号AAD241604839） | I95: 静岡県磐田市社山493-14 | J95: 1998 | K95: 1998 | L95: 高圧（高圧版回答書） | M95: 新平山変電所（配電用変電所の変圧器取替が必要） | N95: 新平山変電所F26 54エ192より分岐 | O95: 325144000 | P95: 税込 | Q95: =IF(O95="","",IF(P95="税抜",O95*1.1,O95)/10000) -> 32514.4 | R95: =IF(Q95="","不明",IF(Q95<=500,"〜500万",IF(Q95<=1000,"500〜1,000万",IF(Q95<=3000,"1,000〜3,000万","3,000万〜")))) -> 3,000万〜 | S95: 工事費負担金の総額 325,144.0千円(消費税相当額 29,558.6千円を含む)、税抜295,585.5千円（架空線工事344.9/計量設備工事158.6/その他77,305.0/一般負担の上限額超過分217,777.0）。概算工事費の総額 415,253.8千円(税込) | T95: 16257000 | U95: 42 | V95: =IF(U95="","不明",IF(U95<=6,"〜6ヶ月",IF(U95<=12,"7〜12ヶ月",IF(U95<=24,"13〜24ヶ月","25ヶ月〜")))) -> 25ヶ月〜 | W95: 工事費負担金の入金後 42ヶ月程度（契約手続き期間は含まず。別紙4「所要工期について」の工程表は変電所工事・配電架空線工事・計器・上位系統で〜42カ月） | X95: 希望2027年1月11日。回答日＋工期42か月の単純計算で2029年11月頃（契約手続き期間は含まず）→希望日に間に合わず | Y95: 高圧引込線20m(OCW-60mm2)、開閉器新設1台、計量器1台・計器用変成器1台、上位系統増強工事1式（配電用変電所の変圧器取替工事） | Z95: あり: 配電用変電所（新平山変電所）の変圧器取替工事（貴社連系による負荷電流の増加で変圧器が許容値を超過するため）。その他77,305.0千円＋一般負担の上限額超過分217,777.0千円 | AA95: ノンファーム型接続適用、再給電方式（一定の順序）、PCS力率一定制御（放電時99%遅れ／充電時100%）、出力変化速度0→100%で5秒以上（ステップ10%以下／ランプ20%/秒以下）、電力品質対策・保護装置は実機試験データで確認、運用上の制約なし | AB95: 接続検討の回答日から1年を経過した場合は契約申込不可 | AC95: high | AE95: 状態: 保留（【保留】フォルダ内）。系統連系保証金16,257千円(消費税等相当額1,477.9千円を含む)。検討対象年度2025年度。格納フォルダは「12_回答（2回目）」で、受付番号は1回目(2025-12-01回答)と同じAAD241604839（申込受付日は2026年2月12日）。ファイル名は「接続検討回答書」だが2回目の回答のため種別は再接続検討とした。発電場所は本文「社山493-14」、1回目・フォルダ名は「社山493-18」。 | AF95: ○ | AG95: 運開希望日に間に合わず | AH95: =IF(AD95<>"","未読",IF(AND(D95<>"接続検討回答",D95<>"再接続検討",D95<>"契約申込回答"),"",TRIM(IF(O95="","負担金なし ","")&IF(U95="","工期なし ","")&IF(AND(O95<>"",OR(P95="",P95="不明")),"税区分不明 ","")&IF(AC95="low","信頼度low","")))) | AJ95: 未確認 | AM95: 開く | AN95: 【接続検討回答書】No106_磐田市社山493-18（AAD241604839）.pdf | AO95: 03_電力/02_接続検討/12_回答（2回目）/【接続検討回答書】No106_磐田市社山493-18（AAD241604839）.pdf
A96: 95 | B96: 108 | C96: 【保留】/108_八戸市大字大久保字大山79-19（青森県）_高圧蓄電所 | D96: 接続検討回答 | E96: 東北 | F96: 2025-09-30 | G96: 2025-06-30 | H96: 株式会社パワーエックス（PX八戸BESS4, 受付番号A13125446） | I96: 青森県八戸市大字大久保字大山79-19 | J96: 1998 | K96: 1998 | L96: 高圧（高圧版回答書） | N96: 岩渕線（延長。本文(c)より） | O96: 346000000 | P96: 税込 | Q96: =IF(O96="","",IF(P96="税抜",O96*1.1,O96)/10000) -> 34600 | R96: =IF(Q96="","不明",IF(Q96<=500,"〜500万",IF(Q96<=1000,"500〜1,000万",IF(Q96<=3000,"1,000〜3,000万","3,000万〜")))) -> 3,000万〜 | S96: 工事費負担金の総額 346.0百万円(消費税等相当額 31.5百万円を含む)、税抜314.5百万円（架空線57.9/地中線256.3/計量0.3）。概算工事費の総額 346.3百万円(税込)。別紙「概算工事費及び工事費負担金の総額」より | U96: 31 | V96: =IF(U96="","不明",IF(U96<=6,"〜6ヶ月",IF(U96<=12,"7〜12ヶ月",IF(U96<=24,"13〜24ヶ月","25ヶ月〜")))) -> 25ヶ月〜 | W96: 配電設備工事 2年7か月程度 ／ 変電設備工事(負担金対象外) 2027年2月運開予定 ／ 混雑管理システム(ローカル系統) 運開時期は別途HP等でお知らせします。（契約手続き期間は含まず。工事費負担金入金後の期間） | X96: 希望2026年11月9日。回答日＋配電設備工期31か月の単純計算で2028年4月頃（契約手続き期間は含まず）→希望日に間に合わず | Y96: 電柱72本／10本(共架事業者柱含む)、高圧線3,251m(AL-ACSR-L120mm2)、高圧引込線12m、B種接地改修26個所、電圧調整器1台(逆潮流対応II型SVR 3000kVA)、管路1,157m(3条以下)、マンホール3個所(プレハブMH)、高圧ケーブル1,247m(CVT100mm2)、計量器2台・計器用変成器1台(200A)。岩渕線延長、離隔確保困難箇所は地中線路、電圧調整器新設 | Z96: 上位系統増強工事なし。別途、変電設備工事（負担金対象外）2027年2月運開予定 | AA96: ノンファーム型接続適用（基幹系統:別紙1-1グループ[青森1]、ローカル系統:154kV南八戸線(0520)154kV西八戸線(0521)八戸変電所154/66kV主要変圧器(109)）、再給電方式（一定の順序）、PCS力率一定制御 85%（有効出力1,998kW程度）、非認証PCSの実機試験成績書提出、出力制御設定の確認書類提出、書類不備による未検討項目あり（系統連系申込時に技術検討）、早期連系追加対策(充電制限)は現時点不要、N-1電制本格適用、運用上の制約あり（作業停止時等の発電抑制・停止） | AB96: 接続検討の回答日から1年を経過した場合は契約申込不可 | AC96: high | AE96: 状態: 保留（【保留】フォルダ内）。検討対象年度2024~2025年度。 | AF96: ○ | AG96: 運開希望日に間に合わず | AH96: =IF(AD96<>"","未読",IF(AND(D96<>"接続検討回答",D96<>"再接続検討",D96<>"契約申込回答"),"",TRIM(IF(O96="","負担金なし ","")&IF(U96="","工期なし ","")&IF(AND(O96<>"",OR(P96="",P96="不明")),"税区分不明 ","")&IF(AC96="low","信頼度low","")))) | AJ96: 未確認 | AM96: 開く | AN96: 【接続検討回答書】No108_八戸市大字大久保字大山79-19（A13125446）.pdf | AO96: 03_電力/02_接続検討/04_回答/【接続検討回答書】No108_八戸市大字大久保字大山79-19（A13125446）.pdf
A97: 96 | B97: 110 | C97: 【保留】/110_佐久市布施2200-1（長野県）_高圧蓄電所 | D97: 接続検討回答 | E97: 中部 | F97: 2025-10-21 | G97: 2025-07-25 | H97: 株式会社パワーエックス（PX佐久BESS1, 受付番号AAD522735200） | I97: 長野県佐久市布施2200-1 | J97: 1998 | K97: 1998 | L97: 高圧（高圧版回答書） | M97: 三岡変電所 | N97: 三岡変電所F16 03モ461(最寄)より分岐 | O97: 77313800 | P97: 税込 | Q97: =IF(O97="","",IF(P97="税抜",O97*1.1,O97)/10000) -> 7731.38 | R97: =IF(Q97="","不明",IF(Q97<=500,"〜500万",IF(Q97<=1000,"500〜1,000万",IF(Q97<=3000,"1,000〜3,000万","3,000万〜")))) -> 3,000万〜 | S97: 工事費負担金の総額 77,313.8千円(消費税相当額 7,028.5千円を含む)、税抜70,285.3千円（架空線工事68,716.4/地中線工事1,416.9/計量設備工事152.0）。概算工事費の総額も同額 | T97: 3865000 | U97: 24 | V97: =IF(U97="","不明",IF(U97<=6,"〜6ヶ月",IF(U97<=12,"7〜12ヶ月",IF(U97<=24,"13〜24ヶ月","25ヶ月〜")))) -> 13〜24ヶ月 | W97: 工事費負担金の入金後 24ヶ月程度（契約手続き期間は含まず。詳細の工期は別紙「所要工期について」参照） | X97: 希望2026年12月7日。回答日＋工期24か月の単純計算で2027年10月頃（契約手続き期間は含まず）→希望日に間に合わず | Y97: 電柱新設8本・建替56本、高圧線新設254m・張替5,776m・撤去134m(OC-W60mm2 送電容量240A)、開閉器新設26台・撤去26台、電圧調整器新設2台・撤去2台、高圧ケーブル張替66m、計量器1台・計器用変成器1台 | Z97: 上位系統増強工事なし（対象設備表は空欄） | AA97: ノンファーム型接続適用（出力制御量に影響を与える主な設備: 信濃変電所500/275kV変圧器）、再給電方式（一定の順序）、早期連系追加対策(充電制限)は現時点不要、力率一定制御（充電時100%・放電時95%）、出力変化速度0→100%で5秒以上、並列時許容周波数・電力品質(EMC試験結果)・保護装置(OVGR動作時の遮断時間)・保安通信用電話設備(連絡体制)は資料提出要、運用上の制約あり（三岡変電所の作業停止時等） | AB97: 接続検討の回答日から1年を経過した場合は契約申込不可 | AC97: high | AE97: 状態: 保留（【保留】フォルダ内）。系統連系保証金3,865千円(消費税等相当額351.3千円を含む)。検討対象年度2025年度。同フォルダ[OLD]に差替前の回答書あり（行にしていない）。 | AF97: ○ | AG97: 運開希望日に間に合わず | AH97: =IF(AD97<>"","未読",IF(AND(D97<>"接続検討回答",D97<>"再接続検討",D97<>"契約申込回答"),"",TRIM(IF(O97="","負担金なし ","")&IF(U97="","工期なし ","")&IF(AND(O97<>"",OR(P97="",P97="不明")),"税区分不明 ","")&IF(AC97="low","信頼度low","")))) | AJ97: 未確認 | AM97: 開く | AN97: 【接続検討回答書】No110_佐久市布施2200-1（AAD522735200）.pdf | AO97: 03_電力/02_接続検討/04_回答/【接続検討回答書】No110_佐久市布施2200-1（AAD522735200）.pdf
A98: 97 | B98: 112 | C98: 【保留】/112_松本市板場406（長野県）_高圧蓄電所 | D98: 接続検討回答 | E98: 中部 | F98: 2025-12-25 | G98: 2025-10-02 | H98: 株式会社パワーエックス（PX松本BESS1, 受付番号AAD535543550） | I98: 長野県松本市板場406 | J98: 1998 | K98: 1998 | L98: 高圧（高圧版回答書） | M98: 犀川変電所 | N98: 犀川変電所F21 10イ671より分岐 | O98: 70000000 | P98: 税込 | Q98: =IF(O98="","",IF(P98="税抜",O98*1.1,O98)/10000) -> 7000 | R98: =IF(Q98="","不明",IF(Q98<=500,"〜500万",IF(Q98<=1000,"500〜1,000万",IF(Q98<=3000,"1,000〜3,000万","3,000万〜")))) -> 3,000万〜 | S98: 工事費負担金の総額 70.0百万円(消費税相当額 6.4百万円を含む)、税抜63.6百万円（架空線工事63.5/計量設備工事0.2）。概算工事費の総額も同額 | T98: 3500000 | U98: 36 | V98: =IF(U98="","不明",IF(U98<=6,"〜6ヶ月",IF(U98<=12,"7〜12ヶ月",IF(U98<=24,"13〜24ヶ月","25ヶ月〜")))) -> 25ヶ月〜 | W98: 工事費負担金の入金後 36ヶ月程度（契約手続き期間は含まず。詳細の工期は別紙「所要工期について」参照） | X98: 希望2027年1月11日。回答日＋工期36か月の単純計算で2028年12月頃（契約手続き期間は含まず）→希望日に間に合わず | Y98: 電柱新設2本・建替52本、高圧線張替6,165m(OC-W60mm2 送電容量240A)、開閉器新設20台・撤去20台、電圧調整器新設1台・取替2台・撤去1台、計量器1台・計器用変成器1台 | Z98: 上位系統増強工事なし（対象設備表は空欄） | AA98: ノンファーム型接続適用、再給電方式（一定の順序）、力率一定制御（充電時100%・放電時98%）、励磁突入電流対策の検討に単線結線図が必要、蓄電池の出力変化速度・EMC試験結果・並列時許容周波数・保安通信用電話設備(連絡体制)は資料提出要、運用上の制約あり（犀川変電所および上位系統設備の作業停止時等） | AB98: 接続検討の回答日から1年を経過した場合は契約申込不可 | AC98: high | AE98: 状態: 保留（【保留】フォルダ内）。系統連系保証金3,500千円(消費税等相当額318.1千円を含む)。検討対象年度2025年度。 | AF98: ○ | AG98: 運開希望日に間に合わず | AH98: =IF(AD98<>"","未読",IF(AND(D98<>"接続検討回答",D98<>"再接続検討",D98<>"契約申込回答"),"",TRIM(IF(O98="","負担金なし ","")&IF(U98="","工期なし ","")&IF(AND(O98<>"",OR(P98="",P98="不明")),"税区分不明 ","")&IF(AC98="low","信頼度low","")))) | AJ98: 未確認 | AM98: 開く | AN98: 【接続検討回答書】No112_松本市板場406（AAD535543550）.pdf | AO98: 03_電力/02_接続検討/04_回答/【接続検討回答書】No112_松本市板場406（AAD535543550）.pdf
A99: 98 | B99: 114 | C99: 【保留】/114_八戸市大字大久保字大塚17-427（青森県）_高圧蓄電所 | D99: 接続検討回答 | E99: 東北 | F99: 2025-12-01 | G99: 2025-09-01 | H99: 株式会社パワーエックス（PX八戸BESS5, 受付番号A13125516） | I99: 青森県八戸市大字大久保字大塚17-427 | J99: 1998 | K99: 1998 | L99: 高圧（高圧版回答書） | N99: 岩渕線（延長。本文(c)より） | O99: 189200000 | P99: 税込 | Q99: =IF(O99="","",IF(P99="税抜",O99*1.1,O99)/10000) -> 18920 | R99: =IF(Q99="","不明",IF(Q99<=500,"〜500万",IF(Q99<=1000,"500〜1,000万",IF(Q99<=3000,"1,000〜3,000万","3,000万〜")))) -> 3,000万〜 | S99: 工事費負担金の総額 189.2百万円(消費税等相当額 17.2百万円を含む)、税抜172.0百万円（架空線76.8/地中線94.9/計量0.3）。概算工事費の総額 189.5百万円(税込)。別紙「概算工事費及び工事費負担金の総額」より | U99: 25 | V99: =IF(U99="","不明",IF(U99<=6,"〜6ヶ月",IF(U99<=12,"7〜12ヶ月",IF(U99<=24,"13〜24ヶ月","25ヶ月〜")))) -> 25ヶ月〜 | W99: 配電設備工事 2年1か月程度 ／ 変電設備工事(負担金対象外) 2027年2月運開予定 ／ 混雑管理システム(ローカル系統) 運開時期は別途HP等でお知らせします。（契約手続き期間は含まず。工事費負担金入金後の期間） | X99: 希望2027年1月11日。回答日＋配電設備工期25か月の単純計算で2028年1月頃（契約手続き期間は含まず）→希望日に間に合わず | Y99: 電柱3本／54本(共架事業者柱含む)、高圧線2,315m(AL-ACSR-L120mm2)、高圧引込線12m、電圧調整器1台(逆潮流対応II型SVR 3000kVA)、架空ケーブル131m(CVT100mm2)、管路384m(3条以下)、マンホール3個所(プレハブMH)、高圧ケーブル394m(CVT100mm2)、計量器2台・計器用変成器1台(200A)。岩渕線延長、離隔確保困難箇所は地中線路、電圧調整器新設 | Z99: 上位系統増強工事なし。別途、変電設備工事（負担金対象外）2027年2月運開予定 | AA99: ノンファーム型接続適用（基幹系統:別紙1-1グループ[青森1]、ローカル系統:154kV南八戸線(0520)154kV西八戸線(0521)八戸変電所154/66kV主要変圧器(109)）、再給電方式（一定の順序）、PCS力率一定制御 85%、非認証PCSの実機試験成績書提出、出力制御設定の確認書類提出、早期連系追加対策(充電制限)は現時点不要、N-1電制本格適用、運用上の制約あり（作業停止時等の発電抑制・停止） | AB99: 接続検討の回答日から1年を経過した場合は契約申込不可 | AC99: high | AE99: 状態: 保留（【保留】フォルダ内）。検討対象年度2024~2025年度。 | AF99: ○ | AG99: 運開希望日に間に合わず | AH99: =IF(AD99<>"","未読",IF(AND(D99<>"接続検討回答",D99<>"再接続検討",D99<>"契約申込回答"),"",TRIM(IF(O99="","負担金なし ","")&IF(U99="","工期なし ","")&IF(AND(O99<>"",OR(P99="",P99="不明")),"税区分不明 ","")&IF(AC99="low","信頼度low","")))) | AJ99: 未確認 | AM99: 開く | AN99: 【接続検討回答書】No114_八戸市大字大久保字大塚17-427（A13125516）.pdf | AO99: 03_電力/02_接続検討/04_回答/【接続検討回答書】No114_八戸市大字大久保字大塚17-427（A13125516）.pdf
A100: 99 | B100: 116 | C100: 116_笠岡市今立2509-1（岡山県）_高圧蓄電所 | D100: 接続検討回答 | E100: 中国 | F100: 2026-02-12 | G100: 2025-11-28 | H100: 株式会社パワーエックス（PX笠岡BESS1, 受付番号G倉敷330） | I100: 岡山県笠岡市今立2509-1 | J100: 1998 | K100: 1998 | L100: 高圧（高圧版回答書、6kV） | M100: 本文に配電用変電所名の記載なし（工事概要図は別紙1）／基幹:新岡山変電所 | N100: 6kV絵師線 今井支37号柱と構内柱を接続（近傍配電線の空き容量不足のため、高圧線延伸および系統変更を行い絵師線へ架空線連系） | O100: 20400000 | P100: 税込 | Q100: =IF(O100="","",IF(P100="税抜",O100*1.1,O100)/10000) -> 2040 | R100: =IF(Q100="","不明",IF(Q100<=500,"〜500万",IF(Q100<=1000,"500〜1,000万",IF(Q100<=3000,"1,000〜3,000万","3,000万〜")))) -> 1,000〜3,000万 | S100: 工事費負担金の総額 20.4百万円(消費税等相当額 1.9百万円を含む)、税抜18.5百万円（架空線17.7/計量0.3/その他(上位系設備対策)0.5）。概算工事費の総額 180.2百万円(税込) | U100: 34 | V100: =IF(U100="","不明",IF(U100<=6,"〜6ヶ月",IF(U100<=12,"7〜12ヶ月",IF(U100<=24,"13〜24ヶ月","25ヶ月〜")))) -> 25ヶ月〜 | W100: 工事費負担金の入金後 34箇月程度。工事費負担金対象となる工事には34箇月程度を見込んでいるためアクセス設備の運用開始希望日には連系不可、連系時期の調整が必要。東岡山変電所ほかの設備対策は実施中だが本対策完了前の連系が可能（契約手続き期間、試充電・試運転期間は含まず） | X100: 希望2027年3月8日は不可（入金後34箇月程度、連系時期の調整が必要） | Y100: 電柱新設28本・建替20本、高圧線新設1,100m・張替等1,802m、高圧引込線20m(ACSR-OC58sq)、計測機能付開閉器1台、計量器2台(精密級)・計器用変成器1台(300A)・自動検針装置1式、上位系統増強工事1式(新岡山(変)N-1充電停止制御装置ほか・新岡山系SSC改造) | Z100: あり: 新岡山(変)500/220kV連系変圧器のN-1電制装置（過負荷保護装置。過負荷検出盤・SSC改造・通信設備）。一般負担額1.3百万円で上限超過なし。東岡山変電所ほかの設備対策は実施中、完了前の連系可 | AA100: ノンファーム型接続、再給電方式（一定の順序）、N-1電制（新岡山(変)連系変圧器事故時の充電停止制御）、早期連系追加対策(充電制限)は現時点不要 | AB100: 接続検討の回答日から1年を経過した場合は契約申込不可 | AC100: medium | AE100: 状態: 進行中（対象フォルダ直下）。別紙1工事概要図・別紙2工事概略工程表は別ファイル。概算工事費内訳の「その他」欄は原文の印字が「143.8.0」と読める。正ファイルは画像のみのPDF（テキスト層なし、原本はパスワード付き）のため、ページ画像を画面表示して目視で読取。数値は検証時に原本と照合のこと。 | AF100: ○ | AG100: 運開希望日に間に合わず | AH100: =IF(AD100<>"","未読",IF(AND(D100<>"接続検討回答",D100<>"再接続検討",D100<>"契約申込回答"),"",TRIM(IF(O100="","負担金なし ","")&IF(U100="","工期なし ","")&IF(AND(O100<>"",OR(P100="",P100="不明")),"税区分不明 ","")&IF(AC100="low","信頼度low","")))) | AJ100: 未確認 | AM100: 開く | AN100: 【接続検討回答書】No116_笠岡市今立2509-1（G倉敷330）.pdf | AO100: 03_電力/02_接続検討/04_回答/【接続検討回答書】No116_笠岡市今立2509-1（G倉敷330）.pdf
...

Sheet 凡例
A1: 接続検討回答 検証一覧
A2: 作成日 | B2: 2026-10-01（2026-10-05 追記）
A3: 出典 | B3: Googleドライブ「10_案件別資料」(フォルダID 1EPmWUK4lLBGkOlqCMv0b9XRxa3kipsIt) 配下の回答書をAIで読取（No1〜45）。2026-10-05追記: 「02_案件資料（PowerX様）」(フォルダID 1HR5tWnhE-0XOhtQnFoUVPtwMLtKMTdw-) 配下の案件別フォルダ（進行中36・【保留】61・【中止】115の計212フォルダ）にある接続検討回答書・再接続検討回答書をAIで読取（No46〜124、79件）
A4: 未取得 | B4: なし（フォルダID 1HR5tWnhE-0XOhtQnFoUVPtwMLtKMTdw- は2026-10-05に読取済。Googleドライブ連携では読めないため、Chromeで開いているアカウント経由で読取）。本文を読めなかったPDFは0件。中国電力NWの回答書のうち15件は画像のみのPDF（テキスト層なし、原本はパスワード付き）で文字を機械抽出できないため、ページ画像を画面に表示して目視で読み取り、読取信頼度をmediumとした（備考に明記、要確認シートにも掲載）
A6: シート | B6: 内容
A7: 回答一覧 | B7: 回答書1件=1行。青字=AI読取値（原本と照合する対象）。黄色セル=検証者が入力
A8: 要確認 | B8: 未読・読取信頼度low・負担金/工期の欠落・7月メモとの差異がある行の抜粋
A9: 集計 | B9: 負担金帯・工期帯・電力会社別の件数（回答一覧から数式で自動集計）
A10: 7月メモ比較 | B10: 2026-07-24分析メモの値と今回読取値の突合
A11: 案件フォルダ | B11: 10_案件別資料の48案件フォルダ＋02_案件資料（PowerX様）の212案件フォルダの回答書有無（追記分は 進行中→保留→中止 の順）
A13: 列の見方
A14: 負担金(税込・万円) | B14: 税抜の記載は×1.1で税込換算（数式）。税区分不明はそのまま
A15: 負担金帯 | B15: 〜500万 / 500〜1,000万 / 1,000〜3,000万 / 3,000万〜 / 不明
A16: 工期帯 | B16: 〜6ヶ月 / 7〜12ヶ月 / 13〜24ヶ月 / 25ヶ月〜 / 不明（起点は「工期の原文」列で確認）
A17: 集計対象 | B17: ○=案件(サイト)ごとの最新の回答（接続検討/再接続検討/契約申込で負担金あり）。集計シートは○のみを数える
A18: 律速・可否メモ | B18: 連系不可・運開希望日に間に合わず・工期と別にバンク逆潮流/上位系対策の待ち がある回答を自動表示
A19: 自動チェック | B19: 負担金なし・工期なし・税区分不明・信頼度low・未読 を自動表示
A20: 検証ステータス | B20: 黄色セルに 未確認 / 確認済 / 要修正 をプルダウンで入力
A21: 注意 | B21: AI読取値はスクリーニング用。社外提出や判断の前に必ず原本PDFで確認すること
A23: 追記分（No46以降）の書き方
A24: 案件名 | B24: フォルダ名のまま。【保留】【中止】フォルダ内の案件は「【保留】/…」「【中止】/…」と表記し、備考の先頭にも「状態: 進行中／保留／中止」を記載
A25: 重複ファイルの扱い | B25: 同じ回答書が複数の名前で保存されている場合は、受付番号つきの「【接続検討回答書】No…（受付番号）.pdf」「【再接続検討回答書】No…」を正として1行にした。「4.」「4-1.」などで始まる写し、原本の「PX…_【秘】…」、[OLD]の差替前は行にしていない
A26: 放電kW／充電kW | B26: 放電kW＝最大受電電力、充電kW＝最大自家消費電力（回答書の記載）
A27: 工期(月) | B27: 東北電力は配電設備(工事)の所要工期を記載。上位系統増強工事・バンク逆潮流対策・変電設備工事の工期や完了予定は「工期の原文」「上位系統増強」に記載し、配電設備より長い／遅い場合は律速・可否メモに「工期と別にバンク/上位系対策待ち」を表示
A28: 運開見込み（東北・中部） | B28: 回答書に希望日への可否の記載がないため、回答日＋工期(月)の単純計算（契約手続き期間は含まず）が運用開始希望日の月を超える場合に「運開希望日に間に合わず」とした
A29: 主な対策工事（東北） | B29: 対象設備表の項目と数量を転記。数量が「／」で2つ並ぶものは表の左→右（新設／建替・張替・取替／改造・改修・撤去）の順で、列の別は原本の表で確認すること
A30: 負担金(円)（東北） | B30: 別紙「概算工事費及び工事費負担金の総額」の工事費負担金の総額（百万円単位・税込）を円に換算。上位系統増強が必要な案件は一般負担の上限超過分を含むため数十億円になるものがある
A31: 読取信頼度（追記分） | B31: high＝PDFのテキストを機械抽出して読取。medium＝画像のみのPDFをページ画像の目視で読取（数字の読み違いの可能性があるため優先して原本照合）。low＝本文を読めなかったもの
A32: 集計対象（追記分） | B32: 案件フォルダごとに、負担金の記載がある最新の接続検討回答／再接続検討を○とした（保留・中止の案件も含む。連系否の回答は記載の負担金概算で集計）。フォルダ名に「※無効」とある回答は○にしていない

Sheet 要確認
A1: 回答一覧No | B1: 案件名 | C1: ファイル名 | D1: 理由 | E1: 原本リンク
A2: 6 | B2: 0916_島根県浜田市宇野町1819-1他3筆（エクスパワー） | C2: 【秘】接続検討回答書 （G松江320）.pdf | D2: 運開希望日に間に合わず | E2: 開く
A3: 7 | B3: 0916_島根県浜田市宇野町1819-1他3筆（エクスパワー） | C3: 916（エクスパワー）_発電設備等に関する契約申込みお回答について（承諾）_中国電力NW_20260707.pdf | D3: 工期(月)が読めていない | E3: 開く
A4: 10 | B4: 0919_山口県周防大島町久賀2086-4（エクスパワー） | C4: 接続検討回答_#0919_山口県大島郡周防大島町久賀2086-4.pdf | D4: 未読: スキャン画像PDF（約7MB）: read_file_contentでは本文テキスト化されず（グラフ断片のみ）、download_file_contentはMCPセッション切断で2回失敗 / 読取信頼度low | E4: 開く
A5: 11 | B5: 1092_三重県伊勢市特高 | C5: 接続検討回答書【株式会社パワーエックスさま（三重伊勢蓄電所）】.pdf | D5: 運開希望日に間に合わず | E5: 開く
A6: 13 | B6: 1113_茨城県行方市浜1985-1,1985-3,1986-3（合同会社高塚） | C6: 接続検討回答.pdf | D6: 未読: スキャン画像PDF（約7MB）: read_file_contentでは本文テキスト化されず（グラフ断片のみ）、download_file_contentはMCPセッション切断で2回失敗 / 読取信頼度low | E6: 開く
A7: 14 | B7: 00_取り下げ、進行不可/1123_北海道道厚岸郡浜中町姉別南三線(エクスパワー）) | C7: 03_接続検討回答書（約款改訂に係る更新）_【託2024_1167】_1.pdf | D7: 運開希望日に間に合わず | E7: 開く
A8: 16 | B8: 1129_崇徳学園入野グラウンド(大柿産業) | C8: 【秘】接続検討回答書(G東広島654).pdf | D8: 運開希望日に間に合わず | E8: 開く
A9: 18 | B9: 1136_兵庫県高砂市中筋3丁目780番（藤栄建設） | C9: 接続検討申込みに対する回答について.pdf | D9: 運開希望日に間に合わず | E9: 開く
A10: 19 | B10: 1147_愛知県岡崎市板田町東流石（中部産業） | C10: 接続検討回答書（株式会社パワーエックス PX愛知県岡崎市蓄電所）.pdf | D10: 工期と別にバンク/上位系対策待ち | E10: 開く
A11: 21 | B11: 1168_兵庫県高砂市伊保四丁目５１６番 | C11: 接続検討申込に対する回答_兵庫高砂伊保四丁目蓄電所.pdf | D11: 運開希望日に間に合わず | E11: 開く
A12: 22 | B12: 確認要_1169_島根県邑智郡梁瀬（石見簗瀬駅）（JR西日本） | C12: 【秘】接続検討回答書（G松江691） | D12: 運開希望日に間に合わず | E12: 開く
A13: 24 | B13: 確認要_1186_島根県邑智郡石原（沢谷駅）（JR西日本） | C13: 【秘】接続検討回答書（G松江670） | D13: 運開希望日に間に合わず | E13: 開く
... A96: 124 | B96: 【保留】/166_小山町上野277-2（静岡県）_高圧蓄電所 | C96: 概算工期回答書_JK26GHZ057572.pdf | D96: 工期と別にバンク/上位系対策待ち | E96: 開く

Sheet 集計
A1: 負担金帯（税込） | B1: 件数 | C1: 平均工期(月)
A2: 〜500万 | B2: =COUNTIFS('回答一覧'!$R$2:$R$125,A2,'回答一覧'!$AF$2:$AF$125,"○") -> 5 | C2: =IFERROR(AVERAGEIFS('回答一覧'!$U$2:$U$125,'回答一覧'!$R$2:$R$125,A2,'回答一覧'!$AF$2:$AF$125,"○"),"-") -> 11
A3: 500〜1,000万 | B3: =COUNTIFS('回答一覧'!$R$2:$R$125,A3,'回答一覧'!$AF$2:$AF$125,"○") -> 5 | C3: =IFERROR(AVERAGEIFS('回答一覧'!$U$2:$U$125,'回答一覧'!$R$2:$R$125,A3,'回答一覧'!$AF$2:$AF$125,"○"),"-") -> 6.4
A4: 1,000〜3,000万 | B4: =COUNTIFS('回答一覧'!$R$2:$R$125,A4,'回答一覧'!$AF$2:$AF$125,"○") -> 8 | C4: =IFERROR(AVERAGEIFS('回答一覧'!$U$2:$U$125,'回答一覧'!$R$2:$R$125,A4,'回答一覧'!$AF$2:$AF$125,"○"),"-") -> 21.625
A5: 3,000万〜 | B5: =COUNTIFS('回答一覧'!$R$2:$R$125,A5,'回答一覧'!$AF$2:$AF$125,"○") -> 71 | C5: =IFERROR(AVERAGEIFS('回答一覧'!$U$2:$U$125,'回答一覧'!$R$2:$R$125,A5,'回答一覧'!$AF$2:$AF$125,"○"),"-") -> 33.151515
A6: 不明 | B6: =COUNTIFS('回答一覧'!$R$2:$R$125,A6,'回答一覧'!$AF$2:$AF$125,"○") -> 0 | C6: =IFERROR(AVERAGEIFS('回答一覧'!$U$2:$U$125,'回答一覧'!$R$2:$R$125,A6,'回答一覧'!$AF$2:$AF$125,"○"),"-") -> -
A7: 合計 | B7: =SUM(B2:B6) -> 89
A9: 工期帯 | B9: 件数 | C9: 平均負担金(税込・万円)
A10: 〜6ヶ月 | B10: =COUNTIFS('回答一覧'!$V$2:$V$125,A10,'回答一覧'!$AF$2:$AF$125,"○") -> 8 | C10: =IFERROR(AVERAGEIFS('回答一覧'!$Q$2:$Q$125,'回答一覧'!$V$2:$V$125,A10,'回答一覧'!$AF$2:$AF$125,"○"),"-") -> 240790.36
A11: 7〜12ヶ月 | B11: =COUNTIFS('回答一覧'!$V$2:$V$125,A11,'回答一覧'!$AF$2:$AF$125,"○") -> 13 | C11: =IFERROR(AVERAGEIFS('回答一覧'!$Q$2:$Q$125,'回答一覧'!$V$2:$V$125,A11,'回答一覧'!$AF$2:$AF$125,"○"),"-") -> 261140.61
A12: 13〜24ヶ月 | B12: =COUNTIFS('回答一覧'!$V$2:$V$125,A12,'回答一覧'!$AF$2:$AF$125,"○") -> 21 | C12: =IFERROR(AVERAGEIFS('回答一覧'!$Q$2:$Q$125,'回答一覧'!$V$2:$V$125,A12,'回答一覧'!$AF$2:$AF$125,"○"),"-") -> 33185.856
A13: 25ヶ月〜 | B13: =COUNTIFS('回答一覧'!$V$2:$V$125,A13,'回答一覧'!$AF$2:$AF$125,"○") -> 42 | C13: =IFERROR(AVERAGEIFS('回答一覧'!$Q$2:$Q$125,'回答一覧'!$V$2:$V$125,A13,'回答一覧'!$AF$2:$AF$125,"○"),"-") -> 35496.861
A14: 不明 | B14: =COUNTIFS('回答一覧'!$V$2:$V$125,A14,'回答一覧'!$AF$2:$AF$125,"○") -> 5 | C14: =IFERROR(AVERAGEIFS('回答一覧'!$Q$2:$Q$125,'回答一覧'!$V$2:$V$125,A14,'回答一覧'!$AF$2:$AF$125,"○"),"-") -> 260980.14
A16: 電力会社 | B16: 件数 | C16: 平均負担金(税込・万円) | D16: 平均工期(月) | E16: 最大負担金(税込・万円) | F16: 最長工期(月)
A17: 中国 | B17: =COUNTIFS('回答一覧'!$E$2:$E$125,A17,'回答一覧'!$AF$2:$AF$125,"○") -> 28 | C17: =IFERROR(AVERAGEIFS('回答一覧'!$Q$2:$Q$125,'回答一覧'!$E$2:$E$125,A17,'回答一覧'!$AF$2:$AF$125,"○"),"-") -> 59388.953 | D17: =IFERROR(AVERAGEIFS('回答一覧'!$U$2:$U$125,'回答一覧'!$E$2:$E$125,A17,'回答一覧'!$AF$2:$AF$125,"○"),"-") -> 45.166667 | E17: =IF(COUNTIFS('回答一覧'!$E$2:$E$125,A17,'回答一覧'!$AF$2:$AF$125,"○",'回答一覧'!$Q$2:$Q$125,">0")=0,"-",MAXIFS('回答一覧'!$Q$2:$Q$125,'回答一覧'!$E$2:$E$125,A17,'回答一覧'!$AF$2:$AF$125,"○")) -> 1207850 | F17: =IF(COUNTIFS('回答一覧'!$E$2:$E$125,A17,'回答一覧'!$AF$2:$AF$125,"○",'回答一覧'!$U$2:$U$125,">0")=0,"-",MAXIFS('回答一覧'!$U$2:$U$125,'回答一覧'!$E$2:$E$125,A17,'回答一覧'!$AF$2:$AF$125,"○")) -> 144
A18: 中部 | B18: =COUNTIFS('回答一覧'!$E$2:$E$125,A18,'回答一覧'!$AF$2:$AF$125,"○") -> 10 | C18: =IFERROR(AVERAGEIFS('回答一覧'!$Q$2:$Q$125,'回答一覧'!$E$2:$E$125,A18,'回答一覧'!$AF$2:$AF$125,"○"),"-") -> 17035.977 | D18: =IFERROR(AVERAGEIFS('回答一覧'!$U$2:$U$125,'回答一覧'!$E$2:$E$125,A18,'回答一覧'!$AF$2:$AF$125,"○"),"-") -> 26.444444 | E18: =IF(COUNTIFS('回答一覧'!$E$2:$E$125,A18,'回答一覧'!$AF$2:$AF$125,"○",'回答一覧'!$Q$2:$Q$125,">0")=0,"-",MAXIFS('回答一覧'!$Q$2:$Q$125,'回答一覧'!$E$2:$E$125,A18,'回答一覧'!$AF$2:$AF$125,"○")) -> 92290 | F18: =IF(COUNTIFS('回答一覧'!$E$2:$E$125,A18,'回答一覧'!$AF$2:$AF$125,"○",'回答一覧'!$U$2:$U$125,">0")=0,"-",MAXIFS('回答一覧'!$U$2:$U$125,'回答一覧'!$E$2:$E$125,A18,'回答一覧'!$AF$2:$AF$125,"○")) -> 57
A19: 九州 | B19: =COUNTIFS('回答一覧'!$E$2:$E$125,A19,'回答一覧'!$AF$2:$AF$125,"○") -> 3 | C19: =IFERROR(AVERAGEIFS('回答一覧'!$Q$2:$Q$125,'回答一覧'!$E$2:$E$125,A19,'回答一覧'!$AF$2:$AF$125,"○"),"-") -> 22680 | D19: =IFERROR(AVERAGEIFS('回答一覧'!$U$2:$U$125,'回答一覧'!$E$2:$E$125,A19,'回答一覧'!$AF$2:$AF$125,"○"),"-") -> 32 | E19: =IF(COUNTIFS('回答一覧'!$E$2:$E$125,A19,'回答一覧'!$AF$2:$AF$125,"○",'回答一覧'!$Q$2:$Q$125,">0")=0,"-",MAXIFS('回答一覧'!$Q$2:$Q$125,'回答一覧'!$E$2:$E$125,A19,'回答一覧'!$AF$2:$AF$125,"○")) -> 31140 | F19: =IF(COUNTIFS('回答一覧'!$E$2:$E$125,A19,'回答一覧'!$AF$2:$AF$125,"○",'回答一覧'!$U$2:$U$125,">0")=0,"-",MAXIFS('回答一覧'!$U$2:$U$125,'回答一覧'!$E$2:$E$125,A19,'回答一覧'!$AF$2:$AF$125,"○")) -> 32
A20: 北海道 | B20: =COUNTIFS('回答一覧'!$E$2:$E$125,A20,'回答一覧'!$AF$2:$AF$125,"○") -> 2 | C20: =IFERROR(AVERAGEIFS('回答一覧'!$Q$2:$Q$125,'回答一覧'!$E$2:$E$125,A20,'回答一覧'!$AF$2:$AF$125,"○"),"-") -> 43900 | D20: =IFERROR(AVERAGEIFS('回答一覧'!$U$2:$U$125,'回答一覧'!$E$2:$E$125,A20,'回答一覧'!$AF$2:$AF$125,"○"),"-") -> 31 | E20: =IF(COUNTIFS('回答一覧'!$E$2:$E$125,A20,'回答一覧'!$AF$2:$AF$125,"○",'回答一覧'!$Q$2:$Q$125,">0")=0,"-",MAXIFS('回答一覧'!$Q$2:$Q$125,'回答一覧'!$E$2:$E$125,A20,'回答一覧'!$AF$2:$AF$125,"○")) -> 81450 | F20: =IF(COUNTIFS('回答一覧'!$E$2:$E$125,A20,'回答一覧'!$AF$2:$AF$125,"○",'回答一覧'!$U$2:$U$125,">0")=0,"-",MAXIFS('回答一覧'!$U$2:$U$125,'回答一覧'!$E$2:$E$125,A20,'回答一覧'!$AF$2:$AF$125,"○")) -> 36
A21: 東京 | B21: =COUNTIFS('回答一覧'!$E$2:$E$125,A21,'回答一覧'!$AF$2:$AF$125,"○") -> 2 | C21: =IFERROR(AVERAGEIFS('回答一覧'!$Q$2:$Q$125,'回答一覧'!$E$2:$E$125,A21,'回答一覧'!$AF$2:$AF$125,"○"),"-") -> 7861.975 | D21: =IFERROR(AVERAGEIFS('回答一覧'!$U$2:$U$125,'回答一覧'!$E$2:$E$125,A21,'回答一覧'!$AF$2:$AF$125,"○"),"-") -> 18 | E21: =IF(COUNTIFS('回答一覧'!$E$2:$E$125,A21,'回答一覧'!$AF$2:$AF$125,"○",'回答一覧'!$Q$2:$Q$125,">0")=0,"-",MAXIFS('回答一覧'!$Q$2:$Q$125,'回答一覧'!$E$2:$E$125,A21,'回答一覧'!$AF$2:$AF$125,"○")) -> 13100 | F21: =IF(COUNTIFS('回答一覧'!$E$2:$E$125,A21,'回答一覧'!$AF$2:$AF$125,"○",'回答一覧'!$U$2:$U$125,">0")=0,"-",MAXIFS('回答一覧'!$U$2:$U$125,'回答一覧'!$E$2:$E$125,A21,'回答一覧'!$AF$2:$AF$125,"○")) -> 18
A22: 東北 | B22: =COUNTIFS('回答一覧'!$E$2:$E$125,A22,'回答一覧'!$AF$2:$AF$125,"○") -> 40 | C22: =IFERROR(AVERAGEIFS('回答一覧'!$Q$2:$Q$125,'回答一覧'!$E$2:$E$125,A22,'回答一覧'!$AF$2:$AF$125,"○"),"-") -> 170061.5 | D22: =IFERROR(AVERAGEIFS('回答一覧'!$U$2:$U$125,'回答一覧'!$E$2:$E$125,A22,'回答一覧'!$AF$2:$AF$125,"○"),"-") -> 21.575 | E22: =IF(COUNTIFS('回答一覧'!$E$2:$E$125,A22,'回答一覧'!$AF$2:$AF$125,"○",'回答一覧'!$Q$2:$Q$125,">0")=0,"-",MAXIFS('回答一覧'!$Q$2:$Q$125,'回答一覧'!$E$2:$E$125,A22,'回答一覧'!$AF$2:$AF$125,"○")) -> 808390 | F22: =IF(COUNTIFS('回答一覧'!$E$2:$E$125,A22,'回答一覧'!$AF$2:$AF$125,"○",'回答一覧'!$U$2:$U$125,">0")=0,"-",MAXIFS('回答一覧'!$U$2:$U$125,'回答一覧'!$E$2:$E$125,A22,'回答一覧'!$AF$2:$AF$125,"○")) -> 58
A23: 関西 | B23: =COUNTIFS('回答一覧'!$E$2:$E$125,A23,'回答一覧'!$AF$2:$AF$125,"○") -> 4 | C23: =IFERROR(AVERAGEIFS('回答一覧'!$Q$2:$Q$125,'回答一覧'!$E$2:$E$125,A23,'回答一覧'!$AF$2:$AF$125,"○"),"-") -> 1637.0575 | D23: =IFERROR(AVERAGEIFS('回答一覧'!$U$2:$U$125,'回答一覧'!$E$2:$E$125,A23,'回答一覧'!$AF$2:$AF$125,"○"),"-") -> 17.25 | E23: =IF(COUNTIFS('回答一覧'!$E$2:$E$125,A23,'回答一覧'!$AF$2:$AF$125,"○",'回答一覧'!$Q$2:$Q$125,">0")=0,"-",MAXIFS('回答一覧'!$Q$2:$Q$125,'回答一覧'!$E$2:$E$125,A23,'回答一覧'!$AF$2:$AF$125,"○")) -> 3250 | F23: =IF(COUNTIFS('回答一覧'!$E$2:$E$125,A23,'回答一覧'!$AF$2:$AF$125,"○",'回答一覧'!$U$2:$U$125,">0")=0,"-",MAXIFS('回答一覧'!$U$2:$U$125,'回答一覧'!$E$2:$E$125,A23,'回答一覧'!$AF$2:$AF$125,"○")) -> 30
A25: 検証ステータス | B25: 件数
A26: 未確認 | B26: =COUNTIF('回答一覧'!$AJ$2:$AJ$125,A26) -> 124
A27: 確認済 | B27: =COUNTIF('回答一覧'!$AJ$2:$AJ$125,A27) -> 0
A28: 要修正 | B28: =COUNTIF('回答一覧'!$AJ$2:$AJ$125,A28) -> 0

Sheet 7月メモ比較
A1: キーワード | B1: 7月メモの案件 | C1: メモ負担金(円) | D1: メモ税区分 | E1: メモ工期(月) | F1: メモ備考 | G1: 今回の該当行(回答一覧No) | H1: 今回の突合結果
A2: 鹿屋 | B2: 鹿児島県鹿屋市上小原 | C2: 61400000 | D2: 不明 | E2: 16 | F2: 付箋メモ・要再確認 | G2: 今回フォルダに無し
A3: 由仁 | B3: 北海道由仁町(案件1135) | C3: 4100000 | D3: 税込 | E3: 6 | G3: 17 | H3: 比較不可(片方に値なし)（メモ:北海道由仁町(案件1135)）
A4: 神崎 | B4: 大分市神崎(東盛) | C4: 9200000 | D4: 税込 | E4: 3 | G4: 今回フォルダに無し
A5: 久山 | B5: 福岡県久山町(KMP) | C5: 16300000 | D5: 税抜 | E5: 17 | G5: 今回フォルダに無し
A6: 喜多方 | B6: 喜多方市松山 No071 | D6: 不明 | E6: 7 | F6: 上位系統増強10年2ヶ月 | G6: 74, 75 | H6: メモは再接続検討回答(A64225404)側に対応（メモ:喜多方市松山 No071） | 工期一致(7ヶ月)・上位系統増強10年2ヶ月も一致。負担金はメモに値なし（メモ:喜多方市松山 No071）
A7: 崇徳 | B7: 東広島654(1129崇徳) | D7: 不明 | F7: 7月時点 未読(PDFパスワード付) | G7: 15, 16 | H7: 比較不可(片方に値なし)（メモ:東広島654(1129崇徳)） | 比較不可(片方に値なし)（メモ:東広島654(1129崇徳)）
A8: 関市 | B8: 岐阜県関市小屋名(B646G) | C8: 6200000 | D8: 税込 | E8: 18 | F8: 保証金31万円 | G8: 今回フォルダに無し
A9: 柏原 | B9: 長野県信濃町 柏原2390-1 | C9: 8500000 | D9: 税込 | E9: 6 | F9: 保証金42.5万 | G9: 今回フォルダに無し
A10: 野尻 | B10: 長野県信濃町 野尻蓄電所 | C10: 17820000 | D10: 税抜 | E10: 24 | F10: 契約申込回答 | G10: 今回フォルダに無し
A11: 吉井 | B11: 群馬県高崎市吉井町(特高) | C11: 464000000 | D11: 税抜 | E11: 26 | F11: 保証金2,551万 | G11: 今回フォルダに無し

Sheet 案件フォルダ
A1: 案件フォルダ | B1: 回答書件数 | C1: 備考 | D1: フォルダリンク
A2: 確認要_1169_島根県邑智郡梁瀬（石見簗瀬駅）（JR西日本） | B2: 1 | D2: 開く
A3: 1168_兵庫県高砂市伊保四丁目５１６番 | B3: 1 | D3: 開く
A4: 1315_長野県上水内郡信濃町案件（本久） | B4: 1 | D4: 開く
A5: xxxx_熊本県玉名郡（CIP）210MW設備変更_小嶋さん | B5: 6 | D5: 開く
A6: 1277_宮城県亘理郡山元町坂元字大檀7番2他（ソーラークリエート） | B6: 0 | C6: 01_先方より受領した資料（位置図・公図・登記地図PDF、Document.docx）、02_自社スクリーニング（案件チェックシートxlsx、ルート表pptx、ハザード等スクリーンショットpng）のみ。系統連系の回答書類なし | D6: 開く
A7: 1704_岩手県九戸郡軽米町大字軽米第14地割字土弓6番1 | B7: 0 | C7: 02.自社スクリーニング（PX案件チェックシートxlsx、ルート表pptx、ハザード等gif）のみ。01_先方より受領した資料は空。系統連系の回答書類なし | D7: 開く
A8: 1703_岩手県九戸郡軽米町大字晴山第8地割字大崎山94番2 | B8: 0 | C8: 02.自社スクリーニング（PX案件チェックシートxlsx、ルート表pptx、ハザード等gif）のみ。01_先方より受領した資料は空。系統連系の回答書類なし | D8: 開く
A9: xxxx_熊本県阿蘇郡杖立（アークエル）設備変更_小嶋さん | B9: 1 | D9: 開く
A10: 確認要_1186_島根県邑智郡石原（沢谷駅）（JR西日本） | B10: 1 | D10: 開く
A11: 1228_広島県福山市神島町142-2（JR西日本） | B11: 1 | D11: 開く
A12: 1519_大阪府寝屋川市石津南町9-29 | B12: 0 | C12: 回答書なし。フォルダ内: PXさま_電力申請依頼シート.xlsx、desktop.ini、01.受取資料/image.png のみ | D12: 開く
A13: 1326_大栄工業_伊賀市案件 | B13: 1 | D13: 開く
A14: 1227_島根県出雲市知井宮町1360-1（JR西日本） | B14: 1 | D14: 開く
A15: 1517_大阪府池田市桃園1丁目9-14 | B15: 0 | C15: 回答書なし。フォルダ内: 02.接続検討/(接続検討申込書xlsx(old含む)、PCS出力制限docx、単線結線図pdf、特別措置確認書xlsx、仕様書pdf x15)、登記PDF x6、電力申請依頼シートxlsx、image.png | D15: 開く
A16: 1518_大阪府茨木市中津町22 | B16: 0 | C16: 回答書なし。フォルダ内: 02.接続検討/(接続検討申込書xlsx(old含む)、PCS出力制限docx、単線結線図pdf、特別措置確認書xlsx、仕様書pdf x15)、登記PDF、電力申請依頼シートxlsx、image.png | D16: 開く
A17: 1239_つくばみらい10MW（自然電力→三田証券） | B17: 1 | D17: 開く
A18: 00_取り下げ、進行不可 | B18: 0 | C18: 取り下げ・進行不可の24サブ案件フォルダ。回答書があるのは1123のみ（別レコード）。他23件(1133,1276,1138,1085,XXX朝来,1275,1221,1391,1224,1198,1268,1222,1257,1219,1267,1191,1263,1280,1140,1131,1132,1141,1142)は接続検討申込書xlsx・様式5の3〜5の7pdf・PCS出力制限docx・機器仕様書pdf・チェックシート/ルート表・スクリーニングpng・登記等のみ（1275/1268/1267は申込書一式【取下げ済み】）。1141/1142の『中国電力事前相談20260122.xlsx』は自社作成シート（内容『7MW』のみ）で回答書ではない | D18: 開く
A19: 1326_三重県伊賀市予野字向川540番2 | B19: 4 | D19: 開く
A20: 1437_大阪府大阪市平野区長吉長原４丁目１８−１０（タイヨー平野店） | B20: 1 | D20: 開く
A21: 1453_南房総市千倉町大貫１０９６－３ | B21: 0 | C21: 回答書なし。フォルダ内: 01_先方より受領した資料(物件資料pptx・登記PDF)、02_自社スクリーニング(チェックシートxlsx・ルート表pptx・スクリーニングpng x15) | D21: 開く
A22: 1405_南九州市頴娃町上別府字入尾原3942-1（つくる地所） | B22: 0 | C22: 回答書なし。案件チェックシートxlsx、ルート表pptx、許認可スクリーニング画像png(13件)、先方受領資料/土地謄本.pdfのみ。接続検討申込書も未格納。 | D22: 開く
A23: 1372_岐阜県土岐市鶴里町柿野1316-1 | B23: 0 | C23: 回答書なし。03.接続検討申込書一式（申込書xlsx・様式5の4〜5の8図面PDF・PCS出力制限docx・出力制御装置仕様確認依頼書・機器仕様書PDF群）=申込側書類のみで電力会社回答は未格納。他に案件概要PDF、チェックシート、ルート表、スクリーニング画像。 | D23: 開く
A24: 1382_宮崎県児湯郡新富町 | B24: 0 | C24: 回答書なし。03.接続検討申込書一式（申込書xlsx/押印済PDF、PCS仕様、技術資料PDF群、送付書20260629.pdf=九電送配サービス宛に2026-06-29接続検討申込書一式を送付した旨の当方送付状）。九州エリアで接続検討申込済みだが回答書は未格納。 | D24: 開く
A25: 1412_秦野案件(セブンシーズアドバイザーズ) | B25: 1 | D25: 開く
A26: 1211_佐賀県佐賀市鍋島町大字森田（ソーラークリエート） | B26: 0 | C26: 回答書なし。先方受領資料（測量図・謄本・地図・公図・売地資料xls・物件概要PDF）、案件チェックシート、ルート表、スクリーニング画像のみ。 | D26: 開く
A27: 1201_茨城県笠間市福田961-12他（ソーラークリエート） | B27: 0 | C27: 回答書なし。物件概要PDF1件、案件チェックシート、スクリーニング画像のみ。 | D27: 開く
A28: 1187_茨城県土浦市大畑577-1（ソーラークリエート） | B28: 0 | C28: 回答書なし。03_接続検討申込書（申込書xlsx・様式5の3〜5の7 PDF）=申込側書類のみ。他に物件概要PDF、チェックシート、ルート表、スクリーニング画像。 | D28: 開く
A29: 1208_静岡県浜松市浜名区三ヶ日町都筑（ソーラークリエート） | B29: 0 | C29: 回答書なし。物件概要PDF、案件チェックシート、ルート表、スクリーニング画像のみ。 | D29: 開く
A30: 1214_千葉県山武郡柴山町山中字大山（ソーラークリエート） | B30: 0 | C30: 回答書なし。先方受領資料（位置図・物件概要PDF『連系鉄塔200m以内』・28.xlsx・地番図）、案件チェックシート、ルート表、スクリーニング画像のみ。 | D30: 開く
A31: 1210_京都府舞鶴市字倉谷小字縄1350番9（ソーラークリエート） | B31: 0 | C31: 回答書なし。フォルダ内は先方受領の物件概要PDF(77kV1.7km記載)・自社スクリーニング(案件チェックシートxlsx、ハザード等スクリーンショットpng)のみ。接続検討未申込とみられる。 | D31: 開く
A32: 1205_栃木県鹿沼市深津字上台原2523-4（ソーラークリエート） | B32: 0 | C32: 回答書なし。先方受領資料(物件概要PDF、道路台帳、地番図、住宅地図、登記簿謄本PDF、連系変電所までの距離jpg)と自社スクリーニング(案件チェックシート、スクリーンショット)のみ。 | D32: 開く
A33: 1279_島根県出雲市多伎町久村137-18（須山木材） | B33: 1 | D33: 開く
A34: 1135_北海道夕張郡由仁町川端1178番、1180番（葵アセットマネジメント株式会社） | B34: 1 | D34: 開く
A35: 1343_佐賀県鹿島市納富分1909 | B35: 0 | C35: 回答書なし。03.接続検討申込に九州電力送配電向け接続検討申込書xlsx・配置図・単線結線図・PCS/PAS/リレー/蓄電池/変圧器仕様書・工事工程表等の申込書類一式のみ（申込準備/申込済で回答未着とみられる）。他に現地写真jpg、案件チェックシート、スクリーニングpng。 | D35: 開く
A36: 0794_三重県名張市瀬古口（PX） | B36: 2 | D36: 開く
A37: 1244_高砂市阿弥陀町北池190 | B37: 1 | D37: 開く
A38: 1316_北海道虻田郡喜茂別町(ソーラークリエート) | B38: 1 | D38: 開く
A39: 1185_静岡県掛川市淡陽18番1（ティーライフ） | B39: 1 | D39: 開く
A40: 1129_崇徳学園入野グラウンド(大柿産業) | B40: 2 | D40: 開く
A41: 1167_長野県佐久市安原（本久） | B41: 0 | C41: 回答書なし。接続検討申込書(中部_高圧, 2026-02-23作成)・PCS出力制限・出力制御装置仕様確認依頼書、申込時提出資料(機器仕様書等)、登記簿PDF、自社スクリーニング画像/チェックシート/ルート表のみ（申込準備段階） | D41: 開く
A42: 1092_三重県伊勢市特高 | B42: 2 | D42: 開く
A43: 1113_茨城県行方市浜1985-1,1985-3,1986-3（合同会社高塚） | B43: 1 | D43: 開く
A44: 1136_兵庫県高砂市中筋3丁目780番（藤栄建設） | B44: 1 | D44: 開く
A45: 1147_愛知県岡崎市板田町東流石（中部産業） | B45: 2 | D45: 開く
A46: 0876_埼玉県本庄市児玉町入浅見字東日延766（アスソラ） | B46: 3 | D46: 開く
A47: 0919_山口県周防大島町久賀2086-4（エクスパワー） | B47: 1 | D47: 開く
A48: PXさまから共有いただいたパッケージ | B48: 0 | C48: 案件フォルダではなくPXの標準機器パッケージ資料（Mega Power/PCS/変圧器/監視制御/出力抑制ユニットTSO個別認定証明書(各一般送配電の出力制御機能付PCS協議完了通知)/系統連系協議資料・接続検討申込書雛形/消防/類焼試験/広域認定/ロジ/O&M）。接続検討等の回答書なし | D48: 開く
A49: 0916_島根県浜田市宇野町1819-1他3筆（エクスパワー） | B49: 4 | D49: 開く
A50: 006_須賀川市江持字喜太夫70（福島県）_高圧蓄電所 | B50: 1 | C50: 状態: 進行中。 回答一覧No48 | D50: 開く
A51: 008_三春町字樋ノ口144-1（福島県）_高圧蓄電所 | B51: 1 | C51: 状態: 進行中。系統連系承諾書・工事負担金請求書が別にあるが、今回は接続検討回答書のみ対象 回答一覧No49 | D51: 開く
A52: 032_川崎町大字川内字七曲山77（宮城県）_高圧蓄電所 | B52: 1 | C52: 状態: 進行中。 回答一覧No52 | D52: 開く
A53: 040_新地町駒ケ嶺字桜下51-1（福島県）_高圧蓄電所 | B53: 2 | C53: 状態: 進行中。 回答一覧No54,55 | D53: 開く
A54: 071_喜多方市松山町鳥見山字中村道下堰西5045-1（福島県）_高圧蓄電所 | B54: 2 | C54: 状態: 進行中。 回答一覧No74,75 | D54: 開く
A55: 072_福島市小倉寺字中大巻5-1他（福島県）_高圧蓄電所 | B55: 2 | C55: 状態: 進行中。 回答一覧No76,77 | D55: 開く
A56: 083_八戸市大字白銀町字佐部長根24-169（青森県）_高圧蓄電所 | B56: 1 | C56: 状態: 進行中。 回答一覧No82 | D56: 開く
A57: 093_八戸市大字櫛引字烏館場1-1（青森県）_高圧蓄電所 | B57: 1 | C57: 状態: 進行中。系統連系承諾書が別にあるが、今回は接続検討回答書のみ対象 回答一覧No88 | D57: 開く
A58: 116_笠岡市今立2509-1（岡山県）_高圧蓄電所 | B58: 1 | C58: 状態: 進行中。契約申込みの回答（承諾）のPDFが別にあるが、今回は接続検討回答書のみ対象 回答一覧No99 | D58: 開く
A59: 130_和気町藤野1263（岡山県）_高圧蓄電所 | B59: 1 | C59: 状態: 進行中。 回答一覧No107 | D59: 開く
A60: 140_大田市大田町大田ｲ1609-1（島根県）_高圧蓄電所 | B60: 1 | C60: 状態: 進行中。 回答一覧No115 | D60: 開く
A61: 147_福山市引野町4968他（広島県）_高圧蓄電所 | B61: 1 | C61: 状態: 進行中。 回答一覧No120 | D61: 開く
... A261: 【中止】/X2608_大館市山田字下柏木岱14-1（秋田県）_高圧蓄電所 | B261: 0 | C261: 状態: 中止。03_電力配下に接続検討回答書・再接続検討回答書なし | D261: 開く
